Workbook

Sheet RELATORIO CONTROLADORIA
B1: COLABORADOR : | C1: Equipe | D1: RET. COM DESCONTO | E1: IND. 4% DO TOTAL | F1: RET. | G1: RETIRADA | H1: INSTALAÇÃO | I1: MANUTENÇÃO | J1: AT. | K1: P.V | L1: D.A. | M1: ATESTADO | N1: D.U | O1: D.C. | P1: MED. | Q1: valor | R1: Resultado
A2: Ind. Retrabalho | B2: COLABORADOR : | D2: 74.2 | E2: 219.8 | F2: 244 | G2: 49 | H2: 1206 | I2: 4006 | J2: 5495 | K2: 5420.8 | L2: 0 | M2: 0 | N2: 1262 | O2: 1460 | P2: 3.7 | Q2: 18499
A3: 0.0417 | B3: ALEFF PEREIRA SOARES | C3: INSTALAÇÃO | D3: 0.2 | E3: 4.8 | F3: 5 | H3: 42 | I3: 72 | J3: 120 | K3: 119.8 | N3: 24 | O3: 24 | P3: 4.99 | Q3: 594 | R3: Concessão
A4: 0.0303 | B4: ALLYSSON DA SILVA MARINHO | C4: MISTO | D4: 0 | E4: 3.96 | F4: 3 | H4: 20 | I4: 75 | J4: 99 | K4: 99 | N4: 24 | O4: 22 | P4: 4.5 | Q4: 0 | R4: -
A5: 0.0429 | B5: ANDRE SILVA LOIOLA | C5: MISTO | D5: 0.2 | E5: 2.8 | F5: 3 | H5: 3 | I5: 63 | J5: 70 | K5: 69.8 | N5: 24 | O5: 25 | P5: 2.79 | Q5: 0 | R5: -
A6: 0 | B6: ANTONIO CARLOS BARBOSA DE SOUSA | C6: JEBnet | D6: 0 | E6: 0.08 | H6: 2 | J6: 2 | K6: 2 | O6: 21 | P6: 0.1 | Q6: - | R6: -
A7: 0.0734 | B7: ANTONIO CARLOS FERREIRA DA SILVA | C7: INSTALAÇÃO | D7: 3.6 | E7: 4.36 | F7: 8 | G7: 2 | H7: 33 | I7: 69 | J7: 109 | K7: 105.4 | N7: 23 | O7: 23 | P7: 4.58 | Q7: 353.44 | R7: Premio
A8: 0.0761 | B8: ANTONIO EDUARDO TEIXEIRA CAMELO | C8: MISTO | D8: 3.3 | E8: 3.68 | F8: 7 | H8: 18 | I8: 70 | J8: 92 | K8: 88.7 | N8: 23 | O8: 22 | P8: 4.03 | Q8: 0 | R8: -
A9: 0 | B9: ANTONIO EUNARDES SOUSA BRAGA | C9: JEBnet | D9: 0 | E9: 2.76 | H9: 1 | I9: 68 | J9: 69 | K9: 69 | O9: 23 | P9: 3 | Q9: - | R9: -
A10: 0.03 | B10: ANTONIO FELIPE CASTRO DE OLIVEIRA | C10: MISTO COND. | D10: 0 | E10: 4 | F10: 3 | G10: 5 | H10: 25 | I10: 67 | J10: 100 | K10: 100 | N10: 23 | O10: 23 | P10: 4.35 | Q10: 678 | R10: Premio
A11: 0.092 | B11: ANTONIO RAFAEL ALEXANDRE DE SOUSA | C11: MISTO | D11: 4.5 | E11: 3.48 | F11: 8 | H11: 17 | I11: 66 | J11: 87 | K11: 82.5 | N11: 23 | O11: 21 | P11: 3.93 | Q11: 0 | R11: Premio não atingido
A12: 0 | B12: ANTONIO TIAGO AMANCIO DA SILVA | C12: INSTALAÇÃO | D12: 0 | E12: 0.68 | G12: 4 | H12: 1 | I12: 12 | J12: 17 | K12: 17 | O12: 24 | P12: 0.71 | Q12: 51 | R12: Premio
A13: 0.0088 | B13: ANTONIO WILSON SOARES DE SOUSA | C13: JEBnet | D13: 0 | E13: 4.52 | F13: 1 | H13: 44 | I13: 68 | J13: 113 | K13: 113 | O13: 24 | P13: 4.71 | Q13: - | R13: -
A14: 0.0588 | B14: ARLISON DA SILVA PEREIRA | C14: MISTO | D14: 1.6 | E14: 3.4 | F14: 5 | H14: 8 | I14: 71 | J14: 85 | K14: 83.4 | N14: 24 | O14: 23 | P14: 3.63 | Q14: 0 | R14: Premio não atingido
A15: 0.0606 | B15: BRENDHOWN CESAR VIANA SILVA FALCAO | C15: MISTO COND. | D15: 2 | E15: 3.96 | F15: 6 | G15: 2 | H15: 18 | I15: 75 | J15: 99 | K15: 97 | N15: 24 | O15: 23 | P15: 4.22 | Q15: 665.84 | R15: Premio
A16: 0.0843 | B16: BRUNO MATIAS DA SILVA | C16: MISTO COND. | D16: 3.7 | E16: 3.32 | F16: 7 | H16: 22 | I16: 57 | J16: 83 | K16: 79.3 | N16: 24 | O16: 22 | P16: 3.61 | Q16: 609.28 | R16: Premio
A17: 0.2222 | B17: BRUNO MOREIRA MONTEIRO | C17: MISTO | D17: 3.3 | E17: 0.72 | F17: 4 | H17: 8 | I17: 9 | J17: 18 | K17: 14.7 | N17: 23 | O17: 25 | P17: 0.59 | Q17: 0 | R17: Premio não atingido
A18: 0.0923 | B18: CAIO VICTOR MONTEIRO DE OLIVEIRA | C18: MISTO | D18: 3.4 | E18: 2.6 | F18: 6 | H18: 11 | I18: 46 | J18: 65 | K18: 61.6 | N18: 23 | O18: 18 | P18: 3.42 | Q18: 0 | R18: Premio não atingido
A19: 0.0971 | B19: CARLOS HENRIQUE LINO SILVA | C19: MISTO COND. | D19: 5.9 | E19: 4.12 | F19: 10 | H19: 27 | I19: 67 | J19: 103 | K19: 97.1 | N19: 24 | O19: 22 | P19: 4.41 | Q19: 680.48 | R19: Premio
A20: 0.075 | B20: CLAUDIANO CICINATO DA SILVA | C20: INSTALAÇÃO | D20: 2.8 | E20: 3.2 | F20: 6 | G20: 3 | H20: 27 | I20: 46 | J20: 80 | K20: 77.2 | N20: 24 | O20: 22 | P20: 3.51 | Q20: 231.6 | R20: Premio
A21: 0.0133 | B21: DANILO OLIVEIRA DE SOUSA | C21: MISTO | D21: 0 | E21: 3 | F21: 1 | H21: 6 | I21: 64 | J21: 75 | K21: 75 | O21: 24 | P21: 3.13 | Q21: 0 | R21: Premio não atingido
A22: 0.0784 | B22: DAVI MEDINA DE ARAUJO | C22: INSTALAÇÃO | D22: 3.9 | E22: 4.08 | F22: 8 | H22: 34 | I22: 66 | J22: 102 | K22: 98.1 | N22: 23 | O22: 23 | P22: 4.26 | Q22: 324.32 | R22: Premio
A23: 0.08 | B23: DIEGO DA SILVA ASSUNCAO | C23: MISTO | D23: 2 | E23: 2 | F23: 4 | H23: 7 | I23: 41 | J23: 50 | K23: 48 | O23: 23 | P23: 2.09 | Q23: 0 | R23: Premio não atingido
A24: 0.0313 | B24: EDUARDO SANTOS DA SILVA | C24: GIGA | D24: 0 | E24: 1.28 | F24: 1 | H24: 5 | I24: 27 | J24: 32 | K24: 32 | O24: 23 | P24: 1.39 | Q24: 270.3 | R24: Premio
A25: 0.0381 | B25: ELISSON PEREIRA COUTINHO NOVAIS | C25: MISTO | D25: 0 | E25: 4.2 | F25: 4 | H25: 14 | I25: 87 | J25: 105 | K25: 105 | N25: 23 | O25: 22 | P25: 4.77 | Q25: 285 | R25: Concessão
A26: 0.0538 | B26: ELIZEU DA SILVA FERREIRA | C26: INSTALAÇÃO | D26: 1.3 | E26: 3.72 | F26: 5 | H26: 15 | I26: 74 | J26: 93 | K26: 91.7 | N26: 23 | O26: 22 | P26: 4.17 | Q26: 314.88 | R26: Premio
A27: 0.0571 | B27: EVERLAN DA PENHA TOME | C27: MISTO | D27: 1.2 | E27: 2.8 | F27: 4 | H27: 7 | I27: 60 | J27: 70 | K27: 68.8 | N27: 23 | O27: 21 | P27: 3.28 | Q27: 0 | R27: Premio não atingido
A28: 0.0167 | B28: FELIPE MARTINS DAMASCENO | C28: INSTALAÇÃO | D28: 0 | E28: 2.4 | F28: 1 | H28: 16 | I28: 43 | J28: 60 | K28: 60 | N28: 23 | O28: 23 | P28: 2.61 | Q28: 180 | R28: Premio
A29: 0.0455 | B29: FRANCISCO CARLOS EUGENIO DO NASCIMENTO | C29: MISTO | D29: 0.2 | E29: 1.76 | F29: 2 | H29: 7 | I29: 36 | J29: 44 | K29: 43.8 | N29: 16 | O29: 11 | P29: 3.98 | Q29: 0 | R29: -
A30: 0.0211 | B30: FRANCISCO DAS CHAGAS E SILVA ROCHA | C30: INSTALAÇÃO | D30: 0 | E30: 3.8 | F30: 2 | G30: 2 | H30: 13 | I30: 77 | J30: 95 | K30: 95 | N30: 24 | O30: 23 | P30: 4.13 | Q30: 312 | R30: Premio
A31: 0.0756 | B31: FRANCISCO DIEGO ALVES FERREIRA | C31: INSTALAÇÃO | D31: 4.2 | E31: 4.76 | F31: 9 | H31: 52 | I31: 58 | J31: 119 | K31: 114.8 | N31: 24 | O31: 22 | P31: 5.22 | Q31: 628.56 | R31: Premio
A32: 0.0323 | B32: FRANCISCO FELIPE DE LIMA ALVES | C32: MISTO | D32: 0 | E32: 1.24 | F32: 1 | H32: 4 | I32: 27 | J32: 31 | K32: 31 | N32: 6 | O32: 6 | P32: 5.17 | Q32: - | R32: Premio
A33: 0.0361 | B33: FRANCISCO HELIO MARINHO CUNHA NETO | C33: INSTALAÇÃO | D33: 0 | E33: 3.32 | F33: 3 | G33: 3 | H33: 21 | I33: 57 | J33: 83 | K33: 83 | N33: 23 | O33: 16 | P33: 5.19 | Q33: 618 | R33: Premio
A34: 0.1013 | B34: FRANCISCO JHONATA DA COSTA | C34: MISTO | D34: 4.8 | E34: 3.16 | F34: 8 | H34: 9 | I34: 64 | J34: 79 | K34: 74.2 | N34: 24 | O34: 18 | P34: 4.12 | Q34: 0 | R34: Premio não atingido
A35: 0.1045 | B35: FRANCISCO LAERTE PEREIRA RODRIGUES | C35: MISTO COND. | D35: 4.3 | E35: 2.68 | F35: 7 | G35: 1 | H35: 21 | I35: 39 | J35: 67 | K35: 62.7 | N35: 23 | O35: 21 | P35: 2.98 | Q35: 0 | R35: Premio não atingido
A36: 0.0641 | B36: FRANCISCO MATHEUS PEREIRA MENDES | C36: INSTALAÇÃO | D36: 1.9 | E36: 3.12 | F36: 5 | H36: 18 | I36: 53 | J36: 78 | K36: 76.1 | N36: 23 | O36: 22 | P36: 3.46 | Q36: 228.36 | R36: Premio
A37: 0.043 | B37: FRANCISCO TIAGO PINHEIRO | C37: MISTO | D37: 0.3 | E37: 3.72 | F37: 4 | H37: 10 | I37: 80 | J37: 93 | K37: 92.7 | N37: 23 | O37: 20 | P37: 4.64 | Q37: 0 | R37: Premio não atingido
A38: 0.0179 | B38: GABRIEL MARTINS MUNIZ | C38: INSTALAÇÃO | D38: 0 | E38: 6.72 | F38: 3 | G38: 4 | H38: 99 | I38: 62 | J38: 168 | K38: 168 | N38: 24 | O38: 24 | P38: 7 | Q38: 1200 | R38: -
A39: 0.0081 | B39: GEILSON DA SILVA MOURA | C39: MISTO COND. | D39: 0 | E39: 4.92 | F39: 1 | G39: 2 | H39: 42 | I39: 76 | J39: 123 | K39: 123 | N39: 23 | O39: 24 | P39: 5.13 | Q39: 990 | R39: Premio
A40: 0.0157 | B40: GILVAN ASSUNCAO SILVA | C40: MISTO | D40: 0 | E40: 5.08 | F40: 2 | H40: 10 | I40: 115 | J40: 127 | K40: 127 | N40: 21 | O40: 17 | P40: 7.47 | Q40: 964 | R40: -
A41: 0 | B41: GLEISON VALENTIM ARAUJO | C41: MISTO COND. | D41: 0 | E41: 0.12 | H41: 1 | I41: 2 | J41: 3 | K41: 3 | N41: 1 | O41: 1 | P41: 3 | Q41: - | R41: Premio
A42: 0.0496 | B42: GUTEMBERGUE OLIVEIRA | C42: MISTO | D42: 1.2 | E42: 4.84 | F42: 6 | G42: 2 | H42: 14 | I42: 100 | J42: 121 | K42: 119.8 | N42: 23 | O42: 23 | P42: 5.21 | Q42: 319.36 | R42: Premio
A43: 0.0242 | B43: HALLEF GUILHERME LIMA CLEMENTE SILVA | C43: MISTO COND. | D43: 0 | E43: 4.96 | F43: 3 | G43: 2 | H43: 35 | I43: 83 | J43: 124 | K43: 124 | N43: 24 | O43: 22 | P43: 5.64 | Q43: 1224 | R43: Premio
A44: 0.1429 | B44: IGOR BRUNO DE SOUZA CASTRO | C44: MISTO | D44: 0.7 | E44: 0.28 | F44: 1 | H44: 1 | I44: 6 | J44: 7 | K44: 6.3 | N44: 24 | O44: 18 | P44: 0.35 | Q44: 0 | R44: -
A45: 0.0286 | B45: ISRAEL OLIVEIRA MORAIS | C45: MISTO | D45: 0 | E45: 4.2 | F45: 3 | H45: 11 | I45: 88 | J45: 105 | K45: 105 | N45: 23 | O45: 20 | P45: 5.25 | Q45: 320 | R45: Premio
A46: 0 | B46: ITALO BRUSS DE SOUZA CASTRO | C46: MISTO | D46: 0 | E46: 0.12 | I46: 3 | J46: 3 | K46: 3 | N46: 24 | O46: 26 | P46: 0.12 | Q46: 0 | R46: Premio não atingido
A47: 0.0321 | B47: ITALO XAVIER DA SILVA | C47: MISTO | D47: 0 | E47: 6.24 | F47: 5 | H47: 17 | I47: 130 | J47: 156 | K47: 156 | N47: 23 | O47: 22 | P47: 7.09 | Q47: 916 | R47: Premio
A48: 0 | B48: JOAO ADAILSON GOMES ALBANO | C48: JEBnet | D48: 0 | E48: 0.24 | I48: 6 | J48: 6 | K48: 6 | O48: 22 | P48: 0.27 | Q48: - | R48: -
A49: 0.0105 | B49: JOAO BATISTA COELHO GOMES | C49: JEBnet | D49: 0 | E49: 3.8 | F49: 1 | H49: 21 | I49: 72 | J49: 95 | K49: 95 | O49: 25 | P49: 3.8 | Q49: - | R49: -
A50: 0.0588 | B50: JOAO PAULO DA SILVA LIMA | C50: INSTALAÇÃO | D50: 1.6 | E50: 3.4 | F50: 5 | H50: 35 | I50: 48 | J50: 85 | K50: 83.4 | N50: 23 | O50: 22 | P50: 3.79 | Q50: 250.2 | R50: Premio
A51: 0.0469 | B51: JOAO PAULO GOUVEIA DA SILVA | C51: INSTALAÇÃO | D51: 0.4 | E51: 2.56 | F51: 3 | H51: 9 | I51: 52 | J51: 64 | K51: 63.6 | N51: 21 | O51: 20 | P51: 3.18 | Q51: 190.68 | R51: -
A52: 0 | B52: JONATHAN BRENO NOBRE DA SILVA | C52: INSTALAÇÃO | D52: 0 | E52: 0.68 | H52: 4 | I52: 13 | J52: 17 | K52: 17 | N52: 23 | O52: 9 | P52: 1.89 | Q52: 51 | R52: -
A53: 0.0467 | B53: JOSE DIOGO SOUSA ALVES | C53: - | D53: 0.7 | E53: 4.28 | F53: 5 | H53: 23 | I53: 79 | J53: 107 | K53: 106.3 | O53: 25 | P53: 4.25 | Q53: - | R53: -
A54: 0.0515 | B54: JOSE EDNARDO DA SILVA DE LIMA | C54: INSTALAÇÃO | D54: 1.1 | E54: 3.88 | F54: 5 | H54: 25 | I54: 66 | J54: 97 | K54: 95.9 | N54: 24 | O54: 23 | P54: 4.17 | Q54: 590.8 | R54: Concessão
A55: 0.027 | B55: JOSE HENRIQUE PEREIRA SOUSA | C55: MISTO | D55: 0 | E55: 2.96 | F55: 2 | H55: 15 | I55: 56 | J55: 74 | K55: 74 | N55: 23 | O55: 22 | P55: 3.36 | Q55: 0 | R55: Premio não atingido
A56: 0.0105 | B56: JOSE ILDEVAM SOUSA DO NASCIMENTO | C56: MISTO | D56: 0 | E56: 3.8 | F56: 1 | H56: 3 | I56: 88 | J56: 95 | K56: 95 | N56: 24 | O56: 21 | P56: 4.52 | Q56: 0 | R56: Premio não atingido
A57: 0.0597 | B57: JOSE WELLITON VIEIRA FELINTO | C57: INSTALAÇÃO | D57: 1.3 | E57: 2.68 | F57: 4 | H57: 10 | I57: 56 | J57: 67 | K57: 65.7 | N57: 23 | O57: 19 | P57: 3.46 | Q57: 197.04 | R57: Premio
A58: 0 | B58: KELTON CLEMENTE DOS SANTOS | C58: MISTO | D58: 0 | E58: 2.4 | H58: 20 | I58: 39 | J58: 60 | K58: 60 | N58: 23 | O58: 19 | P58: 3.16 | Q58: 0 | R58: Premio não atingido
A59: 0 | B59: KELVER EDUARDO GOMES SOBRAL | C59: INSTALAÇÃO | D59: 0 | E59: 1.24 | G59: 11 | H59: 6 | I59: 14 | J59: 31 | K59: 31 | O59: 23 | P59: 1.35 | Q59: 93 | R59: Premio
A60: 0.0703 | B60: LUCAS SOUZA SILVA | C60: INSTALAÇÃO | D60: 3.9 | E60: 5.12 | F60: 9 | H60: 16 | I60: 105 | J60: 128 | K60: 124.1 | N60: 24 | O60: 22 | P60: 5.64 | Q60: 684.72 | R60: Premio
A61: 0.0206 | B61: LUCIEUDO BANDEIRA ALVES FILHO | C61: MISTO | D61: 0 | E61: 3.88 | F61: 2 | H61: 35 | I61: 60 | J61: 97 | K61: 97 | N61: 24 | O61: 21 | P61: 4.62 | Q61: 0 | R61: Premio não atingido
A62: 0.0408 | B62: LUIZ CARLOS ALVES LOPES | C62: MISTO | D62: 0.1 | E62: 3.92 | F62: 4 | H62: 14 | I62: 79 | J62: 98 | K62: 97.9 | N62: 24 | O62: 21 | P62: 4.66 | Q62: 0 | R62: Premio não atingido
A63: 0.0485 | B63: LUIZ CARLOS MACHADO MACIEL | C63: MISTO | D63: 0.9 | E63: 4.12 | F63: 5 | H63: 4 | I63: 90 | J63: 103 | K63: 102.1 | N63: 23 | O63: 22 | P63: 4.64 | Q63: 0 | R63: Premio não atingido
A64: 0.036 | B64: LUIZ OCTAVIO ALMEIDA DA SILVA | C64: INSTALAÇÃO | D64: 0 | E64: 4.44 | F64: 4 | H64: 44 | I64: 62 | J64: 111 | K64: 111 | N64: 24 | O64: 24 | P64: 4.63 | Q64: 360 | R64: Premio
A65: 0.0122 | B65: MAISSON FERREIRA DA SILVA | C65: MISTO | D65: 0 | E65: 3.28 | F65: 1 | G65: 1 | H65: 9 | I65: 67 | J65: 82 | K65: 82 | N65: 23 | O65: 23 | P65: 3.57 | Q65: 0 | R65: Premio não atingido
A66: 0.0676 | B66: MARCOS AURELIO DE SOUSA OLIVEIRA | C66: MISTO | D66: 2 | E66: 2.96 | F66: 5 | H66: 23 | I66: 47 | J66: 74 | K66: 72 | N66: 24 | O66: 21 | P66: 3.43 | Q66: 0 | R66: Premio não atingido
A67: 0.0413 | B67: MARCOS PEREIRA CARVALHO FILHO | C67: MISTO | D67: 0.2 | E67: 4.84 | F67: 5 | H67: 20 | I67: 95 | J67: 121 | K67: 120.8 | N67: 24 | O67: 22 | P67: 5.49 | Q67: 343.36 | R67: Premio
A68: 0 | B68: MICHEL PLATINI CORREIA MORAIS | C68: JEBnet | D68: 0 | E68: 0.08 | I68: 2 | J68: 2 | K68: 2 | O68: 20 | P68: 0.1 | Q68: - | R68: -
A69: 0 | B69: MILTON FERREIRA DE CASTRO | C69: JEBnet | D69: 0 | E69: 2.8 | H69: 7 | I69: 63 | J69: 70 | K69: 70 | O69: 26 | P69: 2.69 | Q69: - | R69: -
A70: 0.0282 | B70: NATAN DOS SANTOS PEREIRA | C70: MISTO | D70: 0 | E70: 2.84 | F70: 2 | H70: 9 | I70: 59 | J70: 71 | K70: 71 | N70: 23 | O70: 21 | P70: 3.38 | Q70: 0 | R70: Premio não atingido
A71: 0.0517 | B71: PAULO ROBERTO ARAUJO GALVAO | C71: MISTO COND. | D71: 1.4 | E71: 4.64 | F71: 6 | G71: 5 | H71: 38 | I71: 69 | J71: 116 | K71: 114.6 | N71: 24 | O71: 23 | P71: 4.98 | Q71: 966.84 | R71: Premio
A72: 0.0667 | B72: ROMARIO NOBRE DE MELO | C72: MISTO | D72: 2.4 | E72: 3.6 | F72: 6 | H72: 15 | I72: 71 | J72: 90 | K72: 87.6 | N72: 24 | O72: 23 | P72: 3.81 | Q72: 0 | R72: Premio não atingido
A73: 0.0097 | B73: SAMUEL DOS SANTOS | C73: JEBnet | D73: 0 | E73: 4.12 | F73: 1 | H73: 42 | I73: 60 | J73: 103 | K73: 103 | O73: 23 | P73: 4.48 | Q73: - | R73: -
A74: 0 | B74: SERGIO MOURA PINTO | C74: JEBnet | D74: 0 | E74: 2.76 | H74: 5 | I74: 64 | J74: 69 | K74: 69 | O74: 23 | P74: 3 | Q74: - | R74: -
A75: 0 | B75: TARCIO FRANCISCO DA SILVA | C75: INSTALAÇÃO | D75: 0 | E75: 1.56 | G75: 11 | H75: 10 | I75: 18 | J75: 39 | K75: 39 | O75: 24 | P75: 1.63 | Q75: 117 | R75: Premio
A76: 0.0313 | B76: THIAGO CASTRO DO NASCIMENTO | C76: MISTO | D76: 0 | E76: 1.28 | F76: 1 | H76: 10 | I76: 21 | J76: 32 | K76: 32 | N76: 8 | O76: 7 | P76: 4.57 | Q76: 0 | R76: Premio não atingido
A77: 0.0112 | B77: THOMAS JEFFERSON ARAUJO PEREIRA | C77: GIGA | D77: 0 | E77: 3.56 | F77: 1 | H77: 13 | I77: 73 | J77: 89 | K77: 89 | O77: 21 | P77: 4.24 | Q77: 138.94 | R77: Premio
A78: 0.0426 | B78: VALDERILO FERREIRA LIMA JUNIOR | C78: INSTALAÇÃO | D78: 0.2 | E78: 3.76 | F78: 4 | G78: 2 | H78: 32 | I78: 56 | J78: 94 | K78: 93.8 | N78: 24 | O78: 21 | P78: 4.46 | Q78: 339.04 | R78: Premio
A79: 0.0093 | B79: VANIZIO PEREIRA AZEVEDO DO NASCIMENTO | C79: MISTO COND. | D79: 0 | E79: 4.28 | F79: 1 | H79: 31 | I79: 70 | J79: 107 | K79: 107 | N79: 23 | O79: 22 | P79: 4.86 | Q79: 948 | R79: -
A80: 0.0222 | B80: VINICIUS SILVA LEARTE | C80: INSTALAÇÃO | D80: 0 | E80: 3.6 | F80: 2 | H80: 12 | I80: 70 | J80: 90 | K80: 90 | N80: 24 | O80: 24 | P80: 3.75 | Q80: 270 | R80: Premio
A81: 0.0426 | B81: WELLISON FERREIRA LIMA | C81: MISTO | D81: 0.2 | E81: 3.76 | F81: 4 | G81: 1 | H81: 22 | I81: 67 | J81: 94 | K81: 93.8 | N81: 23 | O81: 22 | P81: 4.26 | Q81: 0 | R81: Premio não atingido
A82: 0.0882 | B82: WESLLEY ALVES UCHOA | C82: MISTO | D82: 3.3 | E82: 2.72 | F82: 6 | H82: 3 | I82: 59 | J82: 68 | K82: 64.7 | N82: 24 | O82: 21 | P82: 3.08 | Q82: 0 | R82: Premio não atingido
A85: Auxiliar | B85: Auxiliar | C85: Tecnico | D85: FALTA | E85: D.A. | F85: ATESTADO | G85: D.U | H85: D.C. | I85: Valor
B86: ANTONIO MARCOS LIMA DA SILVA | C86: VALDERILO FERREIRA LIMA JUNIOR | E86: 4 | G86: 22 | H86: 18 | I86: 101.71
B87: MATEUS GABRIEL ROCHA | C87: BRENDHOWN CESAR VIANA SILVA FALCAO | G87: 22 | H87: 22 | I87: 199.75
B88: JOSE AMAURY BORGES FILHO | C88: ANTONIO TIAGO AMANCIO DA SILVA | G88: 22 | H88: 22 | I88: 51
B89: IRINETO FERREIRA DE AGUIAR | C89: ANTONIO FELIPE CASTRO DE OLIVEIRA | G89: 22 | H89: 22 | I89: 203.4
B90: CLAYLSON MORAES DOS SANTOS | C90: VANIZIO PEREIRA AZEVEDO | G90: 22 | H90: 22 | I90: 284.4
B91: ISMAEL JULIÃO SOARES | C91: HALLEF GUILHERME LIMA CLEMENTE SILVA | G91: 22 | H91: 22 | I91: 367.2
G92: 22 | H92: 22 | I92: -
B93: ELEEONAI VIANA DA SILVA | C93: CARLOS HENRIQUE LINO SILVA | G93: 22 | H93: 22 | I93: 204.14
B94: DAVID DE SOUSA SILVA | C94: GEILSON DA SILVA MOURA | G94: 22 | H94: 22 | I94: 297
B96: SAMUEL RIBEIRO FELISMINO | C96: BRUNO MATIAS DA SILVA | F96: 2 | G96: 22 | H96: 20 | I96: 182.78
B97: ANTONIO FELIPE SOARES SILVA TAVARES | C97: PAULO ROBERTO ARAUJO GALVAO | G97: 22 | H97: 22 | I97: 290.05
B98: IGOR DE GOES GOMES | C98: THOMAS JEFFERSON ARAUJO PEREIRA | G98: 22 | H98: 22 | I98: 83.1
D100: FALTA | E100: D.A. | F100: ATESTADO | G100: D.U | H100: D.C. | I100: Valor
A101: EQUIPE INTERNA | B101: ALAN FEITOSA DE SOUTO | C101: COORDENADOR | G101: 22 | H101: 22 | I101: 260 | J101: propocional 20 dias
B102: JOSE MARIA DA COSTA LEONARDO | C102: SUPERVISOR | G102: 22 | H102: 22 | I102: 260
B103: MAILSON FRANCISCO PEREIRA | C103: SUPERVISOR | G103: 22 | H103: 22 | I103: 280
B104: WILLIAM ADRIANO DANTAS | C104: SUPERVISOR | E104: 1 | G104: 22 | H104: 21 | I104: 260
...

Sheet FDT
A1: WA.ME/55 | B1: 959 | D1: 68 | E1: WA.ME/55 | F1: 959
A2: CONTATO WPP | B2: WHATSAPP | D2: TECNICO | E2: CONTATO WPP | F2: WHATSAPP | H2: CPF
C3: #N/A | G3: =C3 -> #N/A | H3: =IFERROR(VLOOKUP(D3,CPF!A:D,4,0),"NAO ENCONTRADO") -> NAO ENCONTRADO
B4: =CONCATENATE($A$1,A4) -> WA.ME/55 | C4: ALAN SOUTO | D4: ALAN FEITOSA DE SOUTO | F4: =CONCATENATE($E$1,E4) -> WA.ME/55 | G4: =C4 -> ALAN SOUTO | H4: =IFERROR(VLOOKUP(D4,CPF!A:D,4,0),"NAO ENCONTRADO") -> 646.525.643-68
B5: =CONCATENATE($A$1,A5) -> WA.ME/55 | C5: ALAN SOUTO | D5: ANTONIO TIAGO AMANCIO DA SILVA | F5: =CONCATENATE($E$1,E5) -> WA.ME/55 | G5: =C5 -> ALAN SOUTO | H5: =IFERROR(VLOOKUP(D5,CPF!A:D,4,0),"NAO ENCONTRADO") -> NAO ENCONTRADO
B6: =CONCATENATE($A$1,A6) -> WA.ME/55 | C6: ALAN SOUTO | D6: FRANCISCO LAERTE PEREIRA RODRIGUES | F6: =CONCATENATE($E$1,E6) -> WA.ME/55 | G6: =C6 -> ALAN SOUTO | H6: =IFERROR(VLOOKUP(D6,CPF!A:D,4,0),"NAO ENCONTRADO") -> NAO ENCONTRADO
B7: =CONCATENATE($A$1,A7) -> WA.ME/55 | C7: ALAN SOUTO | D7: JOAO PAULO DA SILVA LIMA | F7: =CONCATENATE($E$1,E7) -> WA.ME/55 | G7: =C7 -> ALAN SOUTO | H7: =IFERROR(VLOOKUP(D7,CPF!A:D,4,0),"NAO ENCONTRADO") -> 001.058.623-71
B8: =CONCATENATE($A$1,A8) -> WA.ME/55 | C8: ALAN SOUTO | D8: JOSE MARIA DA COSTA LEONARDO | F8: =CONCATENATE($E$1,E8) -> WA.ME/55 | G8: =C8 -> ALAN SOUTO | H8: =IFERROR(VLOOKUP(D8,CPF!A:D,4,0),"NAO ENCONTRADO") -> 734.146.113-68
B9: =CONCATENATE($A$1,A9) -> WA.ME/55 | C9: ALAN SOUTO | D9: KELTON CLEMENTE DOS SANTOS | F9: =CONCATENATE($E$1,E9) -> WA.ME/55 | G9: =C9 -> ALAN SOUTO | H9: =IFERROR(VLOOKUP(D9,CPF!A:D,4,0),"NAO ENCONTRADO") -> 013.487.253-38
B10: =CONCATENATE($A$1,A10) -> WA.ME/55 | C10: MARCOS VICTOR | D10: LUIZ OCTAVIO ALMEIDA DA SILVA | F10: =CONCATENATE($E$1,E10) -> WA.ME/55 | G10: =C10 -> MARCOS VICTOR | H10: =IFERROR(VLOOKUP(D10,CPF!A:D,4,0),"NAO ENCONTRADO") -> 087.399.743-32
B11: =CONCATENATE($A$1,A11) -> WA.ME/55 | C11: ALAN SOUTO | D11: MAILSON FRANCISCO PEREIRA | F11: =CONCATENATE($E$1,E11) -> WA.ME/55 | G11: =C11 -> ALAN SOUTO | H11: =IFERROR(VLOOKUP(D11,CPF!A:D,4,0),"NAO ENCONTRADO") -> 062.780.033-50
B12: =CONCATENATE($A$1,A12) -> WA.ME/55 | C12: ALAN SOUTO | D12: MARCOS VICTOR LOPES MEDEIROS FONSECA | F12: =CONCATENATE($E$1,E12) -> WA.ME/55 | G12: =C12 -> ALAN SOUTO | H12: =IFERROR(VLOOKUP(D12,CPF!A:D,4,0),"NAO ENCONTRADO") -> 034.029.363-21
B13: =CONCATENATE($A$1,A13) -> WA.ME/55 | C13: ALAN SOUTO | D13: WILLIAM ADRIANO DANTAS | F13: =CONCATENATE($E$1,E13) -> WA.ME/55 | G13: =C13 -> ALAN SOUTO | H13: =IFERROR(VLOOKUP(D13,CPF!A:D,4,0),"NAO ENCONTRADO") -> 070.038.853-28
B14: =CONCATENATE($A$1,A14) -> WA.ME/55 | C14: ALAN SOUTO | F14: =CONCATENATE($E$1,E14) -> WA.ME/55 | G14: =C14 -> ALAN SOUTO | H14: =IFERROR(VLOOKUP(D14,CPF!A:D,4,0),"NAO ENCONTRADO") -> NAO ENCONTRADO
B15: =CONCATENATE($A$1,A15) -> WA.ME/55 | C15: ALAN SOUTO | F15: =CONCATENATE($E$1,E15) -> WA.ME/55 | G15: =C15 -> ALAN SOUTO | H15: =IFERROR(VLOOKUP(D15,CPF!A:D,4,0),"NAO ENCONTRADO") -> NAO ENCONTRADO
B16: =CONCATENATE($A$1,A16) -> WA.ME/55 | C16: ALAN SOUTO | F16: =CONCATENATE($E$1,E16) -> WA.ME/55 | G16: =C16 -> ALAN SOUTO | H16: =IFERROR(VLOOKUP(D16,CPF!A:D,4,0),"NAO ENCONTRADO") -> NAO ENCONTRADO
B17: =CONCATENATE($A$1,A17) -> WA.ME/55 | C17: ALAN SOUTO | F17: =CONCATENATE($E$1,E17) -> WA.ME/55 | G17: =C17 -> ALAN SOUTO | H17: =IFERROR(VLOOKUP(D17,CPF!A:D,4,0),"NAO ENCONTRADO") -> NAO ENCONTRADO
B18: =CONCATENATE($A$1,A18) -> WA.ME/55 | C18: ALAN SOUTO | F18: =CONCATENATE($E$1,E18) -> WA.ME/55 | G18: =C18 -> ALAN SOUTO | H18: =IFERROR(VLOOKUP(D18,CPF!A:D,4,0),"NAO ENCONTRADO") -> NAO ENCONTRADO
B19: =CONCATENATE($A$1,A19) -> WA.ME/55 | C19: JEBNET | D19: ANTONIO CARLOS BARBOSA SOUSA | F19: =CONCATENATE($E$1,E19) -> WA.ME/55 | G19: =C19 -> JEBNET | H19: =IFERROR(VLOOKUP(D19,CPF!A:D,4,0),"NAO ENCONTRADO") -> NAO ENCONTRADO
B20: =CONCATENATE($A$1,A20) -> WA.ME/55 | C20: JEBNET | D20: ANTONIO EUNARDES SOUSA BRAGA | F20: =CONCATENATE($E$1,E20) -> WA.ME/55 | G20: =C20 -> JEBNET | H20: =IFERROR(VLOOKUP(D20,CPF!A:D,4,0),"NAO ENCONTRADO") -> NAO ENCONTRADO
B21: =CONCATENATE($A$1,A21) -> WA.ME/55 | C21: JEBNET | D21: ANTONIO WILSON SOARES DE SOUSA | F21: =CONCATENATE($E$1,E21) -> WA.ME/55 | G21: =C21 -> JEBNET | H21: =IFERROR(VLOOKUP(D21,CPF!A:D,4,0),"NAO ENCONTRADO") -> NAO ENCONTRADO
B22: =CONCATENATE($A$1,A22) -> WA.ME/55 | C22: JEBNET | D22: EMANUEL ALBANO GOMES | F22: =CONCATENATE($E$1,E22) -> WA.ME/55 | G22: =C22 -> JEBNET | H22: =IFERROR(VLOOKUP(D22,CPF!A:D,4,0),"NAO ENCONTRADO") -> NAO ENCONTRADO
B23: =CONCATENATE($A$1,A23) -> WA.ME/55 | C23: JEBNET | D23: FRANCISCO DA SILVA RODRIGUES | F23: =CONCATENATE($E$1,E23) -> WA.ME/55 | G23: =C23 -> JEBNET | H23: =IFERROR(VLOOKUP(D23,CPF!A:D,4,0),"NAO ENCONTRADO") -> NAO ENCONTRADO
B24: =CONCATENATE($A$1,A24) -> WA.ME/55 | C24: JEBNET | D24: FRANCISCO JOSE FREITAS NEO | F24: =CONCATENATE($E$1,E24) -> WA.ME/55 | G24: =C24 -> JEBNET | H24: =IFERROR(VLOOKUP(D24,CPF!A:D,4,0),"NAO ENCONTRADO") -> NAO ENCONTRADO
B25: =CONCATENATE($A$1,A25) -> WA.ME/55 | C25: JEBNET | D25: FRANCISCO RAFAEL DIAS | F25: =CONCATENATE($E$1,E25) -> WA.ME/55 | G25: =C25 -> JEBNET | H25: =IFERROR(VLOOKUP(D25,CPF!A:D,4,0),"NAO ENCONTRADO") -> NAO ENCONTRADO
B26: =CONCATENATE($A$1,A26) -> WA.ME/55 | C26: JEBNET | D26: FRANCISCO YURI DA COSTA MARTINS | F26: =CONCATENATE($E$1,E26) -> WA.ME/55 | G26: =C26 -> JEBNET | H26: =IFERROR(VLOOKUP(D26,CPF!A:D,4,0),"NAO ENCONTRADO") -> NAO ENCONTRADO
B27: =CONCATENATE($A$1,A27) -> WA.ME/55 | C27: JEBNET | D27: JOAO ADAILSON GOMES ALBANO | F27: =CONCATENATE($E$1,E27) -> WA.ME/55 | G27: =C27 -> JEBNET | H27: =IFERROR(VLOOKUP(D27,CPF!A:D,4,0),"NAO ENCONTRADO") -> NAO ENCONTRADO
B28: =CONCATENATE($A$1,A28) -> WA.ME/55 | C28: JEBNET | D28: JOAO BATISTA COELHO GOMES | F28: =CONCATENATE($E$1,E28) -> WA.ME/55 | G28: =C28 -> JEBNET | H28: =IFERROR(VLOOKUP(D28,CPF!A:D,4,0),"NAO ENCONTRADO") -> NAO ENCONTRADO
B29: =CONCATENATE($A$1,A29) -> WA.ME/55 | C29: JEBNET | D29: MICHEL PLATINI CORREIA MORAIS | F29: =CONCATENATE($E$1,E29) -> WA.ME/55 | G29: =C29 -> JEBNET | H29: =IFERROR(VLOOKUP(D29,CPF!A:D,4,0),"NAO ENCONTRADO") -> NAO ENCONTRADO
B30: =CONCATENATE($A$1,A30) -> WA.ME/55 | C30: JEBNET | D30: MILTON FERREIRA DE CASTRO | F30: =CONCATENATE($E$1,E30) -> WA.ME/55 | G30: =C30 -> JEBNET | H30: =IFERROR(VLOOKUP(D30,CPF!A:D,4,0),"NAO ENCONTRADO") -> NAO ENCONTRADO
... B69: =CONCATENATE($A$1,A69) -> WA.ME/55 | C69: MAILSON FRANCISCO | D69: YVINA CHAGAS ALENCAR | F69: =CONCATENATE($E$1,E69) -> WA.ME/55 | G69: =C69 -> MAILSON FRANCISCO | H69: =IFERROR(VLOOKUP(D69,CPF!A:D,4,0),"NAO ENCONTRADO") -> 080.135.683-00
B70: =CONCATENATE($A$1,A70) -> WA.ME/55 | C70: MAILSON FRANCISCO | F70: =CONCATENATE($E$1,E70) -> WA.ME/55 | G70: =C70 -> MAILSON FRANCISCO | H70: =IFERROR(VLOOKUP(D70,CPF!A:D,4,0),"NAO ENCONTRADO") -> NAO ENCONTRADO
B71: =CONCATENATE($A$1,A71) -> WA.ME/55 | C71: MAILSON FRANCISCO | F71: =CONCATENATE($E$1,E71) -> WA.ME/55 | G71: =C71 -> MAILSON FRANCISCO | H71: =IFERROR(VLOOKUP(D71,CPF!A:D,4,0),"NAO ENCONTRADO") -> NAO ENCONTRADO
B72: =CONCATENATE($A$1,A72) -> WA.ME/55 | C72: MAILSON FRANCISCO | F72: =CONCATENATE($E$1,E72) -> WA.ME/55 | G72: =C72 -> MAILSON FRANCISCO | H72: =IFERROR(VLOOKUP(D72,CPF!A:D,4,0),"NAO ENCONTRADO") -> NAO ENCONTRADO
B73: =CONCATENATE($A$1,A73) -> WA.ME/55 | C73: MAILSON FRANCISCO | F73: =CONCATENATE($E$1,E73) -> WA.ME/55 | G73: =C73 -> MAILSON FRANCISCO | H73: =IFERROR(VLOOKUP(D73,CPF!A:D,4,0),"NAO ENCONTRADO") -> NAO ENCONTRADO
B74: =CONCATENATE($A$1,A74) -> WA.ME/55 | C74: MAILSON FRANCISCO | F74: =CONCATENATE($E$1,E74) -> WA.ME/55 | G74: =C74 -> MAILSON FRANCISCO | H74: =IFERROR(VLOOKUP(D74,CPF!A:D,4,0),"NAO ENCONTRADO") -> NAO ENCONTRADO
B75: =CONCATENATE($A$1,A75) -> WA.ME/55 | C75: MAILSON FRANCISCO | F75: =CONCATENATE($E$1,E75) -> WA.ME/55 | G75: =C75 -> MAILSON FRANCISCO | H75: =IFERROR(VLOOKUP(D75,CPF!A:D,4,0),"NAO ENCONTRADO") -> NAO ENCONTRADO
B76: =CONCATENATE($A$1,A76) -> WA.ME/55 | C76: MARCOS VICTOR | D76: ANDRE SILVA LOIOLA | F76: =CONCATENATE($E$1,E76) -> WA.ME/55 | G76: =C76 -> MARCOS VICTOR | H76: =IFERROR(VLOOKUP(D76,CPF!A:D,4,0),"NAO ENCONTRADO") -> 066.675.003-38
B77: =CONCATENATE($A$1,A77) -> WA.ME/55 | C77: MARCOS VICTOR | D77: ANTONIO FELIPE CASTRO DE OLIVEIRA | F77: =CONCATENATE($E$1,E77) -> WA.ME/55 | G77: =C77 -> MARCOS VICTOR | H77: =IFERROR(VLOOKUP(D77,CPF!A:D,4,0),"NAO ENCONTRADO") -> 071.005.963-94
B78: =CONCATENATE($A$1,A78) -> WA.ME/55 | C78: MARCOS VICTOR | D78: ANTONIO FELIPE SOARES SILVA TAVARES | F78: =CONCATENATE($E$1,E78) -> WA.ME/55 | G78: =C78 -> MARCOS VICTOR | H78: =IFERROR(VLOOKUP(D78,CPF!A:D,4,0),"NAO ENCONTRADO") -> 076.287.933-55
B79: =CONCATENATE($A$1,A79) -> WA.ME/55 | C79: MARCOS VICTOR | D79: ANTONIO MARCOS LIMA DA SILVA | F79: =CONCATENATE($E$1,E79) -> WA.ME/55 | G79: =C79 -> MARCOS VICTOR | H79: =IFERROR(VLOOKUP(D79,CPF!A:D,4,0),"NAO ENCONTRADO") -> 009.280.143-98
B80: =CONCATENATE($A$1,A80) -> WA.ME/55 | C80: MARCOS VICTOR | D80: ANTONIO RAFAEL ALEXANDRE DE SOUSA | F80: =CONCATENATE($E$1,E80) -> WA.ME/55 | G80: =C80 -> MARCOS VICTOR | H80: =IFERROR(VLOOKUP(D80,CPF!A:D,4,0),"NAO ENCONTRADO") -> 072.535.953-60
B81: =CONCATENATE($A$1,A81) -> WA.ME/55 | C81: MARCOS VICTOR | D81: ARLISON DA SILVA PEREIRA | F81: =CONCATENATE($E$1,E81) -> WA.ME/55 | G81: =C81 -> MARCOS VICTOR | H81: =IFERROR(VLOOKUP(D81,CPF!A:D,4,0),"NAO ENCONTRADO") -> 622.847.103-10
B82: =CONCATENATE($A$1,A82) -> WA.ME/55 | C82: MARCOS VICTOR | D82: BRENDHOWN CESAR VIANA SILVA FALCAO | F82: =CONCATENATE($E$1,E82) -> WA.ME/55 | G82: =C82 -> MARCOS VICTOR | H82: =IFERROR(VLOOKUP(D82,CPF!A:D,4,0),"NAO ENCONTRADO") -> 072.308.153-04
B83: =CONCATENATE($A$1,A83) -> WA.ME/55 | C83: MARCOS VICTOR | D83: CAIO VICTOR MONTEIRO DE OLIVEIRA | F83: =CONCATENATE($E$1,E83) -> WA.ME/55 | G83: =C83 -> MARCOS VICTOR | H83: =IFERROR(VLOOKUP(D83,CPF!A:D,4,0),"NAO ENCONTRADO") -> NAO ENCONTRADO
B84: =CONCATENATE($A$1,A84) -> WA.ME/55 | C84: MARCOS VICTOR | D84: CARLOS HENRIQUE LINO SILVA | F84: =CONCATENATE($E$1,E84) -> WA.ME/55 | G84: =C84 -> MARCOS VICTOR | H84: =IFERROR(VLOOKUP(D84,CPF!A:D,4,0),"NAO ENCONTRADO") -> 076.597.513-01
B85: =CONCATENATE($A$1,A85) -> WA.ME/55 | C85: MARCOS VICTOR | D85: DANILO OLIVEIRA DE SOUSA | F85: =CONCATENATE($E$1,E85) -> WA.ME/55 | G85: =C85 -> MARCOS VICTOR | H85: =IFERROR(VLOOKUP(D85,CPF!A:D,4,0),"NAO ENCONTRADO") -> NAO ENCONTRADO
B86: =CONCATENATE($A$1,A86) -> WA.ME/55 | C86: MARCOS VICTOR | D86: DIEGO DA SILVA ASSUNCAO | F86: =CONCATENATE($E$1,E86) -> WA.ME/55 | G86: =C86 -> MARCOS VICTOR | H86: =IFERROR(VLOOKUP(D86,CPF!A:D,4,0),"NAO ENCONTRADO") -> NAO ENCONTRADO
B87: =CONCATENATE($A$1,A87) -> WA.ME/55 | C87: MARCOS VICTOR | D87: ELEEONAI VIANA DA SILVA | F87: =CONCATENATE($E$1,E87) -> WA.ME/55 | G87: =C87 -> MARCOS VICTOR | H87: =IFERROR(VLOOKUP(D87,CPF!A:D,4,0),"NAO ENCONTRADO") -> 055.744.653-88
... B136: =CONCATENATE($A$1,A136) -> WA.ME/55 | C136: WILLIAM DANTAS | D136: WESLLEY ALVES UCHOA | F136: =CONCATENATE($E$1,E136) -> WA.ME/55 | G136: =C136 -> WILLIAM DANTAS | H136: =IFERROR(VLOOKUP(D136,CPF!A:D,4,0),"NAO ENCONTRADO") -> 083.598.453-28

Sheet TABELA DE METAS
F1: DIAS TRABALHADOS
B2: Premiação | C2: VALOR | D2: META/DIA | E2: AE | F2: 31 | G2: 30 | H2: 29 | I2: 28 | J2: 27 | K2: 26 | L2: 25 | M2: 24 | N2: 23 | O2: 22 | P2: 21 | Q2: 20 | R2: 19 | S2: 18 | T2: 17 | U2: 16 | V2: 15 | W2: 14 | X2: 13 | Y2: 12 | Z2: 11
A3: MISTO | B3: PRATA | C3: 300 | D3: 5 | E3: 4 | F3: 155 | G3: 150 | H3: 145 | I3: 140 | J3: 135 | K3: 130 | L3: 125 | M3: 120 | N3: 115 | O3: 110 | P3: 105 | Q3: 100 | R3: 95 | S3: 90 | T3: 85 | U3: 80 | V3: 75 | W3: 70 | X3: 65 | Y3: 60 | Z3: 55
A4: MISTO | B4: OURO | C4: 600 | D4: 6 | E4: 6 | F4: 186 | G4: 180 | H4: 174 | I4: 168 | J4: 162 | K4: 156 | L4: 150 | M4: 144 | N4: 138 | O4: 132 | P4: 126 | Q4: 120 | R4: 114 | S4: 108 | T4: 102 | U4: 96 | V4: 90 | W4: 84 | X4: 78 | Y4: 72 | Z4: 66
A5: MISTO | B5: PLATINA | C5: 900 | D5: 7 | E5: 8 | F5: 217 | G5: 210 | H5: 203 | I5: 196 | J5: 189 | K5: 182 | L5: 175 | M5: 168 | N5: 161 | O5: 154 | P5: 147 | Q5: 140 | R5: 133 | S5: 126 | T5: 119 | U5: 112 | V5: 105 | W5: 98 | X5: 91 | Y5: 84 | Z5: 77
A6: MISTO | B6: DIAMANTE | C6: 1200 | D6: 8 | E6: 10 | F6: 248 | G6: 240 | H6: 232 | I6: 224 | J6: 216 | K6: 208 | L6: 200 | M6: 192 | N6: 184 | O6: 176 | P6: 168 | Q6: 160 | R6: 152 | S6: 144 | T6: 136 | U6: 128 | V6: 120 | W6: 112 | X6: 104 | Y6: 96 | Z6: 88
A7: PENDENCIA | B7: PRATA | C7: 300 | D7: 6 | E7: 4 | F7: 186 | G7: 180 | H7: 174 | I7: 168 | J7: 162 | K7: 156 | L7: 150 | M7: 144 | N7: 138 | O7: 132 | P7: 126 | Q7: 120 | R7: 114 | S7: 108 | T7: 102 | U7: 96 | V7: 90 | W7: 84 | X7: 78 | Y7: 72 | Z7: 66
A8: PENDENCIA | B8: OURO | C8: 600 | D8: 7 | E8: 6 | F8: 217 | G8: 210 | H8: 203 | I8: 196 | J8: 189 | K8: 182 | L8: 175 | M8: 168 | N8: 161 | O8: 154 | P8: 147 | Q8: 140 | R8: 133 | S8: 126 | T8: 119 | U8: 112 | V8: 105 | W8: 98 | X8: 91 | Y8: 84 | Z8: 77
A9: PENDENCIA | B9: PLATINA | C9: 900 | D9: 8 | E9: 8 | F9: 248 | G9: 240 | H9: 232 | I9: 224 | J9: 216 | K9: 208 | L9: 200 | M9: 192 | N9: 184 | O9: 176 | P9: 168 | Q9: 160 | R9: 152 | S9: 144 | T9: 136 | U9: 128 | V9: 120 | W9: 112 | X9: 104 | Y9: 96 | Z9: 88
A10: PENDENCIA | B10: DIAMANTE | C10: 1200 | D10: 9 | E10: 10 | F10: 279 | G10: 270 | H10: 261 | I10: 252 | J10: 243 | K10: 234 | L10: 225 | M10: 216 | N10: 207 | O10: 198 | P10: 189 | Q10: 180 | R10: 171 | S10: 162 | T10: 153 | U10: 144 | V10: 135 | W10: 126 | X10: 117 | Y10: 108 | Z10: 99
A11: MISTO COND. | B11: PRATA | C11: 600 | D11: 3.5 | E11: 4 | F11: 108.5 | G11: 105 | H11: 101.5 | I11: 98 | J11: 94.5 | K11: 91 | L11: 87.5 | M11: 84 | N11: 80.5 | O11: 77 | P11: 73.5 | Q11: 70 | R11: 66.5 | S11: 63 | T11: 59.5 | U11: 56 | V11: 52.5 | W11: 49 | X11: 45.5 | Y11: 42 | Z11: 38.5
A12: MISTO COND. | B12: OURO | C12: 900 | D12: 4.5 | E12: 6 | F12: 139.5 | G12: 135 | H12: 130.5 | I12: 126 | J12: 121.5 | K12: 117 | L12: 112.5 | M12: 108 | N12: 103.5 | O12: 99 | P12: 94.5 | Q12: 90 | R12: 85.5 | S12: 81 | T12: 76.5 | U12: 72 | V12: 67.5 | W12: 63 | X12: 58.5 | Y12: 54 | Z12: 49.5
A13: MISTO COND. | B13: PLATINA | C13: 1200 | D13: 5.5 | E13: 8 | F13: 170.5 | G13: 165 | H13: 159.5 | I13: 154 | J13: 148.5 | K13: 143 | L13: 137.5 | M13: 132 | N13: 126.5 | O13: 121 | P13: 115.5 | Q13: 110 | R13: 104.5 | S13: 99 | T13: 93.5 | U13: 88 | V13: 82.5 | W13: 77 | X13: 71.5 | Y13: 66 | Z13: 60.5
A14: MISTO COND. | B14: DIAMANTE | C14: 1500 | D14: 6.5 | E14: 10 | F14: 201.5 | G14: 195 | H14: 188.5 | I14: 182 | J14: 175.5 | K14: 169 | L14: 162.5 | M14: 156 | N14: 149.5 | O14: 143 | P14: 136.5 | Q14: 130 | R14: 123.5 | S14: 117 | T14: 110.5 | U14: 104 | V14: 97.5 | W14: 91 | X14: 84.5 | Y14: 78 | Z14: 71.5
... A26: PEND. COND. | B26: DIAMANTE | C26: 1500 | D26: 7.5 | E26: 10 | F26: 232.5 | G26: 225 | H26: 217.5 | I26: 210 | J26: 202.5 | K26: 195 | L26: 187.5 | M26: 180 | N26: 172.5 | O26: 165 | P26: 157.5 | Q26: 150 | R26: 142.5 | S26: 135 | T26: 127.5 | U26: 120 | V26: 112.5 | W26: 105 | X26: 97.5 | Y26: 90 | Z26: 82.5

Sheet CPF
A2: Nome | B2: Matrícula | C2: Empresa | D2: Cpf
A3: ALAN FEITOSA DE SOUTO | B3: 000262 | C3: G INFO | D3: 646.525.643-68
A4: ANTONIO MARCOS LIMA DA SILVA | C4: G INFO | D4: 009.280.143-98
A5: BRUNO MATIAS DA SILVA | C5: G INFO | D5: 070.863.133-94
A6: CLAUDIANO CICINATO DA SILVA | C6: G INFO | D6: 026.126.893-70
A7: DJONATHA COSTA DA SILVA | C7: G INFO | D7: 112.311.524-94
A8: ELISANGELA BOTELHO DA ROCHA | C8: G INFO | D8: 664.730.393-68
A9: ELISSON PEREIRA COUTINHO NOVAIS | C9: G INFO | D9: 078.114.013-71
A10: FABIO SILVESTRE BRITO | B10: 000115 | C10: G INFO | D10: 002.590.223-73
A11: FRANCISCO CARLOS EUGENIO DO NASCIMENTO | B11: 000333 | C11: G INFO | D11: 045.179.853-85
A12: FRANCISCO DAS CHAGAS E SILVA ROCHA | B12: 000216 | C12: G INFO | D12: 604.677.683-07
A13: FRANCISCO DIEGO ALVES FERREIRA | B13: 000295 | C13: G INFO | D13: 065.966.543-38
A14: FRANCISCO HELIO MARINHO CUNHA NETO | C14: G INFO | D14: 078.519.483-55
A15: FRANCISCO LUCAS SOUSA CUNHA | B15: 000305 | C15: G INFO | D15: 625.648.953-52
A16: GABRIEL MARTINS MUNIZ | B16: 000318 | C16: G INFO | D16: 078.282.793-45
A17: GEILSON DA SILVA MOURA | C17: G INFO | D17: 070.629.143-39
A18: GILVAN ASSUNCAO SILVA | B18: 000343 | C18: G INFO | D18: 019.738.393-93
A19: GLEISON VALENTIM ARAUJO | C19: G INFO | D19: 075.630.503-96
A20: GUTEMBERGUE OLIVEIRA | B20: 000271 | C20: G INFO | D20: 020.305.163-76
A21: HALLEF GUILHERME LIMA CLEMENTE SILVA | C21: G INFO | D21: 077.115.853-06
A22: IRINETO FERREIRA DE AGUIAR | B22: 000217 | C22: G INFO | D22: 033.727.593-97
A23: JOAO PAULO GOUVEIA DA SILVA | C23: G INFO | D23: 891.107.223-00
A24: JOSE AMAURY BORGES FILHO | C24: G INFO | D24: 068.959.103-95
A25: JOSE MARIA DA COSTA LEONARDO | B25: 000221 | C25: G INFO | D25: 734.146.113-68
A26: LUCAS SOUZA SILVA | C26: G INFO | D26: 074.800.793-89
A27: LUCIEUDO BANDEIRA ALVES FILHO | B27: 000320 | C27: G INFO | D27: 074.418.063-56
A28: LUIZ CARLOS MACHADO MACIEL | C28: G INFO | D28: 058.715.743-78
A29: MAILSON FRANCISCO PEREIRA | C29: G INFO | D29: 062.780.033-50
A30: MARCOS PEREIRA CARVALHO FILHO | C30: G INFO | D30: 073.501.783-28
A31: MARCOS VICTOR LOPES MEDEIROS FONSECA | C31: G INFO | D31: 034.029.363-21
A32: PAULO ROBERTO ARAUJO GALVAO | C32: G INFO | D32: 014.069.373-47
A33: PEDRO DA SILVA MAIA | C33: G INFO | D33: 092.106.483-74
A34: ROBSON BEZERRA DA SILVA | C34: G INFO | D34: 619.340.993-92
A35: ROMARIO NOBRE DE MELO | B35: 000336 | C35: G INFO | D35: 051.728.733-17
A36: RONALD MESQUITA DOS SANTOS | C36: G INFO | D36: 107.099.153-81
A37: THIAGO CASTRO DO NASCIMENTO | C37: G INFO | D37: 086.965.763-14
A38: VALDERILO FERREIRA LIMA JUNIOR | B38: 000293 | C38: G INFO | D38: 082.974.113-54
A39: WESLLEY ALVES UCHOA | B39: 000119 | C39: G INFO | D39: 083.598.453-28
A40: WILLIAM ADRIANO DANTAS | B40: 000116 | C40: G INFO | D40: 070.038.853-28
A41: YVINA CHAGAS ALENCAR | C41: G INFO | D41: 080.135.683-00
A42: ALEFF PEREIRA SOARES | C42: IFT | D42: 068.984.563-42
A43: ALEXANDRE SANTOS GOMES | C43: IFT | D43: 769.663.563-87
A44: ALLYSSON DA SILVA MARINHO | C44: IFT | D44: 088.824.123-26
A45: ANDRE SILVA LOIOLA | C45: IFT | D45: 066.675.003-38
A46: ANTONIO CARLOS FERREIRA DA SILVA | C46: IFT | D46: 880.346.903-68
A47: ANTONIO EDUARDO TEIXEIRA CAMELO | C47: IFT | D47: 017.467.413-92
A48: ANTONIO FELIPE CASTRO DE OLIVEIRA | B48: 000614 | C48: IFT | D48: 071.005.963-94
A49: ANTONIO FELIPE SOARES SILVA TAVARES | C49: IFT | D49: 076.287.933-55
A50: ANTONIO RAFAEL ALEXANDRE DE SOUSA | C50: IFT | D50: 072.535.953-60
A51: ARLISON DA SILVA PEREIRA | B51: 000475 | C51: IFT | D51: 622.847.103-10
A52: BRENDHOWN CESAR VIANA SILVA FALCAO | C52: IFT | D52: 072.308.153-04
A53: CARLOS HENRIQUE LINO SILVA | C53: IFT | D53: 076.597.513-01
A54: CLAYLSON MORAES DOS SANTOS | C54: IFT | D54: 075.965.843-90
A55: DAVI MEDINA DE ARAUJO | C55: IFT | D55: 014.259.203-06
A56: DAVID DE SOUSA SILVA | C56: IFT | D56: 076.250.123-52
A57: ELEEONAI VIANA DA SILVA | C57: IFT | D57: 055.744.653-88
A58: EMYLLIE CRISTINE ANDRADE CRUZ | C58: IFT | D58: 051.352.823-78
A59: EVERLAN DA PENHA TOME | C59: IFT | D59: 008.385.843-14
A60: FRANCISCO FELIPE DE LIMA ALVES | B60: 000059 | C60: IFT | D60: 058.411.523-78
A61: FRANCISCO MATHEUS PEREIRA MENDES | C61: IFT | D61: 082.775.843-00
A62: FRANCISCO TIAGO PINHEIRO | C62: IFT | D62: 041.037.803-80
A63: ISMAEL JULIAO SOARES | C63: IFT | D63: 633.338.113-67
A64: ISRAEL OLIVEIRA MORAIS | C64: IFT | D64: 095.190.783-20
A65: ISRAEL ROBERTH SANTIAGO DE MENEZES | C65: IFT | D65: 078.961.853-26
A66: ITALO EMANOEL DA SILVA MARQUES | C66: IFT | D66: 109.862.873-00
A67: ITALO XAVIER DA SILVA | C67: IFT | D67: 070.058.973-23
A68: JANIEL TEIXEIRA DE MELO | C68: IFT | D68: 042.868.413-08
A69: JOAO PAULO DA SILVA LIMA | C69: IFT | D69: 001.058.623-71
A70: JOSE EDNARDO DA SILVA DE LIMA | C70: IFT | D70: 615.171.623-00
A71: JOSE HENRIQUE PEREIRA SOUSA | C71: IFT | D71: 620.856.313-55
A72: JOSE ILDEVAM SOUSA DO NASCIMENTO | B72: 000038 | C72: IFT | D72: 071.778.423-14
A73: JOSE WELLITON VIEIRA FELINTO | C73: IFT | D73: 067.905.283-69
A74: LUIZ CARLOS ALVES LOPES | C74: IFT | D74: 080.989.923-06
A75: MAISSON FERREIRA DA SILVA | C75: IFT | D75: 096.369.633-55
A76: MARCOS AURELIO DE SOUSA OLIVEIRA | C76: IFT | D76: 062.256.953-89
A77: MATEUS GABRIEL ROCHA | C77: IFT | D77: 087.975.463-05
A78: RIAN KELVIN ARAUJO MOURAO | C78: IFT | D78: 625.271.283-35
A79: SAMUEL RIBEIRO FELISMINO | C79: IFT | D79: 092.783.123-63
A80: VANIZIO PEREIRA AZEVEDO DO NASCIMENTO | C80: IFT | D80: 048.983.603-86
A81: VICTOR FRANCISCO DE OLIVEIRA GOMES | C81: IFT | D81: 097.395.243-11
A82: VINICIUS SILVA LEARTE | C82: IFT | D82: 603.334.943-18
A83: WELLISON FERREIRA LIMA | C83: IFT | D83: 079.951.163-30
A84: ITALO RIBEIRO DA SILVA | B84: 000602 | C84: INFOLINK | D84: 100.473.673-85
A85: PAULO ITALO JORGE DE MORAES | B85: 000609 | C85: INFOLINK | D85: 071.346.433-01
A86: WESLEY LUCAS BRITO DA SILVA | C86: INFOLINK | D86: 628.843.383-73
A87: FELIPE MARTINS DAMASCENO | C87: TFE | D87: 040.337.373-59
A88: JONATHAN BRENO NOBRE DA SILVA | C88: TFE | D88: 604.548.913-69
A89: KELTON CLEMENTE DOS SANTOS | C89: TWE | D89: 013.487.253-38
A90: LUIZ OCTAVIO ALMEIDA DA SILVA | C90: TWE | D90: 087.399.743-32

Sheet CONCLUIDAS
A1: protocolo | B1: cliente | C1: status_solicitacao | D1: tipo_solicitacao | E1: tipo_rua | F1: rua | G1: numero | H1: cidade | I1: bairro | J1: latitude | K1: longitude | L1: atendente | M1: atendente_origem | N1: data_abertura | O1: data_prazo | P1: data_encerramento | Q1: data_primeiro_relato_encerramento | R1: em_atraso | S1: dias_atraso | T1: cat_2 | U1: cat_3 | V1: cat_4 | W1: cat_5 | X1: solucao | Y1: tecnico_original | Z1: protocolo_original | AA1: olt | AB1: relato_encerramento | AC1: descricao_abertura
A2: 3780562 | B2: ERICK FERREIRA DA SILVA | C2: Encerramento | D2: RETIRADA DE EQUIPAMENTOS | E2: Rua | F2: Rua Visconde do Rio Branco | G2: 8 | H2: Palmares | I2: São Sebastião | J2: -8.6877621e+15 | K2: -3559317156 | L2: KELVER EDUARDO GOMES SOBRAL | M2: ESTEFANY SILVA ARARIPE | N2: 46220 | O2: 46235 | P2: 46281 | Q2: 46281 | R2: Sim | S2: 46 | T2: Retirada de Equipamentos | X2: Equipamento Entregue | AB2: *TEC:* KELVER EDUARDO *DATA: 16/09/2026**COD RETIRADA* 3780562*NOME DO CLIENTE* ERICK FERREIRA DA SILVA*DESCRIÇÃO:* RETIRADA DE EQUIPAMENTO.*SOLUÇÃO:* EQUIPEMENTO NAO RETIRADO. *OBS* EM CONTATO COM CLIENTE O MESMO INFORMOU QUE IRÁ PROCURAR O EQUIPAMENTO , AFIRMOU NAO SABER ONDE COLOCOU , DISSE TAMBEM QUE ASSIM QUE ACHAR ENTREGARÁ EM LOJA.Dispositivo: samsung SM-A146MVersão do Android: 15Versão do V·Tasks: 5.9.214 Status alterado de Andamento para Encerramento | AC2: 1. DESCRIÇÃO DA SOLICITAÇÃO:2.CONTATO TELEFÔNICO (01):3.CONTATO TELEFÔNICO (02):4.WHATSAPP:5.PONTO DE REFERÊNCIA:6.DISPONIBILIDADE:7.PRAZO: 10 DIAS CORRIDOS8. CLIENTE COM NECESSIDADES ESPECIAIS/NECESSIDADE?Contrato cancelado, necessário realizar visita ao cliente para remover os equipamentos em comodato.ONT ZTE 2 ANTENAS V9.0
A3: 3819617 | B3: JOSEFINA JULIA LIRA PORTELA | C3: Encerramento | D3: RETIRADA DE EQUIPAMENTOS | E3: Rua | F3: Rua Diário De Pernambuco | G3: 335 | H3: Palmares | I3: Modelo | J3: -86861283 | K3: -355971726 | L3: TARCIO FRANCISCO DA SILVA | M3: SARA ALLANA RODRIGUES FERNANDES | N3: 46247 | O3: 46248 | P3: 46283 | Q3: 46283 | R3: Sim | S3: 35 | T3: Retirada de Equipamentos | X3: Equipamento Entregue | AB3: *TEC:* TARCIO FRANCISCO *DATA: 18/09/2026**COD RETIRADA* 3819617*NOME DO CLIENTE* JOSEFINA JULIA LIRA PORTELA*ENDEREÇO* Rua Diário De Pernambuco, 335, Modelo - Palmares*DESCRIÇÃO:* RETIRADA DE EQUIPAMENTO*SOLUÇÃO:* EQUIPEMENTO RETIRADO (GPON00EE5C2C)*OBS*Dispositivo: Xiaomi 23053RN02AVersão do Android: 15Versão do V·Tasks: 5.9.215 Status alterado de Andamento para Encerramento | AC3: 1. DESCRIÇÃO DA SOLICITAÇÃO:2.CONTATO TELEFÔNICO (01):3.CONTATO TELEFÔNICO (02):4.WHATSAPP:5.PONTO DE REFERÊNCIA:6.DISPONIBILIDADE:7.PRAZO: 10 DIAS CORRIDOS8. CLIENTE COM NECESSIDADES ESPECIAIS/NECESSIDADE?Contrato cancelado, necessário realizar visita ao cliente para remover os equipamentos em comodato.ONT HG325AX
A4: 3822864 | B4: FÁBIO CAXIAS DE CARVALHO | C4: Encerramento | D4: PENDÊNCIA FIBRA - COND. | E4: Rua | F4: Rua Tomaz de Aquino | G4: 484 | H4: Aquiraz | I4: Centro | L4: HALLEF GUILHERME LIMA CLEMENTE SILVA | M4: FRANCISCA ALICE MESQUITA FERREIRA | N4: 46249 | O4: 46250 | P4: 46269 | Q4: 46269 | R4: Sim | S4: 19 | T4: Cliente Condomínio | U4: Pendência | V4: LOS | W4: Fibra Sem Sinal / Luz Los Vermelha | X4: Troca Conector - Desgastado | AA4: OLT Aquiraz VLAN 12 | AB4: *PENDÊNCIA**Data:* 04/09/2026 *ATENDENTE:**Técnico:* Hallef / Ismael *CLIENTE* FÁBIO CAXIAS DE CARVALHO*ENDEREÇO* Condomínio Mirante da Prainha,Casa 44*Caixa:*8767*Porta:* 5*Potência da Caixa:* -22*Potência do Cliente:*-22*Serviço* Troca de drop, cortado por outra provedora Conexão normalizada pós troca *Materiais* *conector azul:* 1und *conector verde:* 1und *Fixa fio* *adesivo* 1und *canaleta**RJ 45**EQUIPAMENTOS**ONT*: *ROTEADOR* *ONU**DROP**Início* 1000m*Fim* 860m*Utilizado* 140m *EQUIPAMENTO RECOLHIDO**Valor:**Obs.:*Dispositivo: Xiaomi 2311DRK48IVersão do Android: 16Versão do V·Tasks: 5.9.213 Status alterado de Reagendado para Encerramento | AC4: 15/08/2026 - 16:59 01. RELATO DO CLIENTE: Cliente relata sem internet / offline no voalle / link los no UNM / piscando vermelho no equipamento02. ANÁLISE SISTEMA (UNM): linklos no UNM03. ANÁLISE SISTEMA (VOALLE): offline no Voalle04. EXTRATO COM QUEDAS: XX05. GERENCIAMENTO REM. HABILITADO: XX06. PROCEDIMENTO REALIZADO: REBOOT DA TOMADA07. POTÊNCIA: XX08. CAIXA E PORTA: CX 8767 P-0508. CONTATO: 8599801223809. ENDEREÇO COMPLETO: Rua Tomaz de Aquino 484, Centro - Aquiraz, CE61700-00010. CONDOMÍNIO: CONDOMINIO MIRANTE DA PRAINHA 10. PONTO DE REFERÊNCIA: MIRANTE DA PRAINHA 11. DISPONIBILIDADE: DOMINGO O DIA TODO12. OBSERVAÇÃO: ENTRAR EM CONTATO ANTES DE IR AO LOCAL
A5: 3835168 | B5: FATIMA MARIA SILVA | C5: Encerramento | D5: INSTALAÇÃO FIBRA - PF | E5: Avenida | F5: Av. Laureano de Paulo Santana | G5: 663 | H5: Cascavel | I5: Caponga | J5: -4040241 | K5: -381964008 | L5: ISRAEL OLIVEIRA MORAIS | M5: MARIA ANTONIA ABREU NEVES | N5: 46256 | O5: 46257 | P5: 46269 | Q5: 46269 | R5: Sim | S5: 12 | T5: Cliente Pessoa Física | U5: Instalação | X5: Troca Conector - Desgastado | AA5: OLT Caponga VLAN 1005 | AB5: ⚠️ *instalação* ⚠️*Data:* 04/09 /2026*TÉCNICO RESPONSÁVEL:* Israel Oliveira*CLIENTE:* FATIMA MARIA SILVA*ENDEREÇO:* Av. Laureano de Paulo Santana, 663, Caponga - Cascavel*LOCALIZAÇÃO DO CLIENTE*-4.040496,-38.196510*SUPORTE N2:* *CAIXA:* 1591*PORTA:* 01*POTÊNCIA DA CAIXA:* -20*POTÊNCIA DO CLIENTE:* -21*ACESSO REMOTO HABILITADO:* sim*SENHA DO ROTEADOR:**SERVIÇO:* instalação fibra realizada com sucesso.*OBS:* *MATERIAL UTILIZADO:*02 conector verde02 fixa fio.01 canaleta.75m de drop.01 Ont Intelbras ax3000 mac:EE56*VALOR:* 0,00 *DROP INICIAL:* 765*DROP FINAL:* 690*METRAGEM TOTAL:* 75*CLASSIFICAÇÃO DE ENCERRAMENTO :* finalizado✅Dispositivo: samsung SM-A075MVersão do Android: 16Versão do V·Tasks: 5.9.213 Status alterado de Agendado para Encerramento | AC5: VENDEDOR: maria antoniaÁREA: PAP () CALL-CENTER ( ) LOJA ( ) TBR (x )TITULAR: FATIMA MARIA SILVATELEFONE: WHATSAPP: 85 99919-668385996488726DISPONIBILIDADE: MANHA( x) TARDE ( ) DIA TODO ()DATA:CIDADE E BAIRRO: Caponga, Cascavel PLANO: 500mb 99,99VALOR ORIGINAL DO PLANO: POSSUI DESCONTO DE PONTUALIDADE? SIM ( ) NÃO ( x)SE SIM: D5 ( ) ou DNET - D10( )DESCONTO DE __ , SE PAGO ATÉ O VENCIMENTO POR 12 MESESTAXA INSTALAÇÃO: ATENDIMENTO REGISTRADO:Google Drive ( ) Fortics ( ) Smart (x )FIDELIDADE: (x ) SIM NÃO ( )CLIENTE DESEJA NOTA FISCAL: SIM ( ) NÃO (x )COORD: -4.040166080710224, -38.19631497485019CAIXA: 1591CASA DUPLEX ( ) CASA TERREA (x)QUANTOS E QUAIS APARELHOS CONECTADOS:Celulares mais smarte TV notebook etc.OBSERVAÇÃO ADICIONAL:Ativação do contrato: 173795---- Endereço de Instalação ----CEP: 62850-000Logradouro: Av. Laureano de Paulo SantanaNúmero: 663Bairro: CapongaEstado: CECidade: CascavelComplemento: casaReferência: prox a Padaria nossa senhora de Fátima---- Serviços a serem ativados ----- 0422 - IFT - ULTRAINFO - 500MB
A6: 3837312 | B6: ERIVALDA MARIA DA SILVA | C6: Encerramento | D6: RETIRADA DE EQUIPAMENTOS | E6: Quadra | F6: Quadra 13 | G6: 32 | H6: Palmares | I6: Quilombo 2 | J6: -8702848 | K6: -35596849 | L6: TARCIO FRANCISCO DA SILVA | M6: LUCAS DURVAL DAMASCENO SILVA | N6: 46258 | O6: 46261 | P6: 46283 | Q6: 46283 | R6: Sim | S6: 22 | T6: Retirada de Equipamentos | X6: Equipamento Entregue | AB6: *TEC:* TARCIO FRANCISCO *DATA: 18/09/2026**COD RETIRADA* 3837312*DESCRIÇÃO:* RETIRADA DE EQUI sóPAMENTOS*NOME* ERIVALDA MARIA DA SILVA*SOLUÇÃO:* equipamento retirado*ENDEREÇO* Quadra 13, 32, Quilombo 2 - Palmares*ONT XPON DUAL-BAND AC1200*(DO5FAF7D5E1D)*OBS*Dispositivo: Xiaomi 23053RN02AVersão do Android: 15Versão do V·Tasks: 5.9.215 Status alterado de Andamento para Encerramento | AC6: 1. DESCRIÇÃO DA SOLICITAÇÃO:2.CONTATO TELEFÔNICO (01):3.CONTATO TELEFÔNICO (02):4.WHATSAPP:5.PONTO DE REFERÊNCIA:6.DISPONIBILIDADE:7.PRAZO: 10 DIAS CORRIDOS8. CLIENTE COM NECESSIDADES ESPECIAIS/NECESSIDADE?Contrato cancelado, necessário realizar visita ao cliente para remover os equipamentos em comodato.ONT XPON DUAL-BAND AC1200
A7: 3839231 | B7: REGINA CELIA PEREIRA LIMA BARBOSA | C7: Encerramento | D7: DNET - PENDÊNCIA FIBRA - COND. | E7: Rua | F7: RUA CAMPOS FILHO | G7: 167 | H7: Maracanaú | I7: CAGADO | J7: -3.8437576e+16 | K7: -3.8637581e+15 | L7: CARLOS HENRIQUE LINO SILVA | M7: JOSE MATEUS RICARDO SERPA | N7: 46259 | O7: 46260 | P7: 46266 | Q7: 46266 | R7: Sim | S7: 6 | T7: DNET - Cliente Condomínio | U7: DNET - Pendência | V7: DNET - LOS | W7: DNET - Fibra Sem Sinal / Luz Los Vermelha | X7: Troca Conector - Desgastado | AA7: OLT DNET TEMPORARIO | AB7: Abertura Solicitação para visita técnica no cliente, a pedido do mesmo.CLIENTE NORMALIZOU APOS MANUTENÇÃO DA INFRAESTRUTURA. Dispositivo: samsung SM-A055MVersão do Android: 14Versão do V·Tasks: 5.9.211 Status alterado de Tratamento Infra para Encerramento | AC7: 25/08/2026 - 13:37 01. RELATO DO CLIENTE: DNET - Fibra Sem Sinal / Luz Los Vermelha02. ANÁLISE SISTEMA (UNM): offline 03. ANÁLISE SISTEMA (VOALLE): offline 04. EXTRATO COM QUEDAS: xxxx05. GERENCIAMENTO REM. HABILITADO: verificar 06. PROCEDIMENTO REALIZADO: nenhum cliente retenção07. POTÊNCIA: sem08. CAIXA E PORTA: sem08. CONTATO: 85 988665595 98844789109. ENDEREÇO COMPLETO: Rua vamos filho 167 Condomínio Virgílio tavaro 210. CONDOMÍNIO: SIM 10. PONTO DE REFERÊNCIA: Piso novo /BLOCO 10 AP 20411. DISPONIBILIDADE: total12. OBSERVAÇÃO:
A8: 3839677 | B8: RONILSON ALVES DA SILVA | C8: Encerramento | D8: RETIRADA DE EQUIPAMENTOS | E8: Rua | F8: Rua Doutor Costa Lima | G8: 30 | H8: Palmares | I8: Santo Onofre | J8: -86795889 | K8: -355842531 | L8: TARCIO FRANCISCO DA SILVA | M8: ESTEFANY SILVA ARARIPE | N8: 46259 | O8: 46260 | P8: 46283 | Q8: 46283 | R8: Sim | S8: 23 | T8: Retirada de Equipamentos | X8: Equipamento Entregue | AB8: *TEC:* TARCIO FRANCISCO *DATA: 18/09/2026**COD RETIRADA* 3839677*DESCRIÇÃO* RETIRADA DE EQUIPAMENTOS*NOME* RONILSON ALVES DA SILVA*SOLUÇÃO:* equipamentos retirado*ENDEREÇO* Rua Doutor Costa Lima, 30, Santo Onófre - Palmares*ONT ZTE 2 ANTENAS* (ZTEGD4B328EF)Dispositivo: Xiaomi 23053RN02AVersão do Android: 15Versão do V·Tasks: 5.9.215 Status alterado de Andamento para Encerramento | AC8: 1. DESCRIÇÃO DA SOLICITAÇÃO:2.CONTATO TELEFÔNICO (01):3.CONTATO TELEFÔNICO (02):4.WHATSAPP:5.PONTO DE REFERÊNCIA:6.DISPONIBILIDADE:7.PRAZO: 10 DIAS CORRIDOS8. CLIENTE COM NECESSIDADES ESPECIAIS/NECESSIDADE?Contrato cancelado, necessário realizar visita ao cliente para remover os equipamentos em comodato.ONT ZTE 2 ANTENAS V9.0
A9: 3839959 | B9: JOISE NUNES DE OLIVEIRA | C9: Encerramento | D9: PENDÊNCIA FIBRA POTÊNCIA ALTA | E9: Rua | F9: Rua José Carneiro de Andrade | G9: 156 | H9: Choró | I9: Cidade Nova | L9: ANTONIO TIAGO AMANCIO DA SILVA | M9: EMILY LUANY ALVES BASTOS | N9: 46259 | O9: 46260 | P9: 46267 | Q9: 46267 | R9: Sim | S9: 7 | T9: Cliente Pessoa Física | U9: Pendência | V9: Potência Alta | W9: Correção de Potência | X9: Troca Conector - Desgastado | AA9: OLT Choro VLAN 4004 | AB9: ♦️ *PENDÊNCIA* ♦️*Data:* 02/09/2026*Técnico:* Tiago*Auxiliar:* Amaury *Cliente:* JOISE NUNES DE OLIVEIRA*Endereço:* Rua José Carneiro de Andrade, 156, Cidade Nova *Classificação de Encerramento:*RESOLVIDO"CLIENTE RELATA QUE DURANTE O DIA A INTERNET É BOA, POREM A NOITE NÃO TA FUNCIONANDO LEGAL, CLIENTE AFIRMA QUE DURANTE A NOITE A INTERNET FICA CAINDO"Dispositivo: Xiaomi 23100RN82LVersão do Android: 15Versão do V·Tasks: 5.9.211 Status alterado de Andamento para Encerramento | AC9: 25/08/2026 - 20:12 01. RELATO DO CLIENTE: cliente com potência alta, necessário normalizar a potência02. ANÁLISE SISTEMA (UNM): online03. ANÁLISE SISTEMA (VOALLE): Online04. EXTRATO COM QUEDAS: SIM ou NÃO x05. GERENCIAMENTO REM. HABILITADO: SIM ou NÃO, verificar xx06. PROCEDIMENTO REALIZADO: visto a potência no unm07. POTÊNCIA: -16.0708. CAIXA E PORTA: cx1095 p0208. CONTATO: 889931426068899362037809. ENDEREÇO COMPLETO: Rua José Carneiro de Andrade, 156 - Cidade Nova - Choró - CE - CEP 63950-00010. CONDOMÍNIO: SIM (Nome) ou NÃO x10. PONTO DE REFERÊNCIA: Perto Do Hospital11. DISPONIBILIDADE: o dia todo 12. OBSERVAÇÃO:
A10: 3840367 | B10: FRANCISCO AURICLECIO QUEIROZ DE SOUZA | C10: Encerramento | D10: INSTALAÇÃO FIBRA - COND. | E10: Rua | F10: Rua Benjamim Barreto | G10: 73 | H10: Fortaleza | I10: Cristo Redentor | J10: -3705679 | K10: -38566873 | L10: FRANCISCO JHONATA DA COSTA | M10: DANIEL DA SILVA COSTA | N10: 46260 | O10: 46261 | P10: 46267 | Q10: 46267 | R10: Sim | S10: 6 | T10: Cliente Condomínio | U10: Instalação | X10: Troca Conector - Desgastado | AA10: OLT Barra do Ceará VLAN 1001 | AB10: *INSTALAÇÃO**Data* 02/09/2026*Técnico* Jhonata Costa CLIENTE:FRANCISCO AURICLECIO QUEIROZ DE SOUZAENDERECO:Rua Benjamim Barreto, 73, Cristo Redentor - Fortaleza*Caixa:4378*Porta*:04*SINAL DA CAIXA*. -22*SINAL DO CLIENTE:-24*SERVICO REALIZADO*Instalação concluída com sucesso...*Material utilizado*02Conector Verde 00Conector Azul02Fixa fio00 Canaleta00 Esticador00Adesivo conector0 RJ4500 pat Cord01 ONT FIBERHOME *OBS* : Concluído okLogin:multipro Senha:multipro *VALOR* :*Cabo inicial*:*Cabo final* *Metragem* *Drop inicial*1000*Drop final* : 0697*Metragem**0303Dispositivo: samsung SM-A075MVersão do Android: 16Versão do V·Tasks: 5.9.206 Status alterado de Reagendado para Encerramento | AC10: VENDEDOR: DANIEL ÁREA: PAP (X) CALL-CENTER ( ) LOJA ( ) TBR ( )TITULAR: FRANCISCO AURICLECIO QUEIROZ DE SOUZA TELEFONE: 85999133956WHATSAPP: 85999133956DISPONIBILIDADE: MANHA( ) TARDE ( x) DIA TODO ()DATA:CIDADE E BAIRRO: CRISTO REDENTOR FORTALEZA PLANO: 500 CURUJÃO VALOR ORIGINAL DO PLANO: 99.99POSSUI DESCONTO DE PONTUALIDADE? SIM ( x) NÃO ( )SE SIM: D5 ( ) ou DNET - D10( )DESCONTO DE __ , SE PAGO ATÉ O VENCIMENTO POR 12 MESESTAXA INSTALAÇÃO: ATENDIMENTO REGISTRADO:Google Drive ( ) Fortics ( ) Smart ( )FIDELIDADE: ( x) SIM NÃO ( )CLIENTE DESEJA NOTA FISCAL: SIM ( ) NÃO ( )COORD:CAIXA: -3.7056938, -38.5668779CX6166CASA DUPLEX ( x) CASA TERREA ()QUANTOS E QUAIS APARELHOS CONECTADOS: 4 CELULARES OBSERVAÇÃO ADICIONAL:Ativação do contrato: 173980---- Endereço de Instalação ----CEP: 60337-390Logradouro: Rua Benjamim BarretoNúmero: 73Bairro: Cristo RedentorEstado: CECidade: FortalezaComplemento: AILOS---- Serviços a serem ativados ----- 0422 - ULTRAINFO - 500MB
A11: 3840771 | B11: FRANCISCO MOYSES FREITAS DA SILVA | C11: Encerramento | D11: DNET - PENDENCIA FIBRA - PF | E11: Avenida | F11: Avenida Noé Leite de Freitas | G11: 15 | H11: Aquiraz | I11: Altos dos Pereiras | J11: -3914746 | K11: -384271461 | L11: ANDRE SILVA LOIOLA | M11: RUAN VICTOR SANTOS SOUZA CLARINDO | N11: 46260 | O11: 46261 | P11: 46266 | Q11: 46266 | R11: Sim | S11: 5 | T11: DNET - Cliente Pessoa Física | U11: DNET - Pendência | V11: DNET - Configuração Equipamentos | W11: DNET - Configuração Básica | X11: Troca Conector - Desgastado | AA11: OLT DNET TEMPORARIO | AB11: Abertura Solicitação para visita técnica no cliente, a pedido do mesmo.NORMALIZADO PÓS INFRA.Dispositivo: motorola moto g23Versão do Android: 14Versão do V·Tasks: 5.9.211 Status alterado de Tratamento Infra para Encerramento | AC11: 26/08/2026 - 12:44 01. RELATO DO CLIENTE: Cliente informa que está sem conexão há 8 dias e relata que há uma LED vermelha piscando no equipamento. Foi verificado em sistema que o serviço consta como normal e que o cliente está com conexão ativa. O cliente informou que o equipamento está instalado na residência de seu pai e que, no momento do atendimento, não se encontrava no local. Dessa forma, não foi possível realizar os procedimentos padrões nem verificar presencialmente o status da conexão e do equipamento.02. ANÁLISE SISTEMA (UNM): Não localizado03. ANÁLISE SISTEMA (VOALLE): ONLINE04. EXTRATO COM QUEDAS: NÃO05. GERENCIAMENTO REM. HABILITADO: NÃO, habilitar por favor06. PROCEDIMENTO REALIZADO: não foi possível fazer pois cliente não estava no local07. POTÊNCIA: xx08. CAIXA E PORTA:xx08. CONTATO: (85)99675-503509. ENDEREÇO COMPLETO: Rua Maria Liberalina, 0 - Alto dos Pereiras - Aquiraz - CE - CEP 61700-000/ Forrozão 200010. CONDOMÍNIO: NÃO10. PONTO DE REFERÊNCIA: Casa do moyses Freitas 11. DISPONIBILIDADE: Total12. OBSERVAÇÃO: O mesmo está ciente de cobranças a serem geradas caso a visita seja improdutiva
A12: 3840799 | B12: IRIS PEREIRA GOMES | C12: Encerramento | D12: PENDÊNCIA FIBRA DEFINIR PRAZO | E12: Rua | F12: R. Itapipoca | G12: 80 | H12: Cascavel | I12: Caponga | J12: -40450043 | K12: -381897219 | L12: ISRAEL OLIVEIRA MORAIS | M12: ANA CAROLINE GIRAO LIMA | N12: 46260 | O12: 46281 | P12: 46270 | Q12: 46270 | R12: Não | T12: Cliente Pessoa Física | U12: Pendência | V12: Definir Prazo | W12: Definir Prazo | X12: Troca Conector - Desgastado | AA12: OLT Caponga VLAN 1005 | AB12: ⚠️ *pendência* ⚠️*Data:* 05/09/2026*TÉCNICO RESPONSÁVEL:* Israel Oliveira *CLIENTE:* IRIS PEREIRA GOMES*ENDEREÇO:* R. Itapipoca, 80, Caponga - Cascavel*LOCALIZAÇÃO DO CLIENTE* -4.044932,-38.190190*SUPORTE N2:* *CAIXA:* 1654*PORTA:* 08*POTÊNCIA DA CAIXA:* -24*POTÊNCIA DO CLIENTE:* -25*ACESSO REMOTO HABILITADO:* sim*SENHA DO ROTEADOR:**SERVIÇO:* drop rompido, realizado a troca do drop e voltou o acesso.*OBS:* *MATERIAL UTILIZADO:*02 conector verde.190m de drop.*VALOR:* 0,00 *DROP INICIAL:* 190*DROP FINAL:* 0*METRAGEM TOTAL:* 190*CLASSIFICAÇÃO DE ENCERRAMENTO :* finalizado ✅Dispositivo: samsung SM-A075MVersão do Android: 16Versão do V·Tasks: 5.9.213 Status alterado de Agendado para Encerramento | AC12: 26/08/2026 - 12:15 01. RELATO DO CLIENTE: sem internet, led vermelha no equipamento02. ANÁLISE SISTEMA (UNM): loss03. ANÁLISE SISTEMA (VOALLE): off04. EXTRATO COM QUEDAS: SIM ou NÃO05. GERENCIAMENTO REM. HABILITADO: SIM ou NÃO06. PROCEDIMENTO REALIZADO: tirou da tomada07. POTÊNCIA: xx08. CAIXA E PORTA: 1654/0108. CONTATO: (85)99975-9911-(85)98476-014509. ENDEREÇO COMPLETO: R. Itapipoca, 80 - Caponga - Cascavel - CE - CEP 62850000 - casa10. CONDOMÍNIO: SIM (Nome) ou NÃO10. PONTO DE REFERÊNCIA: Rua de Frente com o Hotel Jangadas11. DISPONIBILIDADE: AO SÁBADO DIA 1512. OBSERVAÇÃO: REABERTURA SOLICITADO PELA GESTÃO DE O.S
A13: 3840858 | B13: DAVID ARAUJO ABREU | C13: Encerramento | D13: SERVIÇO - COND. | E13: Rua | F13: RUA INDUSTRIAL AMILCAR ARAUJO | G13: 856 COND. PORTAL DE LION CASA 2 | H13: Eusébio | I13: COITÉ | J13: -38828104 | K13: -3846853 | L13: PAULO ROBERTO ARAUJO GALVAO | M13: LARISSA MOURA DAS NEVES | N13: 46260 | O13: 46263 | P13: 46266 | Q13: 46266 | R13: Sim | S13: 3 | T13: Cliente Condomínio | U13: Serviço | V13: Realocação de Equipamento | W13: Taxa Faturada | X13: Troca Conector - Desgastado | AA13: OLT Eusébio 2 VLAN 58 | AB13: 🚧⚠️ *SERVIÇO* ⚠️🚧*Chegada**Saída**Data* 01.09.2026*SUPORTE**COMERCIAL* *Técnico* Paulo Roberto / Felipe Soares *Cliente* DAVID ARAUJO ABREU*Endereço* RUA INDUSTRIAL AMILCAR ARAUJO, 856 COND. PORTAL DE LION CASA 2, COITÉ - Eusébio*obs sobre o endereço* COND. PORTAL DE LION CASA 2*CONTATO* *Caixa* 6317*PORTA* 09*SINAL DO CAIXA*-21*SINAL DO CLIENTE*-22*Velocidade* *Material utilizado*1 Conector Verde 1 Conector Azul6 Fixa fixo 0 canaleta0 Esticado1 adesivo 0 Per Cord0 RJ45PROBLEMA RELATADO: OBS. Realizada visita técnica para realocação de equipamento.Equipamento realocado para onde o cliente pediu.*TAXA: R$75,00 em 2X*Cabo de redeInicial Final Metragem *SENHA DO EQUIPAMENTO**Equipamento anterior**Equipamento Atual* *MEC* *Drop inicial* 292*Drop Final* 200*Metragem* 092*Classificação de Encerramento*RESOLVIDO✅Dispositivo: motorola moto g04sVersão do Android: 14Versão do V·Tasks: 5.9.203 Status alterado de Andamento para Encerramento | AC13: 26/08/2026 - 13:10 1.SOLICITAÇÃO: deseja realocar o equipamento para outro cômodo3.CONTATO TELEFÔNICO (01): 85994195404FONE 02(WHATSAPP) 859941954044.E-MAIL: CONTACT@ARAUJODAVID.COM5.WHATSAPP: 859941954046.PONTO DE REFERÊNCIA: Rua Industrial Amilcar Araujo 856, Casa 2 / Cond. Portal de Lion // Entrando na rua do Colégio Antares7.DISPONIBILIDADE: o dia todo8.VALOR DO SERVIÇO / FORMA DE PAGAMENTO E VALORES: R$75,00 em 2x9.PRAZO: 5 DIAS CORRIDOS 10.OBS FINAIS:
A14: 3841052 | B14: MIRIAN DE SOUZA DOS SANTOS | C14: Encerramento | D14: SERVIÇO - PF | E14: Rua | F14: RUA MARIANA MENDES | G14: 234 | H14: Guaiúba | I14: PINHEIRO | J14: -4.043295e+15 | K14: -3.863941e+15 | L14: LUCIEUDO BANDEIRA ALVES FILHO | M14: MARIA ENILANE DA SILVA SOUZA ALMEIDA | N14: 46260 | O14: 46263 | P14: 46266 | Q14: 46266 | R14: Sim | S14: 3 | T14: Cliente Pessoa Física | U14: Serviço | V14: Configuração de Repetidor | W14: Taxa Faturada | X14: Troca Conector - Desgastado | AA14: OLT Guaiúba VLAN 2109 | AB14: 🪜🧰 PENDÊNCIA 🧰🪜*Data:* 01/09/2026*Técnico:* Lucieldo Bandeira*Cliente:* MIRIAN DE SOUZA DOS SANTOS*Endereço* RUA MARIANA MENDES, 234, PINHEIRO - Guaiúba*Material utilizado*02 RJ4510 FIXA FIO 23 m de cabo utp *Obs:* RELOCAÇÃO DE EQUIPAMENTO FEITA PRA ONDE O CLIENTE PEDIU 40 reais da visita técnica conforme tem na o.s*Classificação de Encerramento:* Resolvido ✅Dispositivo: motorola moto g04Versão do Android: 14Versão do V·Tasks: 5.9.211 Status alterado de Reagendado para Encerramento | AC14: 26/08/2026 - 14:46 1.SOLICITAÇÃO: cliente solicita que seu repetidor seja realocado3.CONTATO TELEFÔNICO (01): 85987012954FONE 02(WHATSAPP) 859870129544.E-MAIL: my86917894@gmail.com5.WHATSAPP: 859870129546.PONTO DE REFERÊNCIA: Rua: Mariana Mendes N:234 CasaDepois do primeiro quebra mola7.DISPONIBILIDADE: sim 8.VALOR DO SERVIÇO / FORMA DE PAGAMENTO E VALORES: R$ 40,00 + Cabo de rede (CAT 5): R$2,00 + (metro) Conector (RJ45): R$2,00 (unidade)9.PRAZO: 5 DIAS CORRIDOS10.OBS FINAIS:
A15: 3841136 | B15: MOISES ARAUJO DE SOUSA | C15: Encerramento | D15: PENDÊNCIA FIBRA - PF | E15: Rua | F15: Rua José Baltazar de Queiroz | G15: 167 | H15: Choró | I15: Alto do cruzeiro | J15: -4.8448441e+15 | K15: -3.9134194e+15 | L15: ANTONIO TIAGO AMANCIO DA SILVA | M15: KAROL HELLEN DE ALMEIDA SILVA | N15: 46260 | O15: 46261 | P15: 46268 | Q15: 46268 | R15: Sim | S15: 7 | T15: Cliente Pessoa Física | U15: Pendência | V15: Teste de Velocidade | W15: Validação de Serviço/Velocidade | X15: Troca Conector - Desgastado | AA15: OLT Choro VLAN 4004 | AB15: ♦️ *PENDÊNCIA* ♦️*Data:* 03/09/2026*Técnico:* Tiago*Auxiliar:* Amaury *Cliente:* MOISES ARAUJO DE SOUSA*Endereço:* Rua José Baltazar de Queiroz, 167, Alto*Classificação de Encerramento:*RESOLVIDOTESTE FEITO, SEM NENHUM DEFEITO OU PROBLEMA, TUDO OPERANDO NORMAL Dispositivo: Xiaomi 23100RN82LVersão do Android: 15Versão do V·Tasks: 5.9.211 Status alterado de Agendado para Encerramento | AC15: 26/08/2026 - 15:40 01. RELATO DO CLIENTE: cliente relata que não esta conseguindo abrir alguns aplicativos por conta da lentidão e oscilação do wifi , feito as configurações mas continuou da mesma forma02. ANÁLISE SISTEMA (UNM):online03. ANÁLISE SISTEMA (VOALLE):online04. EXTRATO COM QUEDAS: NÃO05. GERENCIAMENTO REM. HABILITADO: SIM 06. PROCEDIMENTO REALIZADO:vconfigurações07. POTÊNCIA:25.23 08. CAIXA E PORTA:cx7859 p-1008. CONTATO:88 99743702409. ENDEREÇO COMPLETO:Rua José Baltazar de Queiroz 167, Alto do cruzeiro - Choró, CE10. CONDOMÍNIO: uNÃO10. PONTO DE REFERÊNCIA:Próxima da casa do sr Lauro Casa grande de varanda11. DISPONIBILIDADE:sim , dia todo12. OBSERVAÇÃO:
A16: 3841282 | B16: FRANCISCA IVANILDA INACIO RIBEIRO | C16: Encerramento | D16: INSTALAÇÃO FIBRA - COND. | E16: Rua | F16: Rua João de Castro | G16: 555 | H16: Aquiraz | I16: Loteamento Bela Vista do Sul | J16: -3916617 | K16: -38383185 | L16: HALLEF GUILHERME LIMA CLEMENTE SILVA | M16: VANESSA DA COSTA ABREU | N16: 46260 | O16: 46261 | P16: 46266 | Q16: 46266 | R16: Sim | S16: 5 | T16: Cliente Condomínio | U16: Instalação | X16: Troca Conector - Desgastado | AA16: OLT Aquiraz VLAN 12 | AB16: 🛠 *INSTALAÇÃO* 🧰*Data:* 01/09/2026 *Técnico:* Hallef / Ismael*Cliente:* FRANCISCA IVANILDA INACIO RIBEIRO*Endereço:* Rua João de Castro, 555, Loteamento Bela Vista do Sul - Aquiraz Condomínio Monte Carmelhttps://maps.app.goo.gl/jNvGd6RSEewt1Ths8 *Potência:* -22*Caixa:* 10545*porta*: 16*MATERIAL USADO* Conector verde 2und Conector azulAdesivoPetcord Fixa fio 5und Canaleta EQUIPAMENTOS * Ont : FHTTFE258C38* Roteador.* ONU *inicial:* 495*Final:* 340*Metragem:* 155m *Serviço Realizado:* Instalação Feito os testes com o cliente.*Classificação de Encerramento:* Instalação Concluída.Dispositivo: motorola moto g04sVersão do Android: 14Versão do V·Tasks: 5.9.211 Status alterado de Reagendado para Encerramento | AC16: VENDEDOR: Vanessa AbreuÁREA: PAP () CALL-CENTER ( ) LOJA (x ) TBR ( )TITULAR: FRANCISCA IVANILDA INACIO RIBEIROTELEFONE: 85988972277WHATSAPP: 85988972277DISPONIBILIDADE: MANHA( ) TARDE ( ) DIA TODO (X)DATA: 27/08/2026CIDADE E BAIRRO: R. João de Castro, 555 (1° Andar- Apt 101) - Lot. Bela Vista do Sul, Aquiraz (Cond. Monte Carmel).PLANO: 500mbVALOR ORIGINAL DO PLANO: 99,99POSSUI DESCONTO DE PONTUALIDADE? SIM ( ) NÃO (x )SE SIM: D5 ( ) ou DNET - D10( )DESCONTO DE __ , SE PAGO ATÉ O VENCIMENTO POR 12 MESESTAXA INSTALAÇÃO: GrátisATENDIMENTO REGISTRADO:Google Drive ( ) Fortics ( ) Smart ( ) Voalle (x)FIDELIDADE: ( x) SIM NÃO ( )CLIENTE DESEJA NOTA FISCAL: SIM ( ) NÃO (x )COORD: -3.916639, -38.383238 CAIXA: 8221/82-8222-47177CASA DUPLEX ( ) CASA TERREA () Condomínio (x)QUANTOS E QUAIS APARELHOS CONECTADOS: 1 tv e 2 cellOBSERVAÇÃO ADICIONAL: Entrar em contato antes de ir.Ativação do contrato: 174015---- Endereço de Instalação ----CEP: 61700-000Logradouro: Rua João de CastroNúmero: 555Bairro: Loteamento Bela Vista do SulEstado: CECidade: AquirazComplemento: Condomínio 1° Andar Apt 101Referência: Fica no Cond Monte Carmel, Próximo a Escola Maria Margarida Ramos---- Serviços a serem ativados ----- 0422 - ULTRAINFO - 500MB
A17: 3841470 | B17: EDINEIDE DE SOUZA ABREU | C17: Encerramento | D17: SERVIÇO - COND. | E17: Rua | F17: Rua Otoni Sá | G17: 288 | H17: Eusébio | I17: Mangabeira | J17: -3.8408088e+15 | K17: -3.8427609e+16 | L17: PAULO ROBERTO ARAUJO GALVAO | M17: SUZETTE CARNEIRO LIMA DE SOUZA | N17: 46260 | O17: 46263 | P17: 46266 | Q17: 46266 | R17: Sim | S17: 3 | T17: Cliente Condomínio | U17: Serviço | V17: Configuração de Repetidor | W17: Taxa Isenta | X17: Troca Conector - Desgastado | AA17: OLT Eusébio 2 VLAN 58 | AB17: 🚧⚠️ *SERVIÇO* ⚠️🚧*Chegada**Saída**Data* 01.09.2026*SUPORTE**COMERCIAL* *Técnico* Paulo Roberto / Felipe Soares *Cliente* EDINEIDE DE SOUZA ABREU*Endereço* Rua Otoni Sá, 288, Mangabeira - Eusébio*obs sobre o endereço* Mangabeira*CONTATO* *Caixa* *PORTA* *SINAL DO CAIXA**SINAL DO CLIENTE**Velocidade* *Material utilizado*0 Conector Verde 0 Conector Azul0 Fixa fios 0 canaleta0 Esticado0 adesivo 0 Per Cord0 RJ45PROBLEMA RELATADO: Foi solicitado visita técnica para manutenção no repetidor de sinal da sala, roteador foi reconfigurado, alterada algumas configurações e a conexão foi restabelecida.Após procedimentos foram realizados testes junto a cliente e navegou normalmente em todos os dispositivos.OBS. *TAXA:* *Isenta*Cabo de redeInicial 000Final 000Metragem 000*SENHA DO EQUIPAMENTO**Equipamento anterior**MAC* *Equipamento Atual* *MAC* *Drop inicial* *Drop Final* *Metragem**Classificação de Encerramento*RESOLVIDO✅Dispositivo: motorola moto g04sVersão do Android: 14Versão do V·Tasks: 5.9.203 Status alterado de Reagendado para Encerramento | AC17: 26/08/2026 - 17:16 1.SOLICITAÇÃO: cliente informa que o seu repetidor não está aparecendo a rede3.CONTATO TELEFÔNICO (01): 85987404993 (85)98526-1251FONE 02(WHATSAPP) 85987404993 (85)99408-41314.E-MAIL: claudianaalvesroqueroque@gmail.com5.WHATSAPP: 859874049936.PONTO DE REFERÊNCIA: prox ao seu esfirra7.DISPONIBILIDADE: total8.VALOR DO SERVIÇO / FORMA DE PAGAMENTO E VALORES: Verificar no Guia Ultra e insira aqui as informações. Taxa Isenta9.PRAZO: 5 DIAS CORRIDOS 10.OBS FINAIS:
A18: 3842107 | B18: KARINA CARVALHO DOS SANTOS | C18: Encerramento | D18: PENDÊNCIA FIBRA - PF | E18: Rua | F18: RUA ARABAIANA | G18: 69 | H18: Fortaleza | I18: Barra do Ceará | L18: FRANCISCO JHONATA DA COSTA | M18: MARIANA ABREU DA SILVA | N18: 46261 | O18: 46262 | P18: 46266 | Q18: 46266 | R18: Sim | S18: 4 | T18: Cliente Pessoa Física | U18: Pendência | V18: LOS | W18: Fibra Sem Sinal / Luz Los Vermelha | X18: Troca Conector - Desgastado | AA18: OLT Barra do Ceará VLAN 1001 | AB18: *PENDENCIA**Data* 01/09/2026*Técnico* Jhonata CLIENTE:KARINA CARVALHO DOS SANTOSENDERECO:RUA ARABAIANA, 69, Barra do Ceará - Fortaleza*Caixa* :Giga*Porta*:*SINAL DA CAIXA*.-17*SINAL DO CLIENTE*-17SERVIÇO REALIZADO Feito Troca dos dois conectores Apc na Cto e Upc na Onu...01Conector Verde01Conector Azul00Fixa fio00 Canaleta00 Esticador01Adesivo conector00 RJ4500 pat Cord00 ONU XPON AX 180000 Roteador Mercusis *OBS* : Normalizada, Internet ok.. Login:multiproSenha:multipro*VALOR* :*Cabo inicial*:*Cabo final* *Metragem* *Drop inicial*:0000*Drop final* : 0000*Metragem*0000Dispositivo: samsung SM-A075MVersão do Android: 16Versão do V·Tasks: 5.9.206 Status alterado de Remarcação para Encerramento | AC18: 27/08/2026 - 10:14 01. RELATO DO CLIENTE: SEM INTERNET,NAO TEM LED PISCANDO VERMELHO02. ANÁLISE SISTEMA (UNM):OFF03. ANÁLISE SISTEMA (VOALLE):OFF04. EXTRATO COM QUEDAS: SIM ou NÃO05. GERENCIAMENTO REM. HABILITADO: SIM ou NÃO06. PROCEDIMENTO REALIZADO:TIROU DA TOMADA07. POTÊNCIA:X08. CAIXA E PORTA:2612/0808. CONTATO:(85)99216-134309. ENDEREÇO COMPLETO:RUA ARABAIANA, 69 - Barra do Ceará - Fortaleza - CE - CEP 60332-41010. CONDOMÍNIO: SIM (Nome) ou NÃO10. PONTO DE REFERÊNCIA:Próximo a rua da feira11. DISPONIBILIDADE:O DIA TODO, POREM PEDE URGENCIA POIS TRABALHA EM HOMEOFFICE12. OBSERVAÇÃO:
A19: 3842160 | B19: CAMILLUS DE LELLIS FREITAS DE SOUSA | C19: Encerramento | D19: PENDÊNCIA FIBRA - PF | E19: Rua | F19: Rua José Nogueira | G19: 183 | H19: Fortaleza | I19: Pedras | J19: -38888642 | K19: -385100559 | L19: MARCOS AURELIO DE SOUSA OLIVEIRA | M19: SUZANA SANTOS MOURA | N19: 46261 | O19: 46262 | P19: 46266 | Q19: 46266 | R19: Sim | S19: 4 | T19: Cliente Pessoa Física | U19: Pendência | V19: LOS | W19: Fibra Sem Sinal / Luz Los Vermelha | X19: Troca Conector - Desgastado | AA19: OLT Jabuti VLAN 1000 | AB19: *Manutenção* *Data* 01. 09.2026*Técnico*: Marcos Aurélio*CLIENTE* CAMILLUS DE LELLIS FREITAS DE SOUSA *ENDEREÇO* Rua José Nogueira, 183, Pedras - Fortaleza*Caixa*: 11930*Porta*: 12*SINAL DA CAIXA*: 24*SINAL DO CLIENTE*: 24*SERVIÇO REALIZADO:* Manutenção *Material utilizado*02 Conector Verde00 Conector Azul00 Fixa fio00 Canaleta00 Esticador00 Adesivo conector 00 RJ4500 patch cord*Equipamento utilizado**Equipamentos retirados* *Obs*: drop atenuado, desfeito atenuação.*VALOR*:*Cabo inicial* *Cabo final* *Metragem*Dispositivo: samsung SM-A075MVersão do Android: 16Versão do V·Tasks: 5.9.211 Status alterado de Agendado para Encerramento | AC19: 27/08/2026 - 10:43 01. RELATO DO CLIENTE: Cliente sem conexão, luz vermelha piscando no equipamento, alarme link loss no unm02. ANÁLISE SISTEMA (UNM): link loss03. ANÁLISE SISTEMA (VOALLE): off04. EXTRATO COM QUEDAS: xx05. GERENCIAMENTO REM. HABILITADO: xx06. PROCEDIMENTO REALIZADO: reboot07. POTÊNCIA: xx08. CAIXA E PORTA: 11930/0208. CONTATO: (85)98510-0521- (85)99701-704709. ENDEREÇO COMPLETO:Rua José Nogueira, 183 - Pedras (3° casa)10. CONDOMÍNIO: NÃO10. PONTO DE REFERÊNCIA:Próximo ao posto de saúde / Está tendo obra da prefeitura bem em frente. Então tem um pedaço da rua interditada 11. DISPONIBILIDADE: total12. OBSERVAÇÃO:Está tendo obra da prefeitura bem em frente. Então tem um pedaço da rua interditada
A20: 3842180 | B20: FRANCISCA FLAVIA GOMES DE SOUSA PONTO 02 | C20: Encerramento | D20: DNET - REPETIDOR - PF | E20: Rua | F20: Rua Lagoa do Mato | G20: S/N | H20: Aquiraz | I20: Justiniano de Serpa | J20: -4032329 | K20: -385067652 | L20: CAIO VICTOR MONTEIRO DE OLIVEIRA | M20: RUAN VICTOR SANTOS SOUZA CLARINDO | N20: 46261 | O20: 46264 | P20: 46267 | Q20: 46267 | R20: Sim | S20: 3 | T20: DNET - Cliente Pessoa Física | U20: DNET - Repetidor | V20: DNET - Inclusão Ultra Repetidor 4.0 | W20: DNET - Faturar Material Excedente | X20: Troca Conector - Desgastado | AA20: OLT DNET TEMPORARIO | AB20: Abertura Solicitação para visita técnica no cliente, a pedido do mesmo.TÉCNICO : CAIO VICTOR CLIENTE : FRANCISCA FLAVIA GOMES DE SOUSA PONTO 02ENDEREÇO CORRETO: Rua Lagoa do Mato, S/N, Justiniano de Serpa - AquirazNº CAIXA: N º PORTA: VERIFICAÇÃO DE CX: SINAL DA CTO: SINAL DO CLIENTE: MATERIAL UTILIZADO*CONECTOR VERDE: CONECTOR AZUL: FIXA FIO: CANALETA: ESTICADOR: ADESIVO CONECTOR: RJ45: 2CABO DE REDE: 20mtEQUIPAMENTO UTILIZADO ONT (S/N) = ONU (S/N) = ROTEADOR (S/N) = DROP CABO INICIAL: DROP CABO FINAL: DROP METRAGEM: TEVE FATURAMENTO? VALOR (SE HOUVER) :SERVIÇO:Dispositivo: motorola moto g04sVersão do Android: 14Versão do V·Tasks: 5.9.211 Status alterado de Andamento para Encerramento | AC20: 27/08/2026 - 11:04 1.SOLICITAÇÃO: Inclusão Ultra Repetidor 4.02.ROTEADOR É DO CLIENTE ( ) ,COMODATO (x) OU LOCAÇÃO ( )? 3.CONTATO TELEFÔNICO (01): 85996819710. 859968527383. (WHATSAPP): 859968197104.WHATSAPP: 859968527385.PONTO DE REFERÊNCIA: Bar do lindo6.DISPONIBILIDADE: Total7.VALOR DO SERVIÇO / FORMA DE PAGAMENTO E VALORES: Mensalidade do aluguel: R$22,99Cabo de rede (até 30 metros) e conectores incluso.8.PRAZO: 5 DIAS CORRIDOS A PARTIR DA ABERTURA DO ATENDIMENTO DO NÍVEL 09.OBS FINAIS:
A21: 3842265 | B21: SYLMARA SILVA ARAUJO | C21: Encerramento | D21: DNET - PENDENCIA FIBRA - PF | E21: Rua | F21: RUA MANUEL COSTA | G21: 704 | H21: Fortaleza | I21: PAUPINA | J21: -38603951 | K21: -384912356 | L21: EVERLAN DA PENHA TOME | M21: MARCOS VINICIUS ALVES DE OLIVEIRA | N21: 46261 | O21: 46262 | P21: 46266 | Q21: 46266 | R21: Sim | S21: 4 | T21: DNET - Cliente Pessoa Física | U21: DNET - Pendência | V21: DNET - LOS | W21: DNET - Fibra Sem Sinal / Luz Los Vermelha | X21: Troca Conector - Desgastado | AA21: OLT DNET TEMPORARIO | AB21: ATIVIDADE MANUTENÇÃO ⚡Data:01/09/2026TÉCNICO: Everlan Tomé AUXILIARES:Cliente:SYLMARA SILVA ARAUJOENDEREÇO:RUA MANUEL COSTA, 704, PAUPINA - FortalezaACESSO REMOTO : Sim ( x ) Não ( )SERVIÇO: Reparo PRODUTOS:02 conector verde Obs feito troca dos conectores ont e caixaPATRIMONIO RECOLHIMENTO:DROP INICIAL DROP FINAL CAIXA : 11457PORTA: 16ACESSO REMOTO : Sim ( x ) Não ( )SERVIÇO: ReparoRECOLHIMENTOCLASSIFICAÇÃO DE ENCERRAMENTO : Finalizado✅Dispositivo: motorola moto g(9) playVersão do Android: 11Versão do V·Tasks: 5.9.211 Status alterado de Reagendado para Encerramento | AC21: 27/08/2026 - 11:25 01. RELATO DO CLIENTE: cliente relata que possui luzes verdes,sem internet e reinicia mais não conecta02. ANÁLISE SISTEMA (UNM): ofline03. ANÁLISE SISTEMA (VOALLE):ofline04. EXTRATO COM QUEDAS: NÃO05. GERENCIAMENTO REM. HABILITADO: verificar06. PROCEDIMENTO REALIZADO:reboot no equipamento07. POTÊNCIA:xxxxxxxxxxxxxxxxxxx08. CAIXA E PORTA:CX11457 P-0308. CONTATO:88 99735-1400 ou 88 99955-342009. ENDEREÇO COMPLETO:RUA MANUEL COSTA 704, PAUPINA - Fortaleza, CE60873-54010. CONDOMÍNIO: NÃO10. PONTO DE REFERÊNCIA:: Na mesma rua que a oficina HP Disel11. DISPONIBILIDADE:dia todo12. OBSERVAÇÃO:
A22: 3842528 | B22: IVANILDE DOS SANTOS MONTEIRO | C22: Encerramento | D22: INSTALAÇÃO FIBRA - PF | E22: Rua | F22: Rua Zildete da Costa | G22: 84b | H22: Fortaleza | I22: Jangurussu | J22: -38507402 | K22: -38520343 | L22: VINICIUS SILVA LEARTE | M22: VITOR CRUZ BATISTA | N22: 46261 | O22: 46262 | P22: 46266 | Q22: 46266 | R22: Sim | S22: 4 | T22: Cliente Pessoa Física | U22: Instalação | X22: Troca Conector - Desgastado | AA22: OLT Conj. Palmeiras VLAN 1002 | AB22: 🌐 *INSTALAÇÃO*🌐*Data:* 01/09/26*Atendente:* *Técnico:* Vinicius Learte *Cliente*: IVANILDE DOS SANTOS MONTEIRO*Endereço*: Rua Zildete da Costa, 84b, Jangurussu - Fortaleza*Caixa*: 7185*Porta*: 07*Potência da Caixa*: -23*Potência do cliente* :-25*Gerenciamento remoto habilitado:* SimLogin:multipro Semha:multipro *Serviço Realizado:* Instalação *Material Utilizado:*01 - ont zte (MAC)=882402 - conector verde 10 - fixa cabo01 - canaleta*MAC:* *Drop inicial*: 395m*Drop final:* 233m*Total*: 162m*Valor:* Instalação gratuita *Obs:**Classificação de Encerramento:* Resolvido ✅Dispositivo: samsung SM-A075MVersão do Android: 16Versão do V·Tasks: 5.9.211 Status alterado de Reagendado para Encerramento | AC22: VENDEDOR: VITOR CRUZ BATISTA ÁREA: PAP (X) CALL-CENTER ( ) LOJA ( ) TBR ( )TITULAR: IVANILDE DOS SANTOS MONTEIRO TELEFONE: 85 99801-3788WHATSAPP: 85 99801-3788DISPONIBILIDADE: MANHA( ) TARDE ( ) DIA TODO (x)DATA:CIDADE E BAIRRO: FORTALEZA/JANGURUSSU PLANO: 300MBVALOR ORIGINAL DO PLANO: 84,99POSSUI DESCONTO DE PONTUALIDADE? SIM ( ) NÃO (x)SE SIM: D5 ( ) ou DNET - D10( )DESCONTO DE __ , SE PAGO ATÉ O VENCIMENTO POR 12 MESESTAXA INSTALAÇÃO: 00ATENDIMENTO REGISTRADO:Google Drive ( ) Fortics ( ) Smart (x)FIDELIDADE: (x ) SIM NÃO ( )CLIENTE DESEJA NOTA FISCAL: SIM ( ) NÃO ( x)COORD: -3.850615,-38.520230 CAIXA: 1714CASA DUPLEX ( ) CASA TERREA (x)QUANTOS E QUAIS APARELHOS CONECTADOS:OBSERVAÇÃO ADICIONAL: CLIENTE AFIRMOU QUE SÓ CONSEGUE RECEBER A INSTALAÇÃO NO SÁBADO. Ativação do contrato: 174068---- Endereço de Instalação ----CEP: 60877-055Logradouro: Rua Zildete da CostaNúmero: 84bBairro: JangurussuEstado: CECidade: FortalezaComplemento: casaReferência: próximo ao mercadinho zidelte---- Serviços a serem ativados ----- 0122 - 300MB - ULTRAINFO
A23: 3842588 | B23: HELLEN LOPES DOS SANTOS | C23: Encerramento | D23: PENDÊNCIA FIBRA - PF | E23: Rua | F23: Rua Santo Antônio | G23: 14 | H23: Aquiraz | I23: Tupuiu | L23: JOSE HENRIQUE PEREIRA SOUSA | M23: JACKELINE RODRIGUES COSTA | N23: 46261 | O23: 46262 | P23: 46270 | Q23: 46270 | R23: Sim | S23: 8 | T23: Cliente Pessoa Física | U23: Pendência | V23: Potência Baixa | W23: Correção de Potência | X23: Troca Conector - Desgastado | AA23: OLT Aquiraz VLAN 12 | AB23: *PENDÊNCIA**Data:* 05/09/2026* *Técnico:* Henrique Sousa *Cliente* HELLEN LOPES DOS SANTOS*Endereço*:Rua Santo Antônio, 14, Tupuiu - Aquiraz*Caixa* : 1373*Porta*: 05*Potência da Caixa*: -24*Potência do Cliente*: -24*Serviço realizado* ao chegar na residência foi visto que o sinal na fibra ótica estava - 27 então foi trocado o conector da CTO, assim normalizando cliente PARA -24 REFERENTE AO DA CTO.TESTES DE CONEXÃO REALIZADO JUNTO COM O CLIENTE TUDO FUNCIONANDO CORRETAMENTE.*OBS* Cliente conectado Caixa e porta que descreve na O.S. Login: Senha: *Acesso Remoto:*Ativado Material Utilizado;01 conector verde 0 azul 00 adesivo *Material Recolhido**Drop:*Início: Fim: Utilizado *Valor:* *Obs.:**Classificação de Encerramento:* Encerramento✅Dispositivo: samsung SM-A075MVersão do Android: 16Versão do V·Tasks: 5.9.213 Status alterado de Reagendado para Encerramento | AC23: 27/08/2026 - 14:11 01. RELATO DO CLIENTE: Cliente com bastante lentidão, identificado que está com potencia baixa 02. ANÁLISE SISTEMA (UNM): ON03. ANÁLISE SISTEMA (VOALLE): ON04. EXTRATO COM QUEDAS: SIM ou NÃO xx05. GERENCIAMENTO REM. HABILITADO: SIM 06. PROCEDIMENTO REALIZADO: ABERTURA DE O.S07. POTÊNCIA: -28.2408. CAIXA E PORTA: 1373 / 0508. CONTATO: (85)99217-8932 (85)98762-365309. ENDEREÇO COMPLETO: Rua Santo Antônio, 14 - Tapuio - Aquiraz - CE - CEP 61700-00010. CONDOMÍNIO: NÃO10. PONTO DE REFERÊNCIA: próx ao mercadinho Maninho11. DISPONIBILIDADE: entrar em contato antes 12. OBSERVAÇÃO:
A24: 3842740 | B24: JOSE NILSON DOS SANTOS JUNIOR | C24: Encerramento | D24: PENDÊNCIA FIBRA - PF | E24: Rua | F24: RUA 03 | G24: 131 | H24: Pacatuba | I24: Jereissati III | L24: ANTONIO RAFAEL ALEXANDRE DE SOUSA | M24: EMILY LUANY ALVES BASTOS | N24: 46261 | O24: 46262 | P24: 46266 | Q24: 46266 | R24: Sim | S24: 4 | T24: Cliente Pessoa Física | U24: Pendência | V24: Potência Baixa | W24: Correção de Potência | X24: Troca Conector - Desgastado | AA24: OLT Pacatuba VLAN 1003 | AB24: PENDÊNCIA TÉCNICAData: 01/09/2026Técnico: Rafael SousaCliente: JOSE NILSON DOS SANTOS JUNIORCaixa/Porta: CX 3103 – P08Descrição do atendimento:Cliente encontrava-se sem conexão (LOS), apresentando potência óptica baixa de -33 dBm.Após intervenção técnica, o sinal foi normalizado. Foram refeitos 2 conectores APC.Foi constatado que a tampa da CTO estava aberta, deixando a caixa exposta à poeira e à chuva. Após a intervenção, a CTO foi devidamente fechada.Cliente conectado e serviço normalizado.Configuração Wi-Fi:- Canal: 6- Largura de banda: 20 MHz- Conexão funcionando perfeitamente.Material utilizado:- 2 conectores APCStatus: Serviço concluído e conexão normalizada.Dispositivo: samsung SM-A146MVersão do Android: 15Versão do V·Tasks: 5.9.211 Status alterado de Andamento para Encerramento | AC24: 27/08/2026 - 15:46 01. RELATO DO CLIENTE: cliente com potência baixa, necessário normalizar a potência02. ANÁLISE SISTEMA (UNM): online03. ANÁLISE SISTEMA (VOALLE): Online04. EXTRATO COM QUEDAS: SIM ou NÃO x05. GERENCIAMENTO REM. HABILITADO: SIM xx ou NÃO06. PROCEDIMENTO REALIZADO: visto a potência07. POTÊNCIA: -3508. CAIXA E PORTA: cx3103 p0808. CONTATO: 85992264666+55 85 99267-284009. ENDEREÇO COMPLETO: RUA 03, 131 - Jereissati III - Pacatuba - CE - CEP 6180000010. CONDOMÍNIO: SIM (Nome) ou NÃO x10. PONTO DE REFERÊNCIA: Prox a delegacia das mulheres11. DISPONIBILIDADE: o dia todo 12. OBSERVAÇÃO:
A25: 3842759 | B25: IVONE ALEXANDRE CARNEIRO | C25: Encerramento | D25: PENDÊNCIA FIBRA - COND. | E25: Rua | F25: R. Valdemiro Barros | G25: 157 | H25: Eusébio | I25: Barrocão | J25: -3926093 | K25: -385063332 | L25: ELISSON PEREIRA COUTINHO NOVAIS | M25: IAGO FROTA SILVA | N25: 46261 | O25: 46262 | P25: 46266 | Q25: 46266 | R25: Sim | S25: 4 | T25: Cliente Condomínio | U25: Pendência | V25: LOS | W25: Fibra Sem Sinal / Luz Los Vermelha | X25: Troca Conector - Desgastado | AA25: OLT Jabuti VLAN 1000 | AB25: ⛔️PENDÊNCIA ⛔️DATA: 01/08/2026TÉCNICO: ELISSONCLIENTE:IVONE ALEXANDRE CARNEIROENDEREÇO:R. Valdemiro Barros, 157, Barrocão - EusébioCAIXA: 2219 PORTA :15🔦POTÊNCIA: CTO( -25) CASA ( -25)RELATO: drop rompido feito recuo do drop pra uma caixa mais proxima acesso normalizado MATERIAL UlTILIZADO:CONECTOR AZUL: ()CONECTOR VERDE:(1)ADESIVO: ( 1 )FIXA FIO ()CANALETA : ( )RJ 45: ( )DROP: ( ) ESTICADOR ( )CABO UTP( ) EQUIPAMENTOS ONT: ROTEADOR: ONU VALOR: OBS: CLASSIFICAÇÃO DE ENCERRAMENTO: ACESSO NORMALIZADO Dispositivo: samsung SM-A065MVersão do Android: 16Versão do V·Tasks: 5.9.211 Status alterado de Andamento para Encerramento | AC25: 27/08/2026 - 15:34 01. RELATO DO CLIENTE: cliente informa que está com luz vermelha e está sem conexão02. ANÁLISE SISTEMA (UNM): link loss03. ANÁLISE SISTEMA (VOALLE): off04. EXTRATO COM QUEDAS: NÃO 05. GERENCIAMENTO REM. HABILITADO: NÃO 06. PROCEDIMENTO REALIZADO: reboot07. POTÊNCIA: xx08. CAIXA E PORTA: CX10287 P-1508. CONTATO: 8599674730209. ENDEREÇO COMPLETO:Avenida Antônio Sobreira 157, Jabuti - Eusébio, CE10. CONDOMÍNIO: sim! loja de roupas(ponto comercial)10. PONTO DE REFERÊNCIA:frente a loja di roupas11. DISPONIBILIDADE: sim12. OBSERVAÇÃO:
A26: 3842875 | B26: FRANCISCA CARLIANE PINHEIRO DA COSTA | C26: Encerramento | D26: DNET - PENDENCIA FIBRA - PF | E26: Rua | F26: POVOADO RUSSEGA | G26: SN | H26: Aquiraz | I26: JUSTINIANO DE SERPA | J26: -40020394 | K26: -384826685 | L26: CAIO VICTOR MONTEIRO DE OLIVEIRA | M26: IAGO FROTA SILVA | N26: 46261 | O26: 46262 | P26: 46266 | Q26: 46266 | R26: Sim | S26: 4 | T26: DNET - Cliente Pessoa Física | U26: DNET - Pendência | V26: DNET - LOS | W26: DNET - Fibra Sem Sinal / Luz Los Vermelha | X26: Troca Conector - Desgastado | AA26: OLT Itaitinga VLAN 2103 | AB26: Abertura Solicitação para visita técnica no cliente, a pedido do mesmo.TÉCNICO : CAIO VICTOR CLIENTE : FRANCISCA CARLIANE PINHEIRO DA COSTAENDEREÇO CORRETO: POVOADO RUSSEGA, SN, JUSTINIANO DE SERPA - AquirazNº CAIXA: N º PORTA: VERIFICAÇÃO DE CX: SINAL DA CTO: SINAL DO CLIENTE: MATERIAL UTILIZADO*CONECTOR VERDE: 2CONECTOR AZUL: FIXA FIO: CANALETA: ESTICADOR: ADESIVO CONECTOR: RJ45: CABO DE REDE: EQUIPAMENTO UTILIZADO ONT (S/N) = ONU (S/N) = ROTEADOR (S/N) = DROP CABO INICIAL: DROP CABO FINAL: DROP METRAGEM: TEVE FATURAMENTO? VALOR (SE HOUVER) :SERVIÇO:Dispositivo: motorola moto g04sVersão do Android: 14Versão do V·Tasks: 5.9.211 Status alterado de Andamento para Encerramento | AC26: 27/08/2026 - 15:54 01. RELATO DO CLIENTE: cliente informa que está com luz vermelha e está sem conexão02. ANÁLISE SISTEMA (UNM): link loss03. ANÁLISE SISTEMA (VOALLE): off04. EXTRATO COM QUEDAS: NÃO 05. GERENCIAMENTO REM. HABILITADO: NÃO 06. PROCEDIMENTO REALIZADO: reboot07. POTÊNCIA: xx08. CAIXA E PORTA: xx08. CONTATO: 558599617964509. ENDEREÇO COMPLETO:POVOADO RUSSEGA SN, JUSTINIANO DE SERPA - Aquiraz, CE10. CONDOMÍNIO: nao10. PONTO DE REFERÊNCIA:. Próximo a fazenda dr Fernando. Casa da Maria Nova.11. DISPONIBILIDADE: sim12. OBSERVAÇÃO:
A27: 3843034 | B27: MATHEUS MENDES SCHOMMER | C27: Encerramento | D27: RETRABALHO PENDÊNCIA - PF | E27: Rua | F27: Rua Elizeu Oriá | G27: 1200 | H27: Fortaleza | I27: Sapiranga-Coité | J27: -37986477 | K27: -384774152 | L27: ALEFF PEREIRA SOARES | M27: LUCAS LUCIO DOS SANTOS XAVIER | N27: 46261 | O27: 46261 | P27: 46268 | Q27: 46268 | R27: Sim | S27: 7 | T27: Cliente Pessoa Física | U27: Retrabalho | V27: LOS | W27: Fibra Sem Sinal / Luz Los Vermelha | X27: Troca Conector - Desgastado | Y27: FRANCISCO LAERTE PEREIRA RODRIGUES | Z27: 3836091 | AA27: OLT WSTC VLAN 2321 | AB27: ✅ PENDENCIA ✅*Data* 03.09.2026*Técnico* AleffCliente: MATHEUS MENDES SCHOMMERENDEREÇO:Rua Elizeu Oriá, 1200, Sapiranga-Coité - Fortaleza ⏹️ *Caixa* 10556 Porta. 01*SINAL DA CAIXA* -24*SINAL DO CLIENTE* -24*DROP COM ETIQUETA 🏷️* ☎️ *GESTÃO DE O.S* *ATENDIMENTO:* 📝 *SERVIÇO: Identificado que a potência estava baixaFeito a troca do conector da caixa potência normalizou ⚙️ *Material utilizado*01 Conector Verde00 Conector Azul00 Fixa fio00 Canaleta00 Esticador00 Adesivo conector 00 RJ4500 patch cord📡 *Equipamento utilizado 00 ONT INTEL (MAC)00 ZTE (MAC) =00 HG325AX (MAC) = 00 XC220G3 (MAC) =00 MERCUSYS (MAC) =00 SHORELINE (MAC)00 ONT TPL (MAC)=*Equipamento RMA*00 ZTE (MAC) =00 HG325AX (MAC) = 00 ONT GLOBAL (MAC) =00 ROTEADOR TPL (MAC)= 00 ROTEADOR TENDA (MAC) = 00 MERCUSYS (MAC) =00 ONU MINI (MAC) = 00 ONU APC (MAC) = *OBS***Cabo inicial* 00m*Cabo final* 00m*Metragem* 00m*Drop inicial**Drop final**Metragem**Classificação de Encerramento**RESOLVIDO✅**Status alterado de Reagendado para Encerramento* 😎 🇮🇹Dispositivo: samsung SM-A075MVersão do Android: 16Versão do V·Tasks: 5.9.213 Status alterado de Andamento para Encerramento | AC27: 27/08/2026 - 16:53 01. RELATO DO CLIENTE:Sem internet02. ANÁLISE SISTEMA (UNM): off03. ANÁLISE SISTEMA (VOALLE):iff04. TÉCNICO ULTIMO ATENDIMENTO (ADICIONAR TAMBÉM AO CHECKLIST FINAL): FRANCISCO LAERTE PEREIRA RODRIGUES05. EXTRATO COM QUEDAS: SIM06. GERENCIAMENTO REM. HABILITADO: Verificar07. PROCEDIMENTO REALIZADO:Cliente com luz vermelha, loss08. POTÊNCIA:Sem info09. CAIXA E PORTA:CX10556 P-0110. CONTATO:(85) 98127-343411. ENDEREÇO COMPLETO:Rua Elizeu Oriá , 1200 - Sapiranga-Coité12. CONDOMÍNIO: SIM (Nome) ou NÃO13. PONTO DE REFERÊNCIA:14. DISPONIBILIDADE:Dia todo15. OBSERVAÇÃO:
A28: 3843119 | B28: PAULO SERGIO DE SOUSA JUNIOR | C28: Encerramento | D28: RETRABALHO PENDÊNCIA - PF | E28: Rua | F28: Rua Pereira Coutinho | G28: 20 | H28: Fortaleza | I28: Pedras | J28: -3897456 | K28: -385164136 | L28: MARCOS AURELIO DE SOUSA OLIVEIRA | M28: MARIA ENILANE DA SILVA SOUZA ALMEIDA | N28: 46261 | O28: 46261 | P28: 46266 | Q28: 46266 | R28: Sim | S28: 5 | T28: Cliente Pessoa Física | U28: Retrabalho | V28: LOS | W28: Fibra Sem Sinal / Luz Los Vermelha | X28: Troca Conector - Desgastado | Y28: ELIZEU DA SILVA FERREIRA | Z28: 3841047 | AA28: OLT Jabuti VLAN 1000 | AB28: *Manutenção* *Data* 01. 09.2026*Técnico*: Marcos Aurélio*CLIENTE* PAULO SERGIO DE SOUSA JUNIOR*ENDEREÇO* Rua Pereira Coutinho, 20, Pedras - Fortaleza*Caixa*: 2652*Porta*: 01*SINAL DA CAIXA*: 24*SINAL DO CLIENTE*: 24*SERVIÇO REALIZADO:* Manutenção *Material utilizado*02 Conector Verde00 Conector Azul00 Fixa fio00 Canaleta00 Esticador00 Adesivo conector 00 RJ4500 patch cord*Equipamento utilizado*Ns: 17c3*Equipamentos retirados* Ns:1dec*Obs*: drop atenuado, desfeito troca pasado u. Novo*VALOR*:*Cabo inicial* 319*Cabo final* 183*Metragem*136Dispositivo: samsung SM-A075MVersão do Android: 16Versão do V·Tasks: 5.9.211 Status alterado de Reagendado para Encerramento | AC28: 27/08/2026 - 17:45 01. RELATO DO CLIENTE: Cliente sem internet; verificado que o equipamento apresenta LED vermelho piscando.02. ANÁLISE SISTEMA (UNM): link loss03. ANÁLISE SISTEMA (VOALLE): off-line 04. TÉCNICO ULTIMO ATENDIMENTO (ADICIONAR TAMBÉM AO CHECKLIST FINAL): 3841047ELIZEU DA SILVA FERREIRA05. EXTRATO COM QUEDAS: NÃO 06. GERENCIAMENTO REM. HABILITADO: off-line 07. PROCEDIMENTO REALIZADO: reboot08. POTÊNCIA: link loss09. CAIXA E PORTA: 11483/0710. CONTATO: 8599911528111. ENDEREÇO COMPLETO: Rua Pereira Coutinho 20, Pedras - Fortaleza, CE12. CONDOMÍNIO: NÃO 13. PONTO DE REFERÊNCIA: não possui14. DISPONIBILIDADE: sim15. OBSERVAÇÃO:
A29: 3843126 | B29: FRANCISCA RENATA DO NASCIMENTO GADELHA | C29: Encerramento | D29: PENDÊNCIA FIBRA - COND. | E29: Rua | F29: Rua José Carlos Gadelha | G29: s/n | H29: Aquiraz | I29: Tapera | J29: -39510419 | K29: -383493466 | L29: HALLEF GUILHERME LIMA CLEMENTE SILVA | M29: FRANCISCA ALICE MESQUITA FERREIRA | N29: 46261 | O29: 46262 | P29: 46266 | Q29: 46266 | R29: Sim | S29: 4 | T29: Cliente Condomínio | U29: Pendência | V29: LOS | W29: Fibra Sem Sinal / Luz Los Vermelha | X29: Troca Conector - Desgastado | AA29: OLT Tapera VLAN 1009 | AB29: *PENDÊNCIA**Data:* 01/09/2026 *ATENDENTE:**Técnico:* Hallef / Ismale*CLIENTE* FRANCISCA RENATA DO NASCIMENTO GADELHA*ENDEREÇO* Rua José Carlos Gadelha, s/n, Tapera - AquirazMinus Doce ( loja ) https://maps.app.goo.gl/7PojxHPYXSnN8nEu9*Caixa:* 4962*Porta:* 16*Potência da Caixa:* - 21*Potência do Cliente:*-22*Serviço*Potencia alterada -44Realizado troca de conectores Potencia normalizada *Materiais* *conector azul:* *conector verde:* 2und *Fixa fio* *adesivo**canaleta**RJ 45**EQUIPAMENTOS**ONT*: *ROTEADOR* *ONU**DROP**Início* *Fim* *Utilizado**EQUIPAMENTO RECOLHIDO**Valor:**Obs.:*Dispositivo: motorola moto g04sVersão do Android: 14Versão do V·Tasks: 5.9.211 Status alterado de Andamento para Encerramento | AC29: 27/08/2026 - 17:42 01. RELATO DO CLIENTE: ROTEADOR COM LED VERMELHA, NO SEU PONTO COMERCIAL.02. ANÁLISE SISTEMA (UNM): LOSS03. ANÁLISE SISTEMA (VOALLE): OFFLINE04. EXTRATO COM QUEDAS: NÃO 05. GERENCIAMENTO REM. HABILITADO: SIM06. PROCEDIMENTO REALIZADO: REBOOT DA TOMADA07. POTÊNCIA: NÃO LOCALIZADO UNM08. CAIXA E PORTA: NÃO LOCALIZADO UNM08. CONTATO: 85989253379 ARTUR09. ENDEREÇO COMPLETO: Rua José Carlos Gadelha s/n, Tapera - Aquiraz, CE61700-00010. CONDOMÍNIO: NÃO 10. PONTO DE REFERÊNCIA: MERCEARINHA ARTUZINHO NO CENTRO DA TAPERA, MIMOS DOCE.11. DISPONIBILIDADE: O DIA TODO 12. OBSERVAÇÃO: LIGAR ANTES DE IR
A30: 3843164 | B30: PAULO DE SOUSA SILVA | C30: Encerramento | D30: DNET - PENDENCIA FIBRA - PF | E30: Rua | F30: RUA TEREZA DE MARCIA | G30: 470 | H30: Fortaleza | I30: PAUPINA | J30: -38546265 | K30: -38485656 | L30: EVERLAN DA PENHA TOME | M30: IAGO FROTA SILVA | N30: 46261 | O30: 46262 | P30: 46266 | Q30: 46266 | R30: Sim | S30: 4 | T30: DNET - Cliente Pessoa Física | U30: DNET - Pendência | V30: DNET - LOS | W30: DNET - Fibra Sem Sinal / Luz Los Vermelha | X30: Troca Conector - Desgastado | AA30: OLT DNET TEMPORARIO | AB30: ATIVIDADE MANUTENÇÃO ⚡Data:01/09/2026TÉCNICO: Everlan Tomé AUXILIARES:Cliente:PAULO DE SOUSA SILVAENDEREÇO:RUA TEREZA DE MARCIA, 470, PAUPINA - FortalezaACESSO REMOTO : Sim ( x ) Não ( )SERVIÇO: Reparo PRODUTOS:02 conector verde Obs feito troca dos conectores int e cauxaPATRIMONIO RECOLHIMENTO:DROP INICIAL DROP FINAL CAIXA : 11130PORTA: 12ACESSO REMOTO : Sim ( x ) Não ( )SERVIÇO: ReparoRECOLHIMENTOCLASSIFICAÇÃO DE ENCERRAMENTO : Finalizado✅Dispositivo: motorola moto g(9) playVersão do Android: 11Versão do V·Tasks: 5.9.211 Status alterado de Andamento para Encerramento | AC30: 27/08/2026 - 18:34 01. RELATO DO CLIENTE: cliente informa que está com luz vermelha e está sem conexão02. ANÁLISE SISTEMA (UNM): link loss03. ANÁLISE SISTEMA (VOALLE): off04. EXTRATO COM QUEDAS: NÃO 05. GERENCIAMENTO REM. HABILITADO: NÃO 06. PROCEDIMENTO REALIZADO: reboot07. POTÊNCIA: xx08. CAIXA E PORTA: cx 11130 p1508. CONTATO: 85989015189 /8599212285909. ENDEREÇO COMPLETO:RUA TEREZA DE MARCIA 470, PAUPINA - Fortaleza, CE10. CONDOMÍNIO: nao10. PONTO DE REFERÊNCIA:Ponto de referência associação danilo pinto11. DISPONIBILIDADE: sim12. OBSERVAÇÃO:
A31: 3843182 | B31: MARIA DO SOCORRO DE BRITO | C31: Encerramento | D31: PENDÊNCIA FIBRA - PF | E31: Rua | F31: Rua Dona Mendinha | G31: 600 | H31: Fortaleza | I31: Cristo Redentor | J31: -3.708095e+15 | K31: -3.8569735e+15 | L31: ELIZEU DA SILVA FERREIRA | M31: MEIRIANNE PEREIRA DE ANDRADE | N31: 46261 | O31: 46262 | P31: 46269 | Q31: 46269 | R31: Sim | S31: 7 | T31: Cliente Pessoa Física | U31: Pendência | V31: LOS | W31: Fibra Sem Sinal / Luz Los Vermelha | X31: Troca Conector - Desgastado | AA31: OLT Barra do Ceará VLAN 1001 | AB31: *PENDÊNCIA**Data* 04/09/2026*Técnico* ELIZEU DA SILVA FERREIRA CLIENTE: MARIA DO SOCORRO DE BRITOENDEREÇO: Rua Dona Mendinha, 600, Cristo Redentor - Fortaleza*Caixa*:*Porta*:*SINAL DA CAIXA*.*SINAL DO CLIENTE*.SERVIÇO REALIZADO Troca de drop cortado *Material utilizado*01Conector Verde00Conector Azul00 Fixa fio00 Canaleta00Esticador00Adesivo conector00 RJ4500 pat Cord00 ONT ZTE00 Repetidor Mercuses00 ont intelbras fiberhome*OBS* : Internet ok cliente.Login:Senha:*VALOR* :*Cabo inicial*:*Cabo final* *Metragem* *Drop inicial*:0215*Drop final* : 0125*Metragem*:0090Dispositivo: samsung SM-A065MVersão do Android: 16Versão do V·Tasks: 5.9.213 Status alterado de Remarcação para Encerramento | AC31: 27/08/2026 - 18:22 01. RELATO DO CLIENTE: Cliente relata sem internet /piscando vermelho no equipamento02. ANÁLISE SISTEMA (UNM): link loss03. ANÁLISE SISTEMA (VOALLE): offline 04. EXTRATO COM QUEDAS: NÃO 05. GERENCIAMENTO REM. HABILITADO: VERIIFCAR E HABILITAR06. PROCEDIMENTO REALIZADO: x07. POTÊNCIA: x08. CAIXA E PORTA: x08. CONTATO: (85)99241-5557\8599776207109. ENDEREÇO COMPLETO: Rua Dona Mendinha 600, Cristo Redentor10. CONDOMÍNIO: NÃO 10. PONTO DE REFERÊNCIA: proximo em cima deposto11. DISPONIBILIDADE: dia todo12. OBSERVAÇÃO:
A32: 3843234 | B32: FRANCISCO COSMO BARBOSA DA SILVA | C32: Encerramento | D32: INSTALAÇÃO FIBRA - PF | E32: Rua | F32: Rua 91 | G32: 144 | H32: Pacatuba | I32: Senador Carlos Jereissati | J32: -3887292 | K32: -386076005 | L32: FRANCISCO DIEGO ALVES FERREIRA | M32: MARIA LEIDIVANIA DA SILVA RAMOS | N32: 46261 | O32: 46265 | P32: 46272 | Q32: 46272 | R32: Sim | S32: 7 | T32: Cliente Pessoa Física | U32: Instalação | X32: Troca Conector - Desgastado | AA32: OLT Pacatuba VLAN 1003 | AB32: ☑️☑️ *INSTALAÇÃO* ☑️☑️*Chegada**Saída**Data* 07.09.2026*SUPORTE**COMERCIAL**Técnico* Francisco Diego *Cliente* FRANCISCO COSMO BARBOSA DA SILVA*ENDEREÇO* Rua 91, 144, Senador Carlos Jereissati - Pacatuba*Caixa*3039*Porta* 3*SINAL DA CAIXA* 23*SINAL DO CLIENTE* 23*Velocidade**Material utilizado* 2 Conector Verde 0 Conector Azul5 Fixa fio0 Canaleta0 Esticador0 Adesivo conector Black0 RJ450 Cabo de rede*OBS* *VALOR* *SENHA* *MAC* intel 01*Drop inicial* 873*Drop final* 803*Metragem*70*Classificação de Encerramento*RESOLVIDO✅Dispositivo: samsung SM-A346MVersão do Android: 16Versão do V·Tasks: 5.9.213 Status alterado de Remarcação para Encerramento | AC32: VENDEDOR: LEIDIVANIA RAMOS ÁREA: PAP () CALL-CENTER ( ) LOJA ( ) TBR (X )TITULAR: FRANCISCO COSMO BARBOSA DA SILVATELEFONE: 85920033498WHATSAPP: 85920033498DISPONIBILIDADE: MANHA( ) TARDE (X ) DIA TODO ()DATA: 27.08.2026CIDADE E BAIRRO: CARLOS JEREISSATI2 - PACATUBA PLANO: 500MBVALOR ORIGINAL DO PLANO: 99,99POSSUI DESCONTO DE PONTUALIDADE? SIM ( ) NÃO (X )SE SIM: D5 ( ) ou DNET - D10( )DESCONTO DE __ , SE PAGO ATÉ O VENCIMENTO POR 12 MESESTAXA INSTALAÇÃO: GRATISATENDIMENTO REGISTRADO:Google Drive ( ) Fortics ( ) Smart ( X)FIDELIDADE: (X ) SIM NÃO ( )CLIENTE DESEJA NOTA FISCAL: SIM ( ) NÃO ( X)COORD: -3.88725685871609, -38.60754787567443CAIXA: cx3039CASA DUPLEX ( ) CASA TERREA (X)QUANTOS E QUAIS APARELHOS CONECTADOS: TV E CELULAR OBSERVAÇÃO ADICIONAL:Ativação do contrato: 174102---- Endereço de Instalação ----CEP: 61814-156Logradouro: Rua 91Número: 144Bairro: Senador Carlos JereissatiEstado: CECidade: PacatubaComplemento: casaReferência: Mercantil super ideal---- Serviços a serem ativados ----- 0422 - IFT - ULTRAINFO - 500MB
A33: 3843261 | B33: MARIA SIMONE RIBEIRO DE LIMA | C33: Encerramento | D33: DNET - PENDENCIA FIBRA - PF | E33: Rua | F33: Rua Nova Canaa de Serpa | G33: SN | H33: Aquiraz | I33: Justiniano de Serpa | L33: CAIO VICTOR MONTEIRO DE OLIVEIRA | M33: EMILY LUANY ALVES BASTOS | N33: 46261 | O33: 46262 | P33: 46268 | Q33: 46266 | R33: Sim | S33: 6 | T33: DNET - Cliente Pessoa Física | U33: DNET - Pendência | V33: DNET - LOS | W33: DNET - Fibra Sem Sinal / Luz Los Vermelha | X33: Troca Conector - Desgastado | AA33: OLT DNET TEMPORARIO | AB33: Abertura Solicitação para visita técnica no cliente, a pedido do mesmo.TÉCNICO : CAIO VICTOR CLIENTE : MARIA SIMONE RIBEIRO DE LIMAENDEREÇO CORRETO: Rua Nova Canaa de Serpa, SN, Justiniano de Serpa - AquirazNº CAIXA: N º PORTA: VERIFICAÇÃO DE CX: SINAL DA CTO: SINAL DO CLIENTE: -24MATERIAL UTILIZADO*CONECTOR VERDE: 2CONECTOR AZUL: FIXA FIO: CANALETA: ESTICADOR: ADESIVO CONECTOR: RJ45: CABO DE REDE: EQUIPAMENTO UTILIZADO ONT (S/N) = ONU (S/N) = ROTEADOR (S/N) = DROP CABO INICIAL: 542DROP CABO FINAL: 414DROP METRAGEM: 127TEVE FATURAMENTO? VALOR (SE HOUVER) :SERVIÇO:Dispositivo: motorola moto g04sVersão do Android: 14Versão do V·Tasks: 5.9.211 Status alterado de Reagendado para Encerramento | AC33: 27/08/2026 - 20:33 01. RELATO DO CLIENTE: , offline no voalle, led vermelha no roteador02. ANÁLISE SISTEMA (UNM): não encontrado03. ANÁLISE SISTEMA (VOALLE): Offline04. EXTRATO COM QUEDAS: SIM ou NÃO x05. GERENCIAMENTO REM. HABILITADO: SIM ou NÃO, verificar x06. PROCEDIMENTO REALIZADO: reboot sem sucesso07. POTÊNCIA: não encontrado no unm08. CAIXA E PORTA: não encontrado no unm08. CONTATO: 859942482198599125563809. ENDEREÇO COMPLETO: Rua Nova Canaa de Serpa, SN - Justiniano de Serpa - Aquiraz - CE - CEP 61700-00010. CONDOMÍNIO: SIM (Nome) ou NÃO x10. PONTO DE REFERÊNCIA: Próx ao bar mineiro11. DISPONIBILIDADE: Só vai ter gente em casa Aparti de 15:30 da tarde12. OBSERVAÇÃO:
A34: 3843320 | B34: FRANCISCO RICARDO PEREIRA DA SILVA | C34: Encerramento | D34: DNET - PENDÊNCIA FIBRA - COND. | E34: Rua | F34: Rua João Campos Filho | G34: 167 | H34: Maracanaú | I34: Parque Tijuca | J34: -38454058 | K34: -386266417 | L34: CARLOS HENRIQUE LINO SILVA | M34: FELIPE MESSIAS ABREU DA SILVA | N34: 46261 | O34: 46262 | P34: 46266 | Q34: 46266 | R34: Sim | S34: 4 | T34: DNET - Cliente Condomínio | U34: DNET - Pendência | V34: DNET - LOS | W34: DNET - Fibra Sem Sinal / Luz Los Vermelha | X34: Troca Conector - Desgastado | AA34: OLT DNET TEMPORARIO | AB34: Abertura Solicitação para visita técnica no cliente, a pedido do mesmo.NORMALIZADO APÓS MANUTENÇÃO DA INFRAESTRUTURA. Dispositivo: samsung SM-A055MVersão do Android: 14Versão do V·Tasks: 5.9.211 Status alterado de Andamento para Encerramento | AC34: 27/08/2026 - 22:53 01. RELATO DO CLIENTE: Cliente relata estar sem internet / piscando vermelho no equipamento02. ANÁLISE SISTEMA (UNM): linklos03. ANÁLISE SISTEMA (VOALLE): offline04. EXTRATO COM QUEDAS: XX05. GERENCIAMENTO REM. HABILITADO: Verificar06. PROCEDIMENTO REALIZADO: REBOOT DA TOMADA07. POTÊNCIA: XX08. CAIXA E PORTA: CX não localizada08. CONTATO: (85)98552-6720 / (85)98146-556009. ENDEREÇO COMPLETO: rua João campos filho 167 / bloco 6 apartamento 10410. CONDOMÍNIO: Sim / residencial Virgílio Távora 210. PONTO DE REFERÊNCIA: residencial Virgílio Távora 211. DISPONIBILIDADE: Manhã12. OBSERVAÇÃO:
A35: 3843334 | B35: JOAO ROBERIO LEONCIO DE ARAUJO | C35: Encerramento | D35: PENDÊNCIA FIBRA - COND. | E35: Rua | F35: Rua das Abelhas | G35: 166 | H35: Itaitinga | I35: Gereraú | L35: WELLISON FERREIRA LIMA | M35: MIRELLA GOMES DE ABREU | N35: 46262 | O35: 46263 | P35: 46268 | Q35: 46268 | R35: Sim | S35: 5 | T35: Cliente Condomínio | U35: Pendência | V35: Potência Baixa | W35: Correção de Potência | X35: Troca Conector - Desgastado | AA35: OLT Jabuti VLAN 1000 | AB35: 🧰 PENDÊNCIA 🧰Data: 03/09/2026Técnico: WellisonCliente JOAO ROBERIO LEONCIO DE ARAUJOEndereço R. Iraí, 118, Gererau - ItaitingaCaixa: Porta: Potência da Caixa:Potência do Cliente: 25Material Utilizado:Drop:00APC Verde:00UPC Azul:01Fixa-fio: 00RJ45: 00Adesivo:00Relato: Ao chega no local cliente relatou que a Internet tava oscilando muito foi verificado que o db tava menos 29 trocado o conector normalizou para menos 25 feito a troca também do equipamento pois estava antigo feito os testes rodando normalmente.Roteador (entrada): 012CRoteador (saída)d52bDispositivo: samsung SM-A075MVersão do Android: 16Versão do V·Tasks: 5.9.213 Status alterado de Agendado para Encerramento | AC35: 28/08/2026 - 06:38 01. RELATO DO CLIENTE: internet oscilando, luzes verdes, potencia baixa02. ANÁLISE SISTEMA (UNM): on, pot. baixa03. ANÁLISE SISTEMA (VOALLE): on04. EXTRATO COM QUEDAS: sim05. GERENCIAMENTO REM. HABILITADO: SIM 06. PROCEDIMENTO REALIZADO: o.s07. POTÊNCIA:-30.0008. CAIXA E PORTA: 8224, p1208. CONTATO: (85)98518-2866 (85)99213-667409. ENDEREÇO COMPLETO: rua das abelhas, 166,AP 205, Gererau10. CONDOMÍNIO: SIM conjunto de apartamentos10. PONTO DE REFERÊNCIA: conjunto de apartamentos11. DISPONIBILIDADE: total12. OBSERVAÇÃO:
A36: 3843391 | B36: ANA PAULA DA CONCEICAO | C36: Encerramento | D36: TRANSFERÊNCIA - PF | E36: Rua | F36: Rua Francisco Edilson da Silva | G36: 110 | H36: Fortaleza | I36: Genibaú | J36: -3.7645126e+16 | K36: -3.8598332e+15 | L36: FELIPE MARTINS DAMASCENO | M36: IZABELY COSTA SILVA | N36: 46262 | O36: 46265 | P36: 46266 | Q36: 46266 | R36: Sim | S36: 1 | T36: Cliente Pessoa Física | U36: Transferência | V36: Equipamento no Novo Endereço | W36: Taxa Faturada | X36: Troca Conector - Desgastado | AA36: OLT Genibau VLAN 2041 | AB36: *transferência*Chegada: 000Saída: 000Data: 01/09/2026N2: *Técnico* Felipe *Cliente* ANA PAULA DA CONCEICAO*Bairro* Rua Francisco Edilson da Silva, 110, Genibaú - FortalezaCaixa: 7282Porta 02Potência da caixa - 22Potência do cliente - 22Plano - *Acesso Remoto Habilitado: SIM✅**Marca* global *Mac:**ACESSO AO ROUTER**Usuario: admin *Senha: Infolink *Porta de Acesso: Exemplo :80*Material Utilizado: 01 LACRE01 Conector Azul01 Conector verde05 Fixa fio 00 Esticador01 Canaleta PVC00 Acoplador00 ONU APC00 NU MINI 00 Mercusys 4 antenas00 Tenda 3 antenas 00 ZTE 2 ANTENAS.00 global00 Wi-Fi 6SERVIÇO: transferência Valor free.Obs: transferência Drop : 740Drop final : 640Utilizando: 100Cabo de Rede Início Final Total Encerramento: finalizado 👍Dispositivo: samsung SM-A065MVersão do Android: 16Versão do V·Tasks: 5.9.211 Status alterado de Andamento para Encerramento | AC36: 28/08/2026 - 08:54 PERGUNTA PRE-REQUISITO PARA ABERTURA:-CLIENTE JA SE MUDOU? SIMTEM ENERGIA ELETRICA NO LOCAL? SIM- É CONDOMINIO ? SIM ( ) NÃO ( X)SE A RESPOSTA FOR NÃO PARA QUALQUER UMA DAS PERGUNTAS, A SOLICITAÇÃO NÃO PODE SER ABERTA.01. FONE 01: 8599245351402. FONE 02:8599245351403. WHATSAPP:8599245351404. NOVO ENDEREÇO:* RUA: R. Francisco Edílson da Silva* Nº: 110* BAIRRO: Parque Genibaú* CIDADE: Fortaleza* PONTO DE REFERÊNCIA DO ENDEREÇO NOVO: é na mesma rua só algumas casas antes não tem como errar05. CAIXA: 728206. COORDENADAS: -3.7645125806122794, -38.5983319711642207. DISPONIBILIDADE PARA RECEBER A EQUIPE: SIM, TOTAL09. DEIXAR O CLIENTE CIENTE QUE OS EQUIPAMENTOS PRECISAM ESTAR NO NOVO ENDEREÇO.10. VALOR ? 75,00 EM 3X NO BOLETO11. ANTIGO ENDEREÇO:Rua Francisco Edilson da Silva, 220 - Genibaú - Fortaleza - CE - CEP 60534-00511. PRAZO: 72 HORAS UTEIS.OBS:
A37: 3843474 | B37: JUCILEIDE JOANA DE OLIVEIRA | C37: Encerramento | D37: RETIRADA DE EQUIPAMENTOS | E37: Rua | F37: Rua Idalino Ferreira Lins | G37: 89 | H37: Palmares | I37: Santa Luzia | J37: -8672043 | K37: -35585083 | L37: TARCIO FRANCISCO DA SILVA | M37: ANTONIO VITOR MOREIRA DE MORAIS | N37: 46262 | O37: 46265 | P37: 46286 | Q37: 46286 | R37: Sim | S37: 21 | T37: Retirada de Equipamentos | X37: Equipamento Entregue | AB37: *TEC:* TARCIO FRANCISCO *DATA: 21/09/2026**COD RETIRADA* 3843474*DESCRIÇÃO:* RETIRADA DE EQUIPAMENTOS*NOME* JUCILEIDE JOANA DE OLIVEIRA*SOLUÇÃO:* equipamentos retirado*ENDEREÇO* Rua Idalino Ferreira Lins, 89, Santa Luzia - Palmares*ONT ZTE 2 ANTENAS*(ZTEGD52CC204))*ROTEADOR TENDA F3**NRO DE SÉRIE* (E6333012938000919)*OBS*Dispositivo: Xiaomi 23053RN02AVersão do Android: 15Versão do V·Tasks: 5.9.215 Status alterado de Andamento para Encerramento | AC37: 1. DESCRIÇÃO DA SOLICITAÇÃO:2.CONTATO TELEFÔNICO (01):3.CONTATO TELEFÔNICO (02):4.WHATSAPP:5.PONTO DE REFERÊNCIA:6.DISPONIBILIDADE:7.PRAZO: 10 DIAS CORRIDOS8. CLIENTE COM NECESSIDADES ESPECIAIS/NECESSIDADE?Contrato cancelado, necessário realizar visita ao cliente para remover os equipamentos em comodato.ONT ZTE 2 ANTENAS V9.0ROTEADOR TENDA F3
A38: 3843497 | B38: JOSELUCIA MELO MARQUES | C38: Encerramento | D38: INSTALAÇÃO FIBRA - COND. | E38: Avenida | F38: Avenida Santos Dumont | G38: 393 | H38: Aquiraz | I38: Central | J38: -39030225 | K38: -383873051 | L38: HALLEF GUILHERME LIMA CLEMENTE SILVA | M38: MARIA THALYA BATISTA FERREIRA | N38: 46262 | O38: 46265 | P38: 46267 | Q38: 46267 | R38: Sim | S38: 2 | T38: Cliente Condomínio | U38: Instalação | X38: Troca Conector - Desgastado | AA38: OLT Aquiraz VLAN 12 | AB38: 🛠 *INSTALAÇÃO* 🧰*Data:* 02/09/2026 *Técnico:* Hallef / Ismael *Cliente:* JOSELUCIA MELO MARQUES*Endereço:* Avenida Santos Dumont, 396, Centro - Aquirazhttps://maps.app.goo.gl/zYDFLdYSSM1UYu2m7 *Potência:* 19*Caixa:* 62*porta*: 4 *MATERIAL USADO* Conector verde 2und Conector azulAdesivoPetcord Fixa fio 25 Canaleta 1 EQUIPAMENTOS * Ont FHTTFE258EF5* Roteador.* ONU *inicial:* 715*Final:* 615*Metragem:*100 *Serviço Realizado:* Instalação Feito os testes com o cliente.*Classificação de Encerramento:* Instalação Concluída.Dispositivo: motorola moto g04sVersão do Android: 14Versão do V·Tasks: 5.9.211 Status alterado de Agendado para Encerramento | AC38: VENDEDOR: MARIA THALYAÁREA: PAP () CALL-CENTER ( ) LOJA ( ) TBR ( X )TITULAR:JOSELUCIA MELO MARQUESTELEFONE:(85) 98886-3442/859920024680WHATSAPP:(85) 98886-3442/859920024680DISPONIBILIDADE: MANHA( ) TARDE ( ) DIA TODO (X)DATA: LIGAR ANTES PARA ELA IR RECEBERCIDADE E BAIRRO: CENTRO-AQUIRAZ-CEPLANO: 400MBVALOR ORIGINAL DO PLANO: 94,99POSSUI DESCONTO DE PONTUALIDADE? SIM ( X ) NÃO ( )SE SIM: D5 ( X ) ou DNET - D10( )DESCONTO DE _5,00_ , SE PAGO ATÉ O VENCIMENTO POR 12 MESESTAXA INSTALAÇÃO: FREEATENDIMENTO REGISTRADO:Google Drive ( ) Fortics ( X ) Smart ( )FIDELIDADE: ( X ) SIM NÃO ( )CLIENTE DESEJA NOTA FISCAL: SIM ( ) NÃO ( X )COORD:-3.902946697270758, -38.38738363340308CAIXA:62CASA DUPLEX ( X ) CASA TERREA ()QUANTOS E QUAIS APARELHOS CONECTADOS:1 CELULAROBSERVAÇÃO ADICIONAL:Ativação do contrato: 174107---- Endereço de Instalação ----CEP: 61700-000Logradouro: Avenida Santos DumontNúmero: 396Bairro: CentroEstado: CECidade: AquirazComplemento: Ap 3Referência: Em cima do cantinho do chef---- Serviços a serem ativados ----- 0522 - ULTRAINFO - 400MB
A39: 3843590 | B39: DAVI HENRRIQUE CAITANO DE SOUSA | C39: Encerramento | D39: DNET - PENDÊNCIA FIBRA - COND. | E39: Rua | F39: Rua Antero Quental | G39: 155 | H39: Fortaleza | I39: São Bento | J39: -38575187 | K39: -384916395 | L39: CARLOS HENRIQUE LINO SILVA | M39: JULIA VICTORIA SILVA DOMICIO | N39: 46262 | O39: 46263 | P39: 46266 | Q39: 46266 | R39: Sim | S39: 3 | T39: DNET - Cliente Condomínio | U39: DNET - Pendência | V39: DNET - Potência Baixa | W39: DNET - Correção de Potência | X39: Troca Conector - Desgastado | AA39: OLT DNET TEMPORARIO | AB39: Abertura Solicitação para visita técnica no cliente, a pedido do mesmo.☑️☑️ *PENDÊNCIA* ☑️☑️*Chegada**Saída**Data* 01.09.2026*SUPORTE**COMERCIAL* *Técnico* CARLOS HENRIQUE*AUXILIAR:* ELEEONAI VIANA *CLIENTE:* DAVI HENRRIQUE CAITANO DE SOUSA*ENDEREÇO* Rua Antero Quental, 155, São Bento - Fortaleza*obs sobre o endereço* *CONTATO* *Caixa* *PORTA* *SINAL DA CAIXA**SINAL DO CLIENTE*-25*Velocidade* *Material utilizado* 1Conector Verde Conector Azul Fixa fixo canaleta0 Esticadoadesivo 0 Per CordRJ45 TUBETEPROBLEMA RELATADO: SEM SINAL.*OBS* POTENCIA BAIXA, FOI REALIZADO A TEOCA DO CONECTOR E CONEXÃO NORMALIZOU. *VALOR:* Cabo de redeInicial Final Metragem*SENHA DO EQUIPAMENTO* *Equipamento anterior* *ONT* *ONU* *ROTEADOR:* *Equipamento Atual* *ONT* *ONU* *ROTEADOR* *Drop inicial* *Drop Final* *Metragem:* *OBS:* *Classificação de Encerramento*RESOLVIDO✅Dispositivo: samsung SM-A055MVersão do Android: 14Versão do V·Tasks: 5.9.211 Status alterado de Andamento para Encerramento | AC39: 28/08/2026 - 09:44 01. RELATO DO CLIENTE: Cliente relata quedas na conexão e oscilção.02. ANÁLISE SISTEMA (UNM): Online03. ANÁLISE SISTEMA (VOALLE): Online04. EXTRATO COM QUEDAS: NÃO05. GERENCIAMENTO REM. HABILITADO: SIM06. PROCEDIMENTO REALIZADO: reboot sem sucesso07. POTÊNCIA: -26.9908. CAIXA E PORTA: 11616 BL01 - 20208. CONTATO: 85 9 2168-480009. ENDEREÇO COMPLETO: Rua G (residencia dos escritores) 155, Paupina - Fortaleza10. CONDOMÍNIO: SIM, condominio raquel de queiroz, apartamento 202 bloco 110. PONTO DE REFERÊNCIA: condominio raquel de queiroz11. DISPONIBILIDADE: O dia todo12. OBSERVAÇÃO: Cliente vai falar com a portaria para autorizar a entrada do técnico.
A40: 3843692 | B40: JOSE OMAR DE FREITAS | C40: Encerramento | D40: PENDÊNCIA FIBRA - PF | E40: Rua | F40: Rua Izaura Gomes | G40: 0 | H40: Aquiraz | I40: Patacas | L40: LUIZ CARLOS ALVES LOPES | M40: LUNARA CUNHA DE FREITAS DOS ANJOS | N40: 46262 | O40: 46263 | P40: 46266 | Q40: 46266 | R40: Sim | S40: 3 | T40: Cliente Pessoa Física | U40: Pendência | V40: Queda de conexão | W40: Extrato Com Quedas | X40: Troca Conector - Desgastado | AA40: OLT Tapera VLAN 1009 | AB40: ✅ *PENDENCIA* ✅*Data* 01.09.2026*Técnico* Luiz Carlos CLIENTE: JOSE OMAR DE FREITAS🏠 ENDEREÇO: Rua Izaura Gomes, 0, Patacas - Aquiraz*LOCALIZAÇÃO DO CLIENTE: *PONTO DE REFERENCIA: Depois da praça do Lima ⏹️ *Caixa: 7347 Porta: 08 SINAL DA CAIXA: -23 SINAL DO CLIENTE: -23*DROP COM ETIQUET 🏷️ ☎️ *GESTÃO DE O.S**ATENDIMENTO:* 📝SERVIÇO: cliente informou que nao precisa mais do atendimento pois ja normalizou⚙️ *Material utilizado 00 Conector Verde00 Conector Azul00 Fixa fio00 Canaleta00 Esticador00 Adesivo conector 00 RJ4500 patch cord📡 *Equipamento utilizado 00 ZTE (MAC) =00 HG325AX (MAC) = 00 XC220G3 (MAC) =00 MERCUSYS (MAC) =00Shoreline (MAC) =00 Ont tplink (MAC) =00 Onu mini(MAC)= *Equipamento RMA*00 ZTE (MAC) = 00 HG325AX (MAC) = 00 ONT GLOBAL (MAC) =00 ROTEADOR TPL (MAC) = 00 ROTEADOR TENDA (MAC) = 00 MERCUSYS (MAC) =00 ONU MINI (MAC) =00 ONU APC (MAC) = ,*OBS* *Valor 75 em 3× *Cabo inicial* 00m*Cabo final* 00m*Metragem* 00m*Drop inicial* 00m*Drop final* 00m*Metragem* 00m*Classificação de Encerramento**RESOLVIDO✅**Status alterado de Reagendado para Encerramento* 😎 🇮🇹Dispositivo: samsung SM-A146MVersão do Android: 15Versão do V·Tasks: 5.9.206 Status alterado de Reagendado para Encerramento | AC40: 28/08/2026 - 10:26 01. RELATO DO CLIENTE: CLIENTE INFORMA QUE ESTA SEM SINAL DE INTERNET , FOI VERIFICADO EM SISTEMA ESTA ONLINE , MAS CONSTA MUITAS QUEDAS DE SINAL REGISTRADAS NOS ULTIMNOS DIAS , ABERTA A VISITA PARA VERIFICAR.02. ANÁLISE SISTEMA (UNM): ESTA ONLINE03. ANÁLISE SISTEMA (VOALLE):ESTA ONLINE04. EXTRATO COM QUEDAS: SIM 05. GERENCIAMENTO REM. HABILITADO: SIM ou NÃO***06. PROCEDIMENTO REALIZADO:***07. POTÊNCIA:-24,2008. CAIXA E PORTA:7347//0808. CONTATO 85)98202-1916 (85)98479-636809. ENDEREÇO COMPLETO:Rua Izaura Gomes, 0Bairro: PatacasAquiraz - CE. BrasilCEP: 61700-000Referência: dpois da praça do limas10. CONDOMÍNIO: NÃO10. PONTO DE REFERÊNCIA: dpois da praça do limas11. DISPONIBILIDADE:O DIA TODO 12. OBSERVAÇÃO:
A41: 3843705 | B41: ALANA LIMA DIAS | C41: Encerramento | D41: PENDÊNCIA FIBRA - COND. | E41: Rua | F41: Rua cedro | G41: 226 | H41: Itaitinga | I41: ponta da serra | J41: -39666469 | K41: -385223752 | L41: GEILSON DA SILVA MOURA | M41: VINICIUS LIMA DA SILVA | N41: 46262 | O41: 46263 | P41: 46266 | Q41: 46266 | R41: Sim | S41: 3 | T41: Cliente Condomínio | U41: Pendência | V41: LOS | W41: Fibra Sem Sinal / Luz Los Vermelha | X41: Troca Conector - Desgastado | AA41: OLT Jabuti VLAN 1000 | AB41: *🧰 PENDÊNCIA 🧰**Data:* 01/09/2026*Técnico:* Geilson/David *cliente*ALANA LIMA DIAS*Endereço*Rua cedro, 226, ponta da serra - Itaitinga*Potência:* -22*Caixa* 9184*porta* 3*MATERIAL USADO* Conector verde 1Conector azul Adesivo Petcord Fixa fio Canaleta Rj45 Cabo de rede EQUIPAMENTOS *Ont* *ONU* *Roteador* *Retirado* *DROP*⬇️*inicial:* 480*Final:* 190*Metragem:* 290*Serviço:Fibra do cliente rompida, puxamos uma nova e a conexão normalizou.*OBS* *Valor*Dispositivo: iPhoneVersão do iOS: 26.6Versão do V·Tasks: 5.9.211 Status alterado de Andamento para Encerramento | AC41: 28/08/2026 - 11:03 01. RELATO DO CLIENTE: CLIENTE SEM INTERNET, PISCANDO VERMELHO02. ANÁLISE SISTEMA (UNM): OFFLINE03. ANÁLISE SISTEMA (VOALLE): OFFLINE04. EXTRATO COM QUEDAS: X05. GERENCIAMENTO REM. HABILITADO: X06. PROCEDIMENTO REALIZADO: REBOOT07. POTÊNCIA: X08. CAIXA E PORTA:11961 0308. CONTATO:(85)99406-388109. ENDEREÇO COMPLETO:Rua Cedro, N°226, AP 10410. CONDOMÍNIO: SIM Condomínio Apis II.10. PONTO DE REFERÊNCIA: Condomínio Apis II.11. DISPONIBILIDADE:dia todo12. OBSERVAÇÃO: CLIENTE INSATISFEITA, PEDE AGILIDADE, TRABALHA DE HOME OFFICE
A42: 3843730 | B42: JOELMIR SOARES MATOS | C42: Encerramento | D42: TRANSFERÊNCIA - PF | E42: Rua | F42: Rua Farias Lemos | G42: 981 | H42: Fortaleza | I42: Messejana | L42: VINICIUS SILVA LEARTE | M42: ANNA LIVIA LEITE GARCEZ | N42: 46262 | O42: 46265 | P42: 46266 | Q42: 46266 | R42: Sim | S42: 1 | T42: Cliente Pessoa Física | U42: Transferência | V42: Equipamento no Novo Endereço | W42: Taxa Faturada | X42: Troca Conector - Desgastado | AA42: OLT Terrazo VLAN 4024 | AB42: ✅ *ALTERACAO DE ENDERECO* ✅*Data* 01.09.2026*Técnico* Vinicius Learte *Cliente*: JOELMIR SOARES MATOS🏠 *ENDEREÇO*: Rua Farias Lemos, 981, Messejana - Fortaleza ⏹️ *Caixa* 10138 *Porta*:04*SINAL DA CAIXA* -26*SINAL DO CLIENTE* -27*DROP COM ETIQUETA 🏷️* ☎️ *GESTÃO DE O.S* *ATENDIMENTO:* 📝 *SERVIÇO*: alteração de endereco concluida⚙️ *Material utilizado*02 Conector Verde*OBS* *VALOR* 75,00 reais em 3x*Cabo inicial* 00m*Cabo final* 00m*Metragem* 00m*Drop inicial* 233m*Drop final* 00m*Metragem* 233m*Classificação de Encerramento**RESOLVIDO✅*Dispositivo: samsung SM-A075MVersão do Android: 16Versão do V·Tasks: 5.9.211 Status alterado de Andamento para Encerramento | AC42: 28/08/2026 - 10:46 PERGUNTA PRE-REQUISITO PARA ABERTURA: -CLIENTE JA SE MUDOU? sim TEM ENERGIA ELETRICA NO LOCAL? sim - É CONDOMINIO ? SIM ( ) NÃO (x ) SE A RESPOSTA FOR NÃO PARA QUALQUER UMA DAS PERGUNTAS, A SOLICITAÇÃO NÃO PODE SER ABERTA. 01. FONE 01: (85)98633-460102. FONE 02: (85)98633-460103. WHATSAPP: (85)98633-460104. NOVO ENDEREÇO: * RUA: R. Farias Lemos * Nº: 981 * BAIRRO: Messejana* CIDADE: Fortaleza* PONTO DE REFERÊNCIA DO ENDEREÇO NOVO: esquina com a uni de melo05. CAIXA: 1013806. COORDENADAS: -3.815353210976129, -38.4930098134914607. DISPONIBILIDADE PARA RECEBER A EQUIPE: o dia todo , entrar em contato antes de ir 09. DEIXAR O CLIENTE CIENTE QUE OS EQUIPAMENTOS PRECISAM ESTAR NO NOVO ENDEREÇO. 10. VALOR ? 75,00 3x 11. ANTIGO ENDEREÇO: * RUA: Rua Eudes Cardoso * Nº: 237* BAIRRO: Messejana* CIDADE: Fortaleza, CE11. PRAZO: 72 HORAS UTEIS. OBS:
A43: 3843734 | B43: MARIA SUERLIR FERREIRA DE CASTRO | C43: Encerramento | D43: INSTALAÇÃO FIBRA - PF | E43: Rua | F43: Rua Elizeu Oliveira | G43: 72 | H43: Eusébio | I43: Amador | J43: -3874152 | K43: -384604541 | L43: ANTONIO CARLOS FERREIRA DA SILVA | M43: VITOR CRUZ BATISTA | N43: 46262 | O43: 46265 | P43: 46266 | Q43: 46266 | R43: Sim | S43: 1 | T43: Cliente Pessoa Física | U43: Instalação | X43: Troca Conector - Desgastado | AA43: OLT Eusébio 1 VLAN 9 | AB43: ✅ *INSTALAÇÃO *✅*Data* 01/09/2026*Técnico* CARLINHOS. *PROTOCOLO* 3843734🧑‍🧑‍🧒‍🧒 *CLIENTE:* MARIA SUERLIR FERREIRA DE CASTRO🏠 *ENDEREÇO: Rua, Francisco Amora72, Amador - Eusébio*LOCALIZAÇÃO DO CLIENTE* -38.460999 -3.873859*PONTO DE REFERÊNCA* próximo a igreja liberdade em Cristo ⏹️ *Caixa* 326*Porta.* 03*SINAL DA 4AIXA* 24*SINAL DO CLIENTE* 24*DROP COM ETIQUETA 🏷️* ☎️ *GESTÃO DE O.S* *ATENDIMENTO:*📝 *SERVIÇO REALIZADO:* ⚙️ *Material utilizado*02 (Conector Verde)00 (Conector Azul)06 (Fixa fio00 (Canaleta)00 (Esticador)00 (Adesivo conector)00 (RJ45)00 (patch cord)📡 *Equipamento utilizado*00 (ZTE)MAC = 01 (ONT INTELBRAS)MAC= 89BB00 (ONT TP-LINK)MAC= 00 (SHORELINE)MAC =00 (HG325AX)MAC =00 (CDATA)MAC =00 (XC220G3)MAC =00 (MERCUSYS)MAC =00 (ROTEADOR TPLINK) (MAC) = *Equipamento RMA*00 (ONT TP LINK)MAC=00 (ZTE)MAC =00 (HG325AX)MAC =00 (ONT GLOBAL)MAC =00 (ROTEADOR TPL)MAC=00 (ROTEADOR TENDA)MAC=00 (MERCUSYS)MAC =00 (ONU MINI)MAC =00 (ONU APC)MAC *OBS* INSTALAÇÃO OK, (obs. A senha do roteador Intelbras é Fibra@info1).*VALOR* *Cabo inicial*00 m*Cabo final* 00m*Metragem* 00m*Drop inicial* 160m*Drop final* 48m*Metragem* 112m*Classificação de Encerramento* *RESOLVIDO✅**Status alterado de Reagendado para Encerramento* 😎 🇮🇹Dispositivo: motorola moto g04Versão do Android: 14Versão do V·Tasks: 5.9.211 Status alterado de Remarcação para Encerramento | AC43: VENDEDOR: VITOR CRUZ BATISTA ÁREA: PAP (X) CALL-CENTER ( ) LOJA ( ) TBR ( )TITULAR: MARIA SUERLIR FERREIRA DE CASTROTELEFONE: 8599280-9770WHATSAPP: 8599280-9770DISPONIBILIDADE: MANHA( ) TARDE ( ) DIA TODO (x)DATA:CIDADE E BAIRRO: EUSÉBIO/GUARIBASPLANO: 200mbVALOR ORIGINAL DO PLANO: 79,99POSSUI DESCONTO DE PONTUALIDADE? SIM ( ) NÃO (x )SE SIM: D5 ( ) ou DNET - D10( )DESCONTO DE __ , SE PAGO ATÉ O VENCIMENTO POR 12 MESESTAXA INSTALAÇÃO: 00ATENDIMENTO REGISTRADO:Google Drive ( ) Fortics ( ) Smart (x )FIDELIDADE: (x ) SIM NÃO ( )CLIENTE DESEJA NOTA FISCAL: SIM ( ) NÃO ( x)COORD: -3.874011,-38.460976 CAIXA: 291CASA DUPLEX ( ) CASA TERREA (x)QUANTOS E QUAIS APARELHOS CONECTADOS:OBSERVAÇÃO ADICIONAL:Ativação do contrato: 174119---- Endereço de Instalação ----CEP: 61769-380Logradouro: Rua Elizeu OliveiraNúmero: 72Bairro: AmadorEstado: CECidade: EusébioComplemento: casaReferência: próximo a igreja liberdade em Cristo---- Serviços a serem ativados ----- 0722 - ULTRAINFO - 200MB
A44: 3843802 | B44: JOSE LUIZ SANTOS DE SOUSA | C44: Encerramento | D44: DNET - PENDÊNCIA FIBRA - COND. | E44: Rua | F44: RUA G | G44: 255 | H44: Fortaleza | I44: PAUPINA MESSEJANA | J44: -38034661 | K44: -385472079 | L44: CARLOS HENRIQUE LINO SILVA | M44: LUANA IASMIM DE SOUZA OLIVEIRA | N44: 46262 | O44: 46263 | P44: 46266 | Q44: 46266 | R44: Sim | S44: 3 | T44: DNET - Cliente Condomínio | U44: DNET - Pendência | V44: DNET - LOS | W44: DNET - Fibra Sem Sinal / Luz Los Vermelha | X44: Troca Conector - Desgastado | AA44: OLT DNET TEMPORARIO | AB44: Abertura Solicitação para visita técnica no cliente, a pedido do mesmo.CLIENTE NORMALIZOU APÓS MANUTENÇÃO DA INFRAESTRUTURA. Dispositivo: samsung SM-A055MVersão do Android: 14Versão do V·Tasks: 5.9.211 Status alterado de Tratamento Infra para Encerramento | AC44: 28/08/2026 - 11:41 01. RELATO DO CLIENTE: Sem internet, LED vermelho no equipamento02. ANÁLISE SISTEMA (UNM): Linkloss03. ANÁLISE SISTEMA (VOALLE): Offline04. EXTRATO COM QUEDAS: *05. GERENCIAMENTO REM. HABILITADO: Verificar06. PROCEDIMENTO REALIZADO: *07. POTÊNCIA: *08. CAIXA E PORTA: *08. CONTATO: (85) 9 8239-4151 - (85) 9 8955-032009. ENDEREÇO COMPLETO: Rua G, 255 - Paupina - Fortaleza/CE - Bl. 28 Apto. 10310. CONDOMÍNIO: SIM (Machado de Assis)10. PONTO DE REFERÊNCIA: fábrica fae11. DISPONIBILIDADE: Dia todo12. OBSERVAÇÃO:
A45: 3843855 | B45: PAULO HENRIQUE DA SILVA ABREU | C45: Encerramento | D45: TRANSFERÊNCIA - PF | E45: Rua | F45: Rua São Mateus | G45: 393 | H45: Maracanaú | I45: Pajuçara | L45: KELTON CLEMENTE DOS SANTOS | M45: CAMILE SUZANE OLIVEIRA LIMA | N45: 46262 | O45: 46265 | P45: 46266 | Q45: 46266 | R45: Sim | S45: 1 | T45: Cliente Pessoa Física | U45: Transferência | V45: Equipamento no Antigo Endereço | W45: Taxa Faturada | X45: Troca Conector - Desgastado | AA45: OLT Pajuçara VLAN 1007 | AB45: ☑️☑️ *TRANSFERÊNCIA*☑️☑️*Chegada**Saída**Data* 1.08.2026*SUPORTE* *COMERCIAL* *Técnico* Kelton Clemente *Cliente* PAULO HENRIQUE DA SILVA ABREU*ENDEREÇO* RUA:R. Manuel Ferreira de Sousa, Cep- 61932-220* Nº:1319* BAIRRO: Pajuçara,* CIDADE: Maracanaú*Caixa* 4361*PORTA* 09*SINAL DA CAIXA* - 24*SINAL DO CLIENTE* -24*Velocidade* 600mb*Material utilizado* 0 RJ 02 Conector Verde 0Conector Azul 0Adesivo0 canaleta 03 fixa fio* MATERIAL RECOLHIDO*** * *OBS*: transferência realizada com sucesso, roteador no local escolhido pelo titular ,testes realizados junto do mesmo e tudo ULTRA CONECTADO.Obs... *VALOR* 75,00$ 3x*SENHA* *MAC* *cabo drop inicial* 1000*cabo drop final* 918*Metragem* 82*Classificação de Encerramento* RESOLVIDO✅Dispositivo: motorola moto g04sVersão do Android: 14Versão do V·Tasks: 5.9.211 Status alterado de Andamento para Encerramento | AC45: 28/08/2026 - 11:57 PERGUNTA PRE-REQUISITO PARA ABERTURA:-CLIENTE JA SE MUDOU? SIMTEM ENERGIA ELETRICA NO LOCAL? SIM- É CONDOMINIO ? SIM ( ) NÃO ( X)SE A RESPOSTA FOR NÃO PARA QUALQUER UMA DAS PERGUNTAS, A SOLICITAÇÃO NÃO PODE SER ABERTA.01. FONE 01: (85) 98951-525502. FONE 02:(85) 98951-525503. WHATSAPP: (85) 98951-525504. NOVO ENDEREÇO:* RUA:R. Manuel Ferreira de Sousa, Cep- 61932-220* Nº:1319* BAIRRO: Pajuçara,* CIDADE: Maracanaú* PONTO DE REFERÊNCIA DO ENDEREÇO NOVO: NÃO POSSUI05. CAIXA: 4361 686506. COORDENADAS:-3.863730677141127, -38.57051111802978507. DISPONIBILIDADE PARA RECEBER A EQUIPE:09. DEIXAR O CLIENTE CIENTE QUE OS EQUIPAMENTOS PRECISAM ESTAR NO NOVO ENDEREÇO. 10. VALOR ? 75 REAIS 3X NO BOLETO11. ANTIGO ENDEREÇO:* RUA:RUA SAO LUCAS, S/N - Bandeirante - Maracanaú - CE - CEP 61900-000* Nº: S/N CEP 61900-000* BAIRRO:Bandeirante* CIDADE: Maracanaú11. PRAZO: 72 HORAS UTEIS.OBS: CLIENTE ORIENTADO QUE O EQUIPAMENTO TEM QUE ESTÁ NO NOVO ENDEREÇO, PORÉM O MESMO RELATOU QUE ERA TRABALHO DO TÉCNICO RETIRA O EQUIPAMENTO.
A46: 3843857 | B46: RODRIGO SOARES VALENTE | C46: Encerramento | D46: DNET - INSTALAÇÃO FIBRA - PF | E46: Rua | F46: Rua Vereda Tropical | G46: 105 B | H46: Aquiraz | I46: Vereda Tropical | J46: -39123762 | K46: -384492008 | L46: ANDRE SILVA LOIOLA | M46: ANA GABRIELLY ALVES MENEZES | N46: 46262 | O46: 46265 | P46: 46267 | Q46: 46267 | R46: Sim | S46: 2 | T46: DNET - Cliente Pessoa Física | U46: DNET - Instalação | X46: Troca Conector - Desgastado | AA46: OLT Eusébio 2 VLAN 58 | AB46: Abertura Solicitação para visita técnica no cliente, a pedido do mesmo.*TECNICO:* ANDRÉ LOIOLA *CLIENTE:* (RODRIGO SOARES VALENTE )Nº CAIXA: (7935) N º PORTA: (6) VERIFICAÇÃO DE CX: SIM OU NÃO (NÃO)SINAL DA CTO: (-21) SINAL DO CLIENTE: (-21) *MATERIAL UTILIZADO* CONECTOR VERDE: (2)CONECTOR AZUL: ()FIXA FIO: (20)CANALETA: ()ESTICADOR: ()TUBETE: ()ADESIVO CONECTOR: ()RJ45: ()CABO DE REDE: () EQUIPAMENTO UTILIZADO (9925)ONT ()ONU (S/N) ROTEADOR (S/N) DROP CABO INICIAL: (398)DROP CABO FINAL: (308)DROP METRAGEM: (90)TEVE FATURAMENTO? SIM OU NÃO (NÃO)VALOR () : () ()SERVIÇO: ( INSTALAÇÃO)Dispositivo: motorola moto g23Versão do Android: 14Versão do V·Tasks: 5.9.213 Status alterado de Remarcação para Encerramento | AC46: VENDEDOR:GABRIELLY MENEZESÁREA: PAP () CALL-CENTER ( ) LOJA ( ) TBR ( )TITULAR: RODRIGO SOARES VALENTETELEFONE:(85) 99627-0079WHATSAPP:(85) 99627-0079DISPONIBILIDADE: MANHA( ) TARDE ( ) DIA TODO (X)DATA: 29/08/2026CIDADE E BAIRRO:Rua Vereda Tropical, 105 B AquirazPLANO:🔹 700 MB – R$ 139,99 (R$ 129,99 até o vencimento)VALOR ORIGINAL DO PLANO: 139,99POSSUI DESCONTO DE PONTUALIDADE? SIM ( x) NÃO ( )SE SIM: D5 ( ) ou DNET - D10(x )DESCONTO DE _10_ , SE PAGO ATÉ O VENCIMENTO POR 12 MESESTAXA INSTALAÇÃO: GRATISATENDIMENTO REGISTRADO:Google Drive ( ) Fortics ( ) Smart ( X)FIDELIDADE: (X ) SIM NÃO ( )CLIENTE DESEJA NOTA FISCAL: SIM ( ) NÃO ( X)COORD:-3.921983900969085, -38.452712521526216CAIXA:CX7935CASA DUPLEX ( ) CASA TERREA (X)QUANTOS E QUAIS APARELHOS CONECTADOS: 7 Celulares, TVs e Notebooks.OBSERVAÇÃO ADICIONAL:Ativação do contrato: 174125---- Endereço de Instalação ----CEP: 61700-000Logradouro: Rua Vereda TropicalNúmero: 105 BBairro: Vereda TropicalEstado: CECidade: Aquiraz---- Serviços a serem ativados ----- 0824 - DNET - 700MB
A47: 3843877 | B47: ANTONIA LOPES SILVA | C47: Encerramento | D47: PENDÊNCIA FIBRA - PF | E47: Rua | F47: José Monteiro Filho | G47: 17 | H47: Cascavel | I47: Caponga | L47: ISRAEL OLIVEIRA MORAIS | M47: MIRELLA GOMES DE ABREU | N47: 46262 | O47: 46263 | P47: 46266 | Q47: 46266 | R47: Sim | S47: 3 | T47: Cliente Pessoa Física | U47: Pendência | V47: LOS | W47: Fibra Sem Sinal / Luz Los Vermelha | X47: Troca Conector - Desgastado | AA47: OLT Caponga VLAN 1005 | AB47: ⚠️ *pendência* ⚠️*Data:* 01/09 /2026*TÉCNICO RESPONSÁVEL:* Israel Oliveira*CLIENTE:* ANTONIA LOPES SILVA*ENDEREÇO:* José Monteiro Filho, 17, Caponga - Cascavel*LOCALIZAÇÃO DO CLIENTE*-4.043976,-38.200993*SUPORTE N2:* *CAIXA:* 7252*PORTA:* 10*POTÊNCIA DA CAIXA:* -25*POTÊNCIA DO CLIENTE:* -25*ACESSO REMOTO HABILITADO:* sim*SENHA DO ROTEADOR:**SERVIÇO:* drop rompido, realizado a troca do drop e voltou o acesso.*OBS:* *MATERIAL UTILIZADO:*01 conector verde01 conector azul.215m de drop.*VALOR:* 0,00 *DROP INICIAL:* 470*DROP FINAL:* 255*METRAGEM TOTAL:* 215*CLASSIFICAÇÃO DE ENCERRAMENTO :* finalizado✅Dispositivo: samsung SM-A075MVersão do Android: 16Versão do V·Tasks: 5.9.206 Status alterado de Reagendado para Encerramento | AC47: 28/08/2026 - 12:11 01. RELATO DO CLIENTE: Fibra Sem Sinal / Luz Los Vermelha02. ANÁLISE SISTEMA (UNM): LOSS03. ANÁLISE SISTEMA (VOALLE): OFF04. EXTRATO COM QUEDAS: X05. GERENCIAMENTO REM. HABILITADO:X06. PROCEDIMENTO REALIZADO: REBOOT07. POTÊNCIA: X08. CAIXA E PORTA: 7252,1008. CONTATO: (85)98835-2237 (85)99219-399409. ENDEREÇO COMPLETO: José Monteiro Filho, 35 - Caponga - Cascavel - CE - CEP 62852000 - POSTO DE GASOLINA10. CONDOMÍNIO: NÃO 10. PONTO DE REFERÊNCIA: POSTO DE GASOLINA11. DISPONIBILIDADE: TOTAL12. OBSERVAÇÃO:
A48: 3843885 | B48: ROSEMBERG MENDES DE OLIVEIRA | C48: Encerramento | D48: PENDÊNCIA FIBRA DEFINIR PRAZO | E48: Loteamento | F48: Loteamento Village do Eusebio | G48: 0 | H48: Aquiraz | I48: Pindoba | L48: ARLISON DA SILVA PEREIRA | M48: MARIANA ABREU DA SILVA | N48: 46262 | O48: 46267 | P48: 46266 | Q48: 46266 | R48: Não | T48: Cliente Pessoa Física | U48: Pendência | V48: Definir Prazo | W48: Definir Prazo | X48: Troca Conector - Desgastado | AA48: OLT Aquiraz VLAN 12 | AB48: *PENDÊNCIA**Data* 01.09.2026*Técnico* Arlison 🫡🧑‍🧑‍🧒‍🧒 *CLIENTE:* ROSEMBERG MENDES DE OLIVEIRA🏠 *ENDEREÇO:* Loteamento Village do Eusebio, 0, Pindoba - Aquiraz *LOCALIZAÇÃO DO CLIENTE:* https://maps.app.goo.gl/bC2V8Vdr9BJjcxmJ8*PONTO DE REFERÊNCIA:* ⏹️ *Caixa* 1280*Porta* 01*SINAL DA CAIXA* -22*SINAL DO CLIENTE* -22*DROP COM ETIQUETA 🏷️* ☎️ *GESTÃO DE O.S* *ATENDIMENTO:* 📝 *SERVIÇO REALIZADO:* Feito troca de ambos os conectores ⚙️ *Material utilizado*02 Conector Verde00 Conector Azul00 Fixa fio00 Canaleta00 Esticador00 Adesivo conector 00 RJ4500 patch cord📡 *Equipamento utilizado*00 ZTE (MAC) = 00 HG325AX (MAC) =00 XC220G3 (MAC) =00 ONU MINI (MAC) =00 Wi-Fi 6 (MAC) = 00 MERCUSYS (MAC) = 00 ROTEADOR (MAC) = *Equipamento RMA*00 HG325AX (MAC) = 00 ZTE (MAC) = 00 ONT GLOBAL (MAC) = 00 ROTEADOR Tenda (MAC)= 00 MERCUSYS (MAC) =00 ROTEADOR TP link(MAC)= 00 ONU MINI (MAC) = 00 ONU APC (MAC) = 00 ROTEADOR (MAC) =*OBS* *VALOR* *Cabo inicial* 0 m*Cabo final* 0 m*Metragem* 0 m*Drop inicial* 0 m*Drop final* 0 m*Metragem* 0 m*Classificação de Remarcação**RESOLVIDO✅**Status alterado de Reagendado para Encerramento*Dispositivo: motorola moto g04sVersão do Android: 14Versão do V·Tasks: 5.9.209 Status alterado de Reagendado para Encerramento | AC48: 28/08/2026 - 12:25 01. RELATO DO CLIENTE: SEM INTERNET, LED PISCANDO VERMELHO02. ANÁLISE SISTEMA (UNM): LINK LOSS03. ANÁLISE SISTEMA (VOALLE): OFF04. EXTRATO COM QUEDAS: SIM ou NÃO05. GERENCIAMENTO REM. HABILITADO: SIM ou NÃO06. PROCEDIMENTO REALIZADO: TIROU DA TOMADA07. POTÊNCIA:xx08. CAIXA E PORTA:CX1280 P-0108. CONTATO:(85)98538-1535-(85)98841-046409. ENDEREÇO COMPLETO: Loteamento Village do Eusebio, 0 - Pindoba - Aquiraz - CE - CEP 61700000 - PROX AO SITIO TIJUCA10. CONDOMÍNIO: SIM (Nome) ou NÃO10. PONTO DE REFERÊNCIA: Ao lado do condomínio do Sr Flávio e perto da Fábrica Staff cosméticos11. DISPONIBILIDADE:A partir das 11:00hrs12. OBSERVAÇÃO:terça feira dia 01/09, pois estarei saindo para viajar hoje à tarde e só volto na segunda
A49: 3843905 | B49: JUAREZ SANTOS DE SOUSA | C49: Encerramento | D49: PENDÊNCIA FIBRA - PF | E49: Rua | F49: Rua Luís Mendes De Barros | G49: 800 | H49: Maracanaú | I49: Pajuçara | L49: KELTON CLEMENTE DOS SANTOS | M49: CAMILE SUZANE OLIVEIRA LIMA | N49: 46262 | O49: 46263 | P49: 46266 | Q49: 46266 | R49: Sim | S49: 3 | T49: Cliente Pessoa Física | U49: Pendência | V49: LOS | W49: Fibra Sem Sinal / Luz Los Vermelha | X49: Troca Conector - Desgastado | AA49: OLT Pajuçara VLAN 1007 | AB49: ☑️ *PENDÊNCIA* *DATA* 1.09.2026*Técnico* Kelton Clemente*Cliente* JUAREZ SANTOS DE SOUSA*ENDEREÇO* Rua Luís Mendes De Barros, 800, Pajuçara - Maracanaú*CAIXA* 3992*PORTA* 15*SINAL DA CAIXA* - 24*SINAL DO CLIENTE* -26*Velocidade* 600 mb*Material utilizado* 0 Ax 60 FIXA FIO0 Conector Verde 0Conector Azul 0 canaleta 0Adesivo * MATERIAL RECOLHIDO** * * *OBS*: equipamento em los, fibra sem sinal, identificado que na CTO a porta da cliente e mais duas estava Los pois a o Splinter esta danificado, então foi verificado uma porta livre e com potência, remanejado o cliente para a porta 15 , potência e conexão normalizada, testes realizados junto da titular e tudo ULTRA CONECTADO novamente.Obs.... *VALOR* *SENHA* *MAC* *cabo drop inicial* *cabo drop final* *Metragem* *Classificação de Encerramento* RESOLVIDO✅Dispositivo: motorola moto g04sVersão do Android: 14Versão do V·Tasks: 5.9.211 Status alterado de Reagendado para Encerramento | AC49: 28/08/2026 - 12:31 01. RELATO DO CLIENTE: CLIENTE RELATA QUE ESTÁ SEM CONEXÃO, O MESMO RELATA QUE TEM UMA LUZ VERMELHA PISCANDO NO ROTEADOR02. ANÁLISE SISTEMA (UNM): NO UNM O CLIENTE NÃO FOI LOCALIZADO.03. ANÁLISE SISTEMA (VOALLE): OFFLINE04. EXTRATO COM QUEDAS: NÃO05. GERENCIAMENTO REM. HABILITADO: NÃO06. PROCEDIMENTO REALIZADO: VERIFICADO NO VOALLE E ABERTURA DE O S07. POTÊNCIA: XX08. CAIXA E PORTA: XX08. CONTATO: (85) 99811-608609. ENDEREÇO COMPLETO: Rua Luís Mendes De Barros, 800 - Pajuçara - Maracanaú - CE - CEP 61932-10010. CONDOMÍNIO: NÃO10. PONTO DE REFERÊNCIA: NÃO POSSUI11. DISPONIBILIDADE: DIA TODO12. OBSERVAÇÃO: LIGAR ANTES
A50: 3843906 | B50: PATRICIA DA COSTA COELHO | C50: Encerramento | D50: PENDÊNCIA FIBRA - PF | E50: Rua | F50: Rua Santa Elisa | G50: 1019 | H50: Fortaleza | I50: Pirambu | L50: ELIZEU DA SILVA FERREIRA | M50: RUAN VICTOR SANTOS SOUZA CLARINDO | N50: 46262 | O50: 46263 | P50: 46266 | Q50: 46266 | R50: Sim | S50: 3 | T50: Cliente Pessoa Física | U50: Pendência | V50: LOS | W50: Fibra Sem Sinal / Luz Los Vermelha | X50: Troca Conector - Desgastado | AA50: OLT Barra do Ceará VLAN 1001 | AB50: *PENDÊNCIA**Data* 01/09/2026*Técnico* ELIZEU DA SILVA FERREIRA CLIENTE: PATRICIA DA COSTA COELHOENDEREÇO: Rua Santa Elisa, 1019, Pirambu - Fortaleza*Caixa*:*Porta*:*SINAL DA CAIXA*.*SINAL DO CLIENTE*.SERVIÇO REALIZADO Conector refeito *Material utilizado*00Conector Verde00Conector Azul00 Fixa fio00 Canaleta00Esticador00Adesivo conector00 RJ4500 pat Cord00 ONT ZTE00 Repetidor Mercuses00 ont intelbras fiberhome*OBS* : Internet ok cliente.Login:Senha:*VALOR* :*Cabo inicial*:*Cabo final* *Metragem* *Drop inicial*:0000*Drop final* : 0000*Metragem*:0000Dispositivo: samsung SM-A065MVersão do Android: 16Versão do V·Tasks: 5.9.211 Status alterado de Andamento para Encerramento | AC50: 28/08/2026 - 12:51 01. RELATO DO CLIENTE: Cliente informa está sem internet e tem uma led vermelha piscando no equipamento02. ANÁLISE SISTEMA (UNM): LinkLoss03. ANÁLISE SISTEMA (VOALLE): Offline04. EXTRATO COM QUEDAS: NÃO 05. GERENCIAMENTO REM. HABILITADO: A verificar07. POTÊNCIA: xx08. CAIXA E PORTA: cx8355 p-0408. CONTATO: (85)98548-7098 e (85)98416-837509. ENDEREÇO COMPLETO: Rua Santa Elisa, 1019 - Pirambu - Fortaleza - CE - CEP 60311020 10. CONDOMÍNIO: NÃO 10. PONTO DE REFERÊNCIA: ESCOLA BRINCANDO E APRENDENDO11. DISPONIBILIDADE: Total12. OBSERVAÇÃO:
A51: 3843985 | B51: FRANCISCA NIKELLY PEREIRA DE ALMEIDA | C51: Encerramento | D51: INSTALAÇÃO FIBRA - COND. | E51: Alameda | F51: Alameda Uruguai | G51: 0 | H51: Eusébio | I51: Cidade Alpha | J51: -38867458 | K51: -384894774 | L51: ANTONIO FELIPE CASTRO DE OLIVEIRA | M51: MARIA THALYA BATISTA FERREIRA | N51: 46262 | O51: 46265 | P51: 46267 | Q51: 46267 | R51: Sim | S51: 2 | T51: Cliente Condomínio | U51: Instalação | X51: Troca Conector - Desgastado | AA51: OLT Eusébio 1 VLAN 9 | AB51: ☑️☑️ *INSTALACAO/COND* ☑️☑️*Chegada**Saída**Data* 02/09/2026*SUPORTE**COMERCIAL* *Técnico* Ant.Felipe/Irineto*Cliente* FRANCISCA NIKELLY PEREIRA DE ALMEIDA*Endereço* Alameda Uruguai, 0, Cidade Alpha - Eusébio*obs sobre o endereço* *LOCALIZAÇÃO*https://maps.app.goo.gl/U73PnMFWmKkAE9g76?g_st=ic*CONTARO* *Caixa* 4225*PORTA* 5*SINAL DO CAIXA* 23*SINAL DO CLIENTE* 23*Velocidade* *Material utilizado*2 Conector Verde 0 Conector Azul0 abraçadeira de nylon0 Fixa fixo 0 canaleta,0 Esticador0 adesivo 0 Per Cord0 RJ45PROBLEMA RELATADO: OBS. InstaladoCabo de redeInicial Final Utilizado *SENHA DO EQUIPAMENTO* *Equipamento anterior**Equipamento Atual**MEC* FHTTFE2FE919*Drop inicial* *Drop Final**Metragem* 282*Classificação de Encerramento* *RESOLVIDO*✅Dispositivo: iPhoneVersão do iOS: 26.5Versão do V·Tasks: 5.9.212 Status alterado de Reagendado para Encerramento | AC51: VENDEDOR: MARIA THALYAÁREA: PAP () CALL-CENTER ( ) LOJA ( ) TBR ( X )TITULAR:FRANCISCA NIKELLY PEREIRA DE ALMEIDATELEFONE:88-998380191WHATSAPP:88-998380191DISPONIBILIDADE: MANHA( ) TARDE ( ) DIA TODO (X)DATA:CIDADE E BAIRRO: CIDAD ALPHA-EUSEBIO-CEPLANO: 700MBVALOR ORIGINAL DO PLANO:109,99POSSUI DESCONTO DE PONTUALIDADE? SIM ( ) NÃO ( X )SE SIM: D5 ( ) ou DNET - D10( )DESCONTO DE __ , SE PAGO ATÉ O VENCIMENTO POR 12 MESESTAXA INSTALAÇÃO: FREEATENDIMENTO REGISTRADO:Google Drive ( ) Fortics ( ) Smart ( X )FIDELIDADE: ( X ) SIM NÃO ( )CLIENTE DESEJA NOTA FISCAL: SIM ( ) NÃO ( X )COORD:-3.886478192050522, -38.489541777582936CAIXA: SNCASA DUPLEX ( X ) CASA TERREA ()QUANTOS E QUAIS APARELHOS CONECTADOS:( 4 ) Celular( 3 ) TV Smart( 2 ) Computador/ NotebookOBSERVAÇÃO ADICIONAL:Ativação do contrato: 174132---- Endereço de Instalação ----CEP: 61766-090Logradouro: Alameda UruguaiNúmero: 0Bairro: Cidade AlphaEstado: CECidade: EusébioComplemento: Quadra PA1 /Lote 03Referência: Ceará 2---- Serviços a serem ativados ----- 1023 - ULTRAINFO - 700MB
A52: 3844010 | B52: PATRICIO COSTA DE ABREU | C52: Encerramento | D52: PENDÊNCIA FIBRA - PF | E52: Travessa | F52: Travessa Beira Rio | G52: 27 | H52: Aquiraz | I52: Jacaúna | J52: -3.9454e+15 | K52: -3.8289516e+15 | L52: GUTEMBERGUE OLIVEIRA | M52: LUANA IASMIM DE SOUZA OLIVEIRA | N52: 46262 | O52: 46263 | P52: 46266 | Q52: 46266 | R52: Sim | S52: 3 | T52: Cliente Pessoa Física | U52: Pendência | V52: LOS | W52: Fibra Sem Sinal / Luz Los Vermelha | X52: Troca Conector - Desgastado | AA52: OLT Tapera VLAN 1009 | AB52: , 🛠 *PENDÊNCIA* 🧰*Data:* 01/09/26*Atendente Responsável:* *Técnico:* gutembergue Cliente:PATRICIO COSTA DE ABREUBairro:Travessa Beira Rio, 27, Jacaúna - Aquiraz*Caixa:1440Port:08*Potência da caixa:21*Potência do cliente:21*Acesso remoto Habilitado:*Serviço Realizado:*Foi feito a troca de cabo feito as configurações de canais feito os testes junto ao cliente serviço já normalizado Material Utilizado:151-metros de drop 2-conector verde Obs: rompimento de cabo foi utilizado 151 metros de drop *Valor:* *Obs: *Drop inicia:1000*Drop final:849*Metragem:151*Cabo de rede:* *Classificação de Encerramento:*resolvidoDispositivo: motorola moto g06Versão do Android: 15Versão do V·Tasks: 5.9.211 Status alterado de Reagendado para Encerramento | AC52: 28/08/2026 - 13:52 01. RELATO DO CLIENTE: Sem internet, LED vermelho no equipamento.02. ANÁLISE SISTEMA (UNM): Linkloss03. ANÁLISE SISTEMA (VOALLE): Offline04. EXTRATO COM QUEDAS: *05. GERENCIAMENTO REM. HABILITADO: Verificar06. PROCEDIMENTO REALIZADO: *07. POTÊNCIA: *08. CAIXA E PORTA: CX2428 P0608. CONTATO: (75)99177-8090 - (85)99102-198009. ENDEREÇO COMPLETO: Travessa Beira Rio, 27 - Jacaúna - Aquiraz/CE10. CONDOMÍNIO: NÃO 10. PONTO DE REFERÊNCIA: próximo à praça da beira rio11. DISPONIBILIDADE: Dia todo12. OBSERVAÇÃO:
A53: 3844025 | B53: KATIUCIA AMORIM DE ARAUJO BARRETO DE SOUZA | C53: Encerramento | D53: TRANSFERÊNCIA - PF | E53: Rua | F53: Rua 10 | G53: 118 | H53: Aquiraz | I53: Lot. Planalto do Sol | J53: -38347974 | K53: -38575451 | L53: JOSE ILDEVAM SOUSA DO NASCIMENTO | M53: HILDERLAYNE FERREIRA PIRES SANTOS | N53: 46262 | O53: 46265 | P53: 46266 | Q53: 46266 | R53: Sim | S53: 1 | T53: Cliente Pessoa Física | U53: Transferência | V53: Equipamento no Novo Endereço | W53: Taxa Isenta | X53: Troca Conector - Desgastado | AA53: OLT Aquiraz VLAN 12 | AB53: 🛠 *TRANSFERÊNCIA* 🧰*Data:* 01/09/2026*Atendente Responsável:* *Provisionamento:* *Técnico:* Ildevam *Cliente:* KATIA LIANA DE SOUSA ALVES*Endereço:* *Bairro:* Divinéia *Caixa/Porta:* 7815/01*Potência da caixa:* *Potência do cliente:* - 24*Acesso remoto habilitado:* sim *Senha do Roteador:* Fibra@info *Serviço Realizado:* Transferência *Material Utilizado:*- 1 adesivo- 1 conector azul- 4 fixa fios*Valor:* Isento *Mec Nova:* *Mec Antiga:* *Obs:* Cabo puchado.*Drop inicial:* *Drop final:* *Metragem Total:* *Classificação de Encerramento:* Finalizado✅Dispositivo: samsung SM-G781BVersão do Android: 13Versão do V·Tasks: 5.9.209 Status alterado de Remarcação para Encerramento | AC53: 28/08/2026 - 14:01 PERGUNTA PRE-REQUISITO PARA ABERTURA:-CLIENTE JA SE MUDOU? SimTEM ENERGIA ELETRICA NO LOCAL? Sim- É CONDOMINIO ? SIM ( ) NÃO ( x)SE A RESPOSTA FOR NÃO PARA QUALQUER UMA DAS PERGUNTAS, A SOLICITAÇÃO NÃO PODE SER ABERTA.01. FONE 01: (61) 99155-320002. FONE 02: (61) 99983-881803. WHATSAPP: (61) 99155-320004. NOVO ENDEREÇO:* RUA: Pedro Rodrigues dos Santos* Nº: 62* BAIRRO: Divineia* CIDADE: Aquiraz* PONTO DE REFERÊNCIA DO ENDEREÇO NOVO: Na rua da academia vfitness05. CAIXA: CX 781506. COORDENADAS: Lat: -3.9142546 / Long: -38.382978707. DISPONIBILIDADE PARA RECEBER A EQUIPE: Sim09. DEIXAR O CLIENTE CIENTE QUE OS EQUIPAMENTOS PRECISAM ESTAR NO NOVO ENDEREÇO.10. VALOR ? Isento mediante renovação da fidelidade11. ANTIGO ENDEREÇO:* RUA: Rua 10 * Nº: Casa 118* BAIRRO: Lot. Planalto do Sol* CIDADE: Aquiraz, CE11. PRAZO: 72 HORAS UTEIS.OBS:
A54: 3844063 | B54: JOSE LIANDERSON DE SOUSA SILVA | C54: Encerramento | D54: DNET - RETRABALHO PENDÊNCIA - COND. | E54: Rua | F54: Rua João Campos Filho | G54: 167 | H54: Maracanaú | I54: Parque Tijuca | J54: -38454058 | K54: -386266417 | L54: CARLOS HENRIQUE LINO SILVA | M54: LUANA IASMIM DE SOUZA OLIVEIRA | N54: 46262 | O54: 46262 | P54: 46268 | Q54: 46266 | R54: Sim | S54: 6 | T54: DNET - Cliente Condomínio | U54: DNET - Retrabalho | V54: DNET - LOS | W54: DNET - Fibra Sem Sinal / Luz Los Vermelha | X54: Troca Conector - Desgastado | Y54: Carlos Henrique Lino Silva | Z54: 3844063 | AA54: OLT DNET TEMPORARIO | AB54: Abertura Solicitação para visita técnica no cliente, a pedido do mesmo.☑️☑️ *PENDÊNCIA* ☑️☑️*Chegada**Saída**Data* 01.09.2026*SUPORTE**COMERCIAL* *Técnico* CARLOS HENRIQUE*AUXILIAR:* ELEEONAI VIANA *CLIENTE:* DAVI HENRRIQUE CAITANO DE SOUSA*ENDEREÇO* Rua Antero Quental, 155, São Bento - Fortaleza*obs sobre o endereço* *CONTATO* *Caixa* *PORTA* *SINAL DA CAIXA**SINAL DO CLIENTE*-25*Velocidade* *Material utilizado* 1Conector Verde Conector Azul Fixa fixo canaleta0 Esticadoadesivo 0 Per CordRJ45 TUBETEPROBLEMA RELATADO: SEM SINAL.*OBS* POTENCIA BAIXA, FOI REALIZADO A TEOCA DO CONECTOR E CONEXÃO NORMALIZOU. *VALOR:* Cabo de redeInicial Final Metragem*SENHA DO EQUIPAMENTO* *Equipamento anterior* *ONT* *ONU* *ROTEADOR:* *Equipamento Atual* *ONT* *ONU* *ROTEADOR* *Drop inicial* *Drop Final* *Metragem:* *OBS:* *Classificação de Encerramento*RESOLVIDO✅Dispositivo: samsung SM-A055MVersão do Android: 14Versão do V·Tasks: 5.9.211 Status alterado de Tratamento Infra para Encerramento | AC54: 28/08/2026 - 14:04 01. RELATO DO CLIENTE: Sem internet novamente, LED vermelho no equipamento.02. ANÁLISE SISTEMA (UNM): Linkloss03. ANÁLISE SISTEMA (VOALLE): Offline04. TÉCNICO ULTIMO ATENDIMENTO (ADICIONAR TAMBÉM AO CHECKLIST FINAL): CARLOS HENRIQUE LINO SILVA05. EXTRATO COM QUEDAS: *06. GERENCIAMENTO REM. HABILITADO: Verificar07. PROCEDIMENTO REALIZADO: *08. POTÊNCIA: *09. CAIXA E PORTA: *10. CONTATO: (85)98209-181411. ENDEREÇO COMPLETO: Rua João Campos Filho, 167 - Parque Tijuca - Maracanaú - CE - CEP 61917-390 - Bloco 1012. CONDOMÍNIO: Sim13. PONTO DE REFERÊNCIA: Piso no na CE 06514. DISPONIBILIDADE: Dia todo15. OBSERVAÇÃO:
A55: 3844098 | B55: FRANCISCA CLAUDIANA DE PAULO | C55: Encerramento | D55: DNET - INSTALAÇÃO FIBRA - PF | E55: Rua | F55: Rua José do Carmo Barbosa | G55: 57 | H55: Fortaleza | I55: Ancuri | J55: -38668797 | K55: -38503713 | L55: FRANCISCO HELIO MARINHO CUNHA NETO | M55: ANA GABRIELLY ALVES MENEZES | N55: 46262 | O55: 46265 | P55: 46266 | Q55: 46266 | R55: Sim | S55: 1 | T55: DNET - Cliente Pessoa Física | U55: DNET - Instalação | X55: Troca Conector - Desgastado | AA55: OLT DNET TEMPORARIO | AB55: 🛠 *INSTALAÇÃO* 🧰*Data:* 01/09/2026*Técnico:* Hélio Marinho *Cliente:* FRANCISCA CLAUDIANA DE PAULO*Endereço:* Rua José do Carmo Barbosa, 57, Ancuri - Fortaleza*Potência:* -19*Caixa:* 11177*porta*: 15*MATERIAL USADO* Conector verde: 2undConector azul Adesivo Fixa fio: 10und Canaleta: 1und EQUIPAMENTOS * Ont ztegd4b2fbca* Roteador * ONU *inicial:* 50m*Final:* 25m*Metragem:* 25m*Serviço Realizado:* Instalação Feito os testes com o cliente.*Classificação de Encerramento:* Instalação Concluída.Dispositivo: motorola moto g23Versão do Android: 14Versão do V·Tasks: 5.9.211 Status alterado de Andamento para Encerramento | AC55: VENDEDOR: GABRIELLY MENEZESÁREA: PAP () CALL-CENTER ( ) LOJA ( ) TBR ( )TITULAR: FRANCISCA CLAUDIANA DE PAULOTELEFONE:(85) 9865-49181WHATSAPP:(85) 9865-49181DISPONIBILIDADE: MANHA( ) TARDE ( ) DIA TODO (X)DATA: 29/08/2026CIDADE E BAIRRO: Rua José do Carmo Barbosa, 57 Santa féPLANO:500 MB – R$ 79,99 por 12 meses* ( após fica R$ 99,99 )VALOR ORIGINAL DO PLANO: 99,99POSSUI DESCONTO DE PONTUALIDADE? SIM ( ) NÃO (x )SE SIM: D5 ( ) ou DNET - D10( )DESCONTO DE __ , SE PAGO ATÉ O VENCIMENTO POR 12 MESESTAXA INSTALAÇÃO: GRATISATENDIMENTO REGISTRADO:Google Drive ( ) Fortics ( ) Smart ( X)FIDELIDADE: (X ) SIM NÃO ( )CLIENTE DESEJA NOTA FISCAL: SIM ( ) NÃO ( X)COORD:-3.866604881593597, -38.50370154907525CAIXA:CX 11369CASA DUPLEX (X ) CASA TERREA ()QUANTOS E QUAIS APARELHOS CONECTADOS: CELULAR, TVOBSERVAÇÃO ADICIONAL:Ativação do contrato: 174135---- Endereço de Instalação ----CEP: 60874-224Logradouro: Rua José do Carmo BarbosaNúmero: 57Bairro: AncuriEstado: CECidade: Fortaleza---- Serviços a serem ativados ----- 1124 - ULTRABLACK - DNET - 500MB
A56: 3844122 | B56: ISIDORO BATISTA DA SILVA FILHO | C56: Encerramento | D56: TRANSFERÊNCIA - PF | E56: Rua | F56: Rua Edésio Monteiro | G56: 941 | H56: Fortaleza | I56: Ancuri | J56: -38657806 | K56: -385036707 | L56: MARCOS AURELIO DE SOUSA OLIVEIRA | M56: ANA LIDIA DA COSTA SANTOS FERREIRA | N56: 46262 | O56: 46265 | P56: 46266 | Q56: 46266 | R56: Sim | S56: 1 | T56: Cliente Pessoa Física | U56: Transferência | V56: Equipamento no Novo Endereço | W56: Taxa Faturada | X56: Troca Conector - Desgastado | AA56: OLT Conj. Palmeiras VLAN 1002 | AB56: *TRANSFERÊNCIA* *Data* 01. 09.2026*Técnico*: Marcos Aurélio*CLIENTE:* ISIDORO BATISTA DA SILVA FILHO*ENDEREÇO* Rua Edésio Monteiro, 941, Ancuri - Fortaleza*Caixa*: 2102*Porta*: 03*SINAL DA CAIXA*: 23*SINAL DO CLIENTE* 23*SERVIÇO REALIZADO:* TRANSFERÊNCIA*Material utilizado*01 Conector Verde00 Conector Azul00 Fixa fio00 Canaleta00 Esticador00 Adesivo conector 00 RJ4500 patch cord*Equipamento utilizado**Equipamento recolhido*--*OBS* : Equipamento instalado no local solicitado pelo cliente *VALOR* : 75 3X*Cabo inicial* 00m*Cabo final* 00m*Metragem* 00m*Drop inicial* *Drop final* *Metragem* Status: TRANSFERÊNCIA CONCLUÍDADispositivo: samsung SM-A075MVersão do Android: 16Versão do V·Tasks: 5.9.211 Status alterado de Andamento para Encerramento | AC56: 28/08/2026 - 14:43 PERGUNTA PRE-REQUISITO PARA ABERTURA: -CLIENTE JA SE MUDOU? SIMTEM ENERGIA ELETRICA NO LOCAL? SIM- É CONDOMINIO ? SIM (X) NÃO ( ) SE A RESPOSTA FOR NÃO PARA QUALQUER UMA DAS PERGUNTAS, A SOLICITAÇÃO NÃO PODE SER ABERTA. 01. FONE 01: 8399117467902. FONE 02: 8399399308403. WHATSAPP: 8399117467904. NOVO ENDEREÇO: * RUA: RUA EDESIO MONTEIRO* Nº: 941 CASA 3* BAIRRO: SANTA FÉ * CIDADE: FORTALEZA* PONTO DE REFERÊNCIA DO ENDEREÇO NOVO: PROXIMO AO SESC MESA BRASIL05. CAIXA: 210206. COORDENADAS: -3.865614677507801, -38.5036277890415207. DISPONIBILIDADE PARA RECEBER A EQUIPE: 09. DEIXAR O CLIENTE CIENTE QUE OS EQUIPAMENTOS PRECISAM ESTAR NO NOVO ENDEREÇO. 10. VALOR ? 75,00 DE 3X11. ANTIGO ENDEREÇO: * RUA: RUA EDESIO MONTEIRO* Nº: 949* BAIRRO: SANTA FÉ* CIDADE: FORTALEZA11. PRAZO: 72 HORAS UTEIS. OBS: SE POSSIVEL AGENDAR PARA AMANHÃ 29/08/2026
A57: 3844124 | B57: FRANCISCA CLAUDIANA DE PAULO | C57: Encerramento | D57: DNET - REPETIDOR - PF | E57: Rua | F57: Rua José do Carmo Barbosa | G57: 57 | H57: Fortaleza | I57: Ancuri | J57: -38668797 | K57: -38503713 | L57: FRANCISCO HELIO MARINHO CUNHA NETO | M57: ANA GABRIELLY ALVES MENEZES | N57: 46262 | O57: 46265 | P57: 46267 | Q57: 46267 | R57: Sim | S57: 2 | T57: DNET - Cliente Pessoa Física | U57: DNET - Repetidor | V57: DNET - Inclusão Ultra Repetidor 4.0 | W57: DNET - Faturar Material Excedente | X57: Troca Conector - Desgastado | AA57: OLT DNET TEMPORARIO | AB57: 🛠 *INSTALAÇÃO REPETIDOR* 🧰*Data:* 02/09/2026*Técnico:* Hélio Marinho *Cliente:* FRANCISCA CLAUDIANA DE PAULO*Endereço:* Rua José do Carmo Barbosa, 57, Ancuri - Fortaleza*MATERIAL USADO* RJ45 : 2und Fixa fio: 20und Canaleta: 1und EQUIPAMENTOS * Ont * Roteador ns22213p9008780* ONU *inicial:* 140m*Final:* 160m*Metragem:* 20m*Serviço Realizado:* Instalação Repetidor 4.0Feito os testes com o cliente.*Valor:* isento *Classificação de Encerramento:* Instalação Concluída.Dispositivo: motorola moto g23Versão do Android: 14Versão do V·Tasks: 5.9.211 Status alterado de Andamento para Encerramento | AC57: 28/08/2026 - 14:38 1.SOLICITAÇÃO: ▶ Repetidor 2.4 GHz e 5G → R$ 22,99/mês (incluso cabo e RJ)2.ROTEADOR É DO CLIENTE ( ) ,COMODATO ( x) OU LOCAÇÃO ( )? 3.CONTATO TELEFÔNICO (01): (85) 98654-91813. (WHATSAPP): (85) 98654-91814.WHATSAPP: (85) 98654-91815.PONTO DE REFERÊNCIA: IBC6.DISPONIBILIDADE: SOMENTE A TARDE7.VALOR DO SERVIÇO / FORMA DE PAGAMENTO E VALORES: Repetidor 2.4 GHz e 5G → R$ 22,99/mês (incluso cabo e RJ)8.PRAZO: 5 DIAS CORRIDOS A PARTIR DA ABERTURA DO ATENDIMENTO DO NÍVEL 09.OBS FINAIS:
A58: 3844140 | B58: JANE BEATRIZ PINHEIRO XAVIER | C58: Encerramento | D58: INSTALAÇÃO FIBRA - PF | E58: Rua | F58: Rua Olyntho Arruda | G58: 1088 | H58: Fortaleza | I58: Sapiranga-Coité | J58: -37959814 | K58: -384662167 | L58: VANIZIO PEREIRA AZEVEDO DO NASCIMENTO | M58: VITOR CRUZ BATISTA | N58: 46262 | O58: 46265 | P58: 46268 | Q58: 46268 | R58: Sim | S58: 3 | T58: Cliente Pessoa Física | U58: Instalação | X58: Troca Conector - Desgastado | AA58: OLT WSTC VLAN 2321 | AB58: 🛠 *INSTALAÇÃO/COND.* 🧰*Chegada:**Saída:**Data:* 03/09/2026*Atendente N:* *Técnico:* Vanízio/Claylson *Cliente:* JANE BEATRIZ PINHEIRO XAVIER*Endereço:* Rua Olyntho Arruda, 1088, Sapiranga-Coité - Fortaleza*Caixa:* 10468*Porta:* 02*Potência da caixa:* -20*Potência do cliente:*-20*Serviço Realizado:* Instalação de Internet *Material Utilizado*01 ont Intelbras(188F)00 ont Zte ()00 mercusys ()00 onu mini Apc ()00 fonte 12V00 Canaleta10 Fixa Fio05 esticador85 metros de drop02 conector verde00 conector azul00 conector RJ4500 lacre*Valor:* *Obs:* *Drop inicial:* 190*Drop final:* 105*Metragem Total:* 85*Cabo de rede:* metros*Classificação de Encerramento:*Dispositivo: samsung SM-A266MVersão do Android: 16Versão do V·Tasks: 5.9.213 Status alterado de Reagendado para Encerramento | AC58: VENDEDOR: VITOR CRUZ BATISTA ÁREA: PAP (X) CALL-CENTER ( ) LOJA ( ) TBR ( )TITULAR: JANE BEATRIZ PINHEIRO XAVIERTELEFONE: 85 99909-3282WHATSAPP: 85 99909-3282DISPONIBILIDADE: MANHA( ) TARDE ( ) DIA TODO (x)DATA:CIDADE E BAIRRO: FORTALEZA/SAPIRANGA PLANO: 400MBVALOR ORIGINAL DO PLANO: POSSUI DESCONTO DE PONTUALIDADE? SIM (x ) NÃO ( )SE SIM: D5 (x) ou DNET - D10( )DESCONTO DE _5_ , SE PAGO ATÉ O VENCIMENTO POR 12 MESESTAXA INSTALAÇÃO: 00ATENDIMENTO REGISTRADO:Google Drive ( ) Fortics ( ) Smart (x )FIDELIDADE: (x ) SIM NÃO ( )CLIENTE DESEJA NOTA FISCAL: SIM ( ) NÃO ( x)COORD: -3.918432,-38.592774CAIXA: 79,99CASA DUPLEX ( ) CASA TERREA (x)QUANTOS E QUAIS APARELHOS CONECTADOS:OBSERVAÇÃO ADICIONAL: SERÁ NECESSÁRIO APOIO DE UM AUXILIAR Ativação do contrato: 174138---- Endereço de Instalação ----CEP: 60833-322Logradouro: Rua Olyntho ArrudaNúmero: 1088Bairro: Sapiranga-CoitéEstado: CECidade: FortalezaComplemento: casa altosReferência: próximo a disc água Gungel---- Serviços a serem ativados ----- 0522 - IFT - ULTRAINFO - 400MB
A59: 3844161 | B59: MARIA NATALY DE OLIVEIRA MOREIRA | C59: Encerramento | D59: TRANSFERÊNCIA - PF | E59: Rua | F59: Rua São Jorge | G59: 1526 altos 2 | H59: Fortaleza | I59: Barra do Ceará | L59: JOSE EDNARDO DA SILVA DE LIMA | M59: KAROL HELLEN DE ALMEIDA SILVA | N59: 46262 | O59: 46265 | P59: 46267 | Q59: 46267 | R59: Sim | S59: 2 | T59: Cliente Pessoa Física | U59: Transferência | V59: Equipamento no Novo Endereço | W59: Taxa Isenta | X59: Troca Conector - Desgastado | AA59: OLT Barra do Ceará VLAN 1001 | AB59: transferência Dispositivo: motorola moto g06Versão do Android: 15Versão do V·Tasks: 5.9.213 Status alterado de Remarcação para Encerramento | AC59: 28/08/2026 - 15:17 PERGUNTA PRE-REQUISITO PARA ABERTURA:-CLIENTE JA SE MUDOU? simTEM ENERGIA ELETRICA NO LOCAL? sim- É CONDOMINIO ? SIM ( ) NÃO (x)SE A RESPOSTA FOR NÃO PARA QUALQUER UMA DAS PERGUNTAS, A SOLICITAÇÃO NÃO PODE SER ABERTA.01. FONE 01:8598813321902. FONE 02:8598813321903. WHATSAPP:8598782983404. NOVO ENDEREÇO:* RUA: Rua São Jorge* Nº: 1526 altos 02* BAIRRO: colônia* CIDADE:fortaleza* PONTO DE REFERÊNCIA DO ENDEREÇO NOVO:Próx ao condomínio santo Agostinho05. CAIXA:1089406. COORDENADAS:-3.703032461127889, -38.575542491759707. DISPONIBILIDADE PARA RECEBER A EQUIPE: sim , dia todo09. DEIXAR O CLIENTE CIENTE QUE OS EQUIPAMENTOS PRECISAM ESTAR NO NOVO ENDEREÇO.10. VALOR ?isenta 11. ANTIGO ENDEREÇO:Rua São Jorge, 1321 - Barra do Ceará - Fortaleza* RUA:Rua São Jorge* Nº:1321* BAIRRO: Barra do Ceará * CIDADE: Fortaleza11. PRAZO: 72 HORAS UTEIS.OBS:
A60: 3844162 | B60: ANA KELLE SANTOS SILVA RABELO | C60: Encerramento | D60: DNET - PENDÊNCIA FIBRA - COND. | E60: Rua | F60: Rua G | G60: 255 | H60: Fortaleza | I60: Paupina | J60: -38521348 | K60: -384897959 | L60: CARLOS HENRIQUE LINO SILVA | M60: ITALO NERY FORTE | N60: 46262 | O60: 46263 | P60: 46267 | Q60: 46267 | R60: Sim | S60: 4 | T60: DNET - Cliente Condomínio | U60: DNET - Pendência | V60: DNET - LOS | W60: DNET - Fibra Sem Sinal / Luz Los Vermelha | X60: Troca Conector - Desgastado | AA60: OLT DNET TEMPORARIO | AB60: Abertura Solicitação para visita técnica no cliente, a pedido do mesmo.NORMALIZADO APOS MANUTENÇÃO DA INFRAESTRUTURA. Dispositivo: samsung SM-A055MVersão do Android: 14Versão do V·Tasks: 5.9.213 Status alterado de Tratamento Infra para Encerramento | AC60: 28/08/2026 - 15:13 01. RELATO DO CLIENTE: Cliente está sem conexão, luz vermelha piscando no roteador. 02. ANÁLISE SISTEMA (UNM): link los03. ANÁLISE SISTEMA (VOALLE): off line04. EXTRATO COM QUEDAS: NÃO 05. GERENCIAMENTO REM. HABILITADO:NÃO 06. PROCEDIMENTO REALIZADO: reboot 07. POTÊNCIA: link los08. CAIXA E PORTA: xxxx 08. CONTATO: 8898138257609. ENDEREÇO COMPLETO: Rua G 255, Paupina - Fortaleza, CE60873-57510. CONDOMÍNIO: SIM10. PONTO DE REFERÊNCIA: escola em de ensino fundamental em frente11. DISPONIBILIDADE: tarde12. OBSERVAÇÃO: Conjunto Residencial dos Escritores Bloco 27 apto 104
A61: 3844186 | B61: FRANCISCO RODRIGUES | C61: Encerramento | D61: INSTALAÇÃO FIBRA - PF | E61: Rua | F61: Rua Dom Pedro I | G61: 1038 | H61: Maracanaú | I61: Boa Esperança | J61: -38527854 | K61: -385801435 | L61: LUIZ OCTAVIO ALMEIDA DA SILVA | M61: JAILSON FERREIRA MONTEIRO | N61: 46262 | O61: 46265 | P61: 46268 | Q61: 46267 | R61: Sim | S61: 3 | T61: Cliente Pessoa Física | U61: Instalação | X61: Troca Conector - Desgastado | AA61: OLT Pajuçara VLAN 1007 | AB61: ✅ INSTALACAO ✅*Data* 02.09.2026*Técnico* Luiz Octávio Cliente: MATHEUS DOS SANTOS CABRAL ⏹️ *Caixa* 3578 *Porta.* 08*SINAL DA CAIXA* -22*SINAL DO CLIENTE* -22*DROP COM ETIQUETA 🏷️* ☎️ *GESTÃO DE O.S* *ATENDIMENTO:* 📝 *SERVIÇO: Instalação Concluida⚙️ *Material utilizado*02 Conector Verde00 Conector Azul13 Fixa fio00 Canaleta00 Esticador00 Adesivo conector 00 RJ4500 patch cord📡 *Equipamento utilizado 00 ONT INTEL (MAC)00 ZTE (MAC) =00 HG325AX (MAC) = 00 XC220G3 (MAC) =00 MERCUSYS (MAC) =00 SHORELINE (MAC)00 ONT TPL (MAC)=*Equipamento RMA*00 ZTE (MAC) =00HG325AX (MAC) = 00 ONT GLOBAL (MAC) =00 ROTEADOR TPL (MAC)= 00 ROTEADOR TENDA (MAC) = 00 MERCUSYS (MAC) =00 ONU MINI (MAC) = 00 ONU APC (MAC) = *OBS* instalação *Cabo inicial* 00m*Cabo final* 00m*Metragem* 00m*Drop inicial* 1.000*Drop final* 913*Metragem* 87*Classificação de Encerramento**RESOLVIDO✅*Dispositivo: motorola moto g04sVersão do Android: 14Versão do V·Tasks: 5.9.213 Status alterado de Reagendado para Encerramento | AC61: 28/08/2026 - 15:10 VENDEDOR: DANIELÁREA: PAP (X) CALL-CENTER ( ) LOJA ( ) TBR ( )TITULAR: FRANCISCO RODRIGUESTELEFONE: 8599198813WHATSAPP: 85991008460DISPONIBILIDADE: MANHA( X) TARDE ( ) DIA TODO ()DATA:CIDADE E BAIRRO: MARACANAU PAJUÇARAPLANO: 500 promoção corujãoVALOR ORIGINAL DO PLANO: 99.99POSSUI DESCONTO DE PONTUALIDADE? SIM (x ) NÃO ( )SE SIM: D5 ( ) ou DNET - D10( )DESCONTO DE 20,00 SE PAGO ATÉ O VENCIMENTO POR 12 MESESTAXA INSTALAÇÃO:ATENDIMENTO REGISTRADO:Google Drive ( ) Fortics ( ) Smart ( )FIDELIDADE: (x ) SIM NÃO ( )CLIENTE DESEJA NOTA FISCAL: SIM ( ) NÃO ( )COORD: -3.854141,-38.576477CX3578CAIXA:CASA DUPLEX ( ) CASA TERREA (x)QUANTOS E QUAIS APARELHOS CONECTADOS: 3 celulares e duas tvOBSERVAÇÃO ADICIONAL:Ativação do contrato: 174092---- Endereço de Instalação ----CEP: 61935-610Logradouro: Rua Dom Pedro INúmero: 1038Bairro: Boa EsperançaEstado: CECidade: MaracanaúComplemento: travessa---- Serviços a serem ativados ----- 0422 - ULTRAINFO - 500MB
A62: 3844210 | B62: MIRLENE ROSEMBERG PEREIRA DOS SANTOS | C62: Encerramento | D62: DNET - PENDENCIA FIBRA - PF | E62: Rua | F62: RUA HARIBERTO ONOFRE | G62: 44 | H62: Fortaleza | I62: ANCURI | L62: FRANCISCO HELIO MARINHO CUNHA NETO | M62: CLEITON CHAGAS PEREIRA | N62: 46262 | O62: 46263 | P62: 46266 | Q62: 46266 | R62: Sim | S62: 3 | T62: DNET - Cliente Pessoa Física | U62: DNET - Pendência | V62: DNET - LOS | W62: DNET - Fibra Sem Sinal / Luz Los Vermelha | X62: Troca Conector - Desgastado | AA62: OLT DNET TEMPORARIO | AB62: *PENDÊNCIA**Data:* 01/09/2026*Técnico:* Hélio Marinho *Cliente:* MIRLENE ROSEMBERG PEREIRA DOS SANTOS*Endereço:* RUA HARIBERTO ONOFRE, 44, ANCURI - Fortaleza*Caixa:* 11511*Porta:* 8*Potência da Caixa:*-20*Potência do Cliente:* -21*Serviço:* atendimento sem conexão, cabo da cliente tinha uma emenda, puxando novo drop , sinal -21, conexão normalizada.*Materiais* *conector azul* 1und*conector verde* 1und*Fixa fio* *adesivo* 1und*canaleta* *Petcord* *RJ 45* *EQUIPAMENTOS**ONT* *ROTEADOR* *ONU* *Drop* *Início* 150m*Fim* 50m*Utilizado* 100m*EQUIPAMENTO RECOLHIDO* ONU: Roteador: ONT: *Valor:* *Obs*Dispositivo: motorola moto g23Versão do Android: 14Versão do V·Tasks: 5.9.211 Status alterado de Remarcação para Encerramento | AC62: 28/08/2026 - 15:48 01. RELATO DO CLIENTE: sem internet, led vermelho02. ANÁLISE SISTEMA (UNM): link loss03. ANÁLISE SISTEMA (VOALLE): off line04. EXTRATO COM QUEDAS: NÃO05. GERENCIAMENTO REM. HABILITADO: verificar06. PROCEDIMENTO REALIZADO: reiniciado o roteador.07. POTÊNCIA: x08. CAIXA E PORTA: CX 11511 P-908. CONTATO: (85) 99430-327409. ENDEREÇO COMPLETO: RUA HARIBERTO ONOFRE, 44 - ANCURI - Fortaleza - CE - CEP 60874100 - POR TRAS DA CASA 147010. CONDOMÍNIO: NÃO10. PONTO DE REFERÊNCIA: por traz da casa 1470/ colégio manuelito11. DISPONIBILIDADE: manhã 12. OBSERVAÇÃO:
A63: 3844223 | B63: ROBERIO MESQUITA MACHADO | C63: Encerramento | D63: DNET - INSTALAÇÃO FIBRA - PF | E63: Rua | F63: Rua Habitar Brasil | G63: 13 | H63: Itaitinga | I63: Riachão | J63: -4001427 | K63: -38517938 | L63: CAIO VICTOR MONTEIRO DE OLIVEIRA | M63: ANA GABRIELLY ALVES MENEZES | N63: 46262 | O63: 46265 | P63: 46267 | Q63: 46267 | R63: Sim | S63: 2 | T63: DNET - Cliente Pessoa Física | U63: DNET - Instalação | X63: Troca Conector - Desgastado | AA63: OLT DNET TEMPORARIO | AB63: Abertura Solicitação para visita técnica no cliente, a pedido do mesmo.TÉCNICO : CAIO VICTOR CLIENTE : ROBERIO MESQUITA MACHADOENDEREÇO CORRETO: Rua Habitar Brasil, 13, Riachão - Itaitingahttps://maps.app.goo.gl/29Vbh7Y4jM5Q4Nko9Nº CAIXA: 11757N º PORTA: 6VERIFICAÇÃO DE CX: SSINAL DA CTO: -23SINAL DO CLIENTE: -23MATERIAL UTILIZADO*CONECTOR VERDE: CONECTOR AZUL: FIXA FIO: CANALETA: ESTICADOR: ADESIVO CONECTOR: RJ45: CABO DE REDE: EQUIPAMENTO UTILIZADO ONT (S/N) = 01 ont TP-Link ONU (S/N) = ROTEADOR (S/N) = DROP CABO INICIAL: DROP CABO FINAL: DROP METRAGEM: TEVE FATURAMENTO? VALOR (SE HOUVER) :SERVIÇO:Dispositivo: motorola moto g04sVersão do Android: 14Versão do V·Tasks: 5.9.211 Status alterado de Remarcação para Encerramento | AC63: VENDEDOR: GABRIELLY MENEZESÁREA: PAP () CALL-CENTER ( ) LOJA ( ) TBR ( )TITULAR: ROBERIO MESQUITA MACHADOTELEFONE:(85) 99803-5793WHATSAPP:(85) 99717-7638DISPONIBILIDADE: MANHA( ) TARDE ( ) DIA TODO (X)DATA: 29/08/2026CIDADE E BAIRRO: Rua Habitar Brasil, N13 - Riachão Itaitingahttps://maps.app.goo.gl/iRHt1QCePNKNyyPg6PLANO:🔹 200 MB – R$ 89,99 (R$ 79,99 até o vencimento)VALOR ORIGINAL DO PLANO: 89,99POSSUI DESCONTO DE PONTUALIDADE? SIM (x ) NÃO ( )SE SIM: D5 ( ) ou DNET - D10( x)DESCONTO DE __10 , SE PAGO ATÉ O VENCIMENTO POR 12 MESESTAXA INSTALAÇÃO: GRATISATENDIMENTO REGISTRADO:Google Drive ( ) Fortics ( ) Smart (X )FIDELIDADE: (X ) SIM NÃO ( )CLIENTE DESEJA NOTA FISCAL: SIM ( ) NÃO (X )COORD:-4.000934858207081, -38.51814643634048CAIXA:CX 11757 CASA DUPLEX ( ) CASA TERREA (X)QUANTOS E QUAIS APARELHOS CONECTADOS: CELULAR, TVOBSERVAÇÃO ADICIONAL:Ativação do contrato: 174145---- Endereço de Instalação ----CEP: 61882-503Logradouro: Rua Habitar BrasilNúmero: 13Bairro: RiachãoEstado: CECidade: ItaitingaComplemento: próximo a igreja católica---- Serviços a serem ativados ----- 0824 - DNET - 200MB
A64: 3844291 | B64: PEDRO ALMEIDA LOBO JUNIOR | C64: Encerramento | D64: DNET - PENDÊNCIA FIBRA - COND. | E64: Rua | F64: Rua João Campos Filho | G64: 167 | H64: Maracanaú | I64: Parque Tijuca | J64: -38454058 | K64: -386266417 | L64: CARLOS HENRIQUE LINO SILVA | M64: DIEGO DE SOUSA SILVA | N64: 46262 | O64: 46263 | P64: 46266 | Q64: 46266 | R64: Sim | S64: 3 | T64: DNET - Cliente Condomínio | U64: DNET - Pendência | V64: DNET - LOS | W64: DNET - Fibra Sem Sinal / Luz Los Vermelha | X64: Troca Conector - Desgastado | AA64: OLT DNET TEMPORARIO | AB64: Abertura Solicitação para visita técnica no cliente, a pedido do mesmo.NORMALIZADO APÓS MANUTENÇÃO DA INFRAESTRUTURA. Dispositivo: samsung SM-A055MVersão do Android: 14Versão do V·Tasks: 5.9.211 Status alterado de Andamento para Encerramento | AC64: 28/08/2026 - 15:57 01. RELATO DO CLIENTE: cliente informa esta sem conexão, piscando vermelho no aparelho LOS02. ANÁLISE SISTEMA (UNM): offline03. ANÁLISE SISTEMA (VOALLE): offline04. EXTRATO COM QUEDAS: NÃO05. GERENCIAMENTO REM. HABILITADO: sem acesso06. PROCEDIMENTO REALIZADO: reboot07. POTÊNCIA: não localizado08. CAIXA E PORTA: não localizado08. CONTATO:(85) 98940-353309. ENDEREÇO COMPLETO:Rua João Campos Filho 167, Parque Tijuca - Maracanaú, CE10. CONDOMÍNIO: SIM10. PONTO DE REFERÊNCIA: Residencial Virgílio tavora 211. DISPONIBILIDADE: o dia todo12. OBSERVAÇÃO: Bloco 6 apartamento 101 é condomínio
A65: 3844310 | B65: VINICIUS HENRIQUE MOREIRA DE CASTRO | C65: Encerramento | D65: PENDÊNCIA FIBRA - PF | E65: Rua | F65: R. Maj. José Câmara | G65: 11 | H65: Aquiraz | I65: Centro | J65: -39047435 | K65: -383878138 | L65: HALLEF GUILHERME LIMA CLEMENTE SILVA | M65: FLAVIA CRISTINA DE SOUZA SILVA BATISTA | N65: 46262 | O65: 46263 | P65: 46268 | Q65: 46268 | R65: Sim | S65: 5 | T65: Cliente Pessoa Física | U65: Pendência | V65: LOS | W65: Fibra Sem Sinal / Luz Los Vermelha | X65: Troca Conector - Desgastado | AA65: OLT Aquiraz VLAN 12 | AB65: *PENDÊNCIA**Data:* 03/09/2026*ATENDENTE:**Técnico:* Hallef / Ismael *CLIENTE* VINICIUS HENRIQUE MOREIRA DE CASTRO*ENDEREÇO* R. Maj. José Câmara, 11, Centro - Aquirazhttps://maps.app.goo.gl/ZJK6KboVuf9Eotnc8Loja NewSmart Aquiraz *Caixa:* 7863*Porta:* 6*Potência da Caixa:* -20*Potência do Cliente:*-20 *Serviço*Link loss Realizado troca de drop Conexão normalizada *Materiais* *conector azul:* *conector verde:* 2und*Fixa fio* 5und *adesivo**canaleta**RJ 45**EQUIPAMENTOS**ONT*: *ROTEADOR* *ONU**DROP**Início* 615*Fim* 530*Utilizado*85m*EQUIPAMENTO RECOLHIDO**Valor:**Obs.:*Dispositivo: motorola moto g04sVersão do Android: 14Versão do V·Tasks: 5.9.211 Status alterado de Reagendado para Encerramento | AC65: 28/08/2026 - 15:52 01. RELATO DO CLIENTE: cliente relata que esta sem conexao Fibra Sem Sinal / Luz Los Vermelha02. ANÁLISE SISTEMA (UNM): link loss03. ANÁLISE SISTEMA (VOALLE): off04. EXTRATO COM QUEDAS: NÃO 05. GERENCIAMENTO REM. HABILITADO: NÃO 06. PROCEDIMENTO REALIZADO: reboot07. POTÊNCIA: x08. CAIXA E PORTA: 7863-0708. CONTATO: 558599205745609. ENDEREÇO COMPLETO: R. Maj. José Câmara, 11 - Centro - Aquiraz - CE - CEP 6170000010. CONDOMÍNIO: NÃO 10. PONTO DE REFERÊNCIA: Em frente ao Freitas supermercado11. DISPONIBILIDADE: integral12. OBSERVAÇÃO:caminhão passou e quebrou o fio
A66: 3844313 | B66: THALITA LAREN RIBEIRO DE QUEIROZ | C66: Encerramento | D66: DNET - INSTALAÇÃO FIBRA - PF | E66: Rua | F66: RUA FRANCISCA MARTINS | G66: 4 | H66: Eusébio | I66: Santo Antônio | J66: -38939274 | K66: -384977493 | L66: ELISSON PEREIRA COUTINHO NOVAIS | M66: ANA GABRIELLY ALVES MENEZES | N66: 46262 | O66: 46265 | P66: 46267 | Q66: 46267 | R66: Sim | S66: 2 | T66: DNET - Cliente Pessoa Física | U66: DNET - Instalação | X66: Troca Conector - Desgastado | AA66: OLT DNET TEMPORARIO | AB66: 🛠 INSTALAÇÃO 🧰DATA: 02/09/2026TÉCNICO: ELISSONCLIENTE:THALITA LAREN RIBEIRO DE QUEIROZENDEREÇO:RUA FRANCISCA MARTINS , 04, Santo Antônio - EusébioCTO: PORTA: 🔦 POTÊNCIA: CTO (-23) CASA( -24) 📃 RELATO: instalação realizada com sucesso, feito todos os testes 🧰 MATERIAL UlTILIZADO:CONECTOR AZUL: ( 1)CONECTOR VERDE: ( 1)FIXA FIO: (5)TUBETE: ( )ADESIVO: ( )CANALETA : ()RJ 45: ( )ESTICADOR: ( )Inicial Final DROP: (69)ONT: 896D💸 VALOR: 🚨 OBS:CLASSIFICAÇÃO DE ENCERRAMENTO: INSTALAÇÃO REALIZADA ✅️Dispositivo: samsung SM-A065MVersão do Android: 16Versão do V·Tasks: 5.9.211 Status alterado de Reagendado para Encerramento | AC66: VENDEDOR: GABRIELLY MENEZESÁREA: PAP () CALL-CENTER ( ) LOJA ( ) TBR ( )TITULAR: THALITA LAREN RIBEIRO DE QUEIROZTELEFONE:(85) 9889-68124WHATSAPP:(85) 9878-57569DISPONIBILIDADE: MANHA( ) TARDE ( ) DIA TODO (X)DATA:29/08/2026CIDADE E BAIRRO: Rua Augusto Benvindo, 50 Santo AntônioPLANO:🔹 400 MB – R$ 109,99 (R$ 99,99 até o vencimento)VALOR ORIGINAL DO PLANO: 109,99POSSUI DESCONTO DE PONTUALIDADE? SIM (X ) NÃO ( )SE SIM: D5 ( ) ou DNET - D10( X)DESCONTO DE _10_ , SE PAGO ATÉ O VENCIMENTO POR 12 MESESTAXA INSTALAÇÃO: GRATISATENDIMENTO REGISTRADO:Google Drive ( ) Fortics ( ) Smart (X )FIDELIDADE: (X ) SIM NÃO ( )CLIENTE DESEJA NOTA FISCAL: SIM ( ) NÃO ( X)COORD:-3.8938043032073826, -38.49774393558217CAIXA:CX 11037CASA DUPLEX ( ) CASA TERREA (X)QUANTOS E QUAIS APARELHOS CONECTADOS:celulares, TVsOBSERVAÇÃO ADICIONAL:Ativação do contrato: 174148---- Endereço de Instalação ----CEP: 61767-860Logradouro: Rua Augusto BenvindoNúmero: 50Bairro: Santo AntônioEstado: CECidade: Eusébio---- Serviços a serem ativados ----- 0824 - DNET - 400MB
A67: 3844328 | B67: ANTONIO MARCOS BEZERRA | C67: Encerramento | D67: PENDÊNCIA FIBRA - PF | E67: Rua | F67: Rua Zenaide Magalhães | G67: 120 | H67: Fortaleza | I67: Barra do Ceará | L67: ELIZEU DA SILVA FERREIRA | M67: JACKELINE RODRIGUES COSTA | N67: 46262 | O67: 46263 | P67: 46268 | Q67: 46268 | R67: Sim | S67: 5 | T67: Cliente Pessoa Física | U67: Pendência | V67: LOS | W67: Fibra Sem Sinal / Luz Los Vermelha | X67: Troca Conector - Desgastado | AA67: OLT Barra do Ceará VLAN 1001 | AB67: *PENDÊNCIA**Data* 03/09/2026*Técnico* ELIZEU DA SILVA FERREIRA CLIENTE: ANTONIO MARCOS BEZERRAENDEREÇO: Rua Zenaide Magalhães, 120 , Barra do Ceará - Fortaleza*Caixa*:*Porta*:*SINAL DA CAIXA*.*SINAL DO CLIENTE*.-SERVIÇO REALIZADO Troca de conector desgastado *Material utilizado*01Conector Verde00Conector Azul00 Fixa fio00 Canaleta00Esticador00Adesivo conector00 RJ4500 pat Cord00 ONT ZTE00 Repetidor Mercuses00 ont intelbras fiberhome*OBS* : Internet ok cliente.Login:Senha:*VALOR* :*Cabo inicial*:*Cabo final* *Metragem* *Drop inicial*:0000*Drop final* : 0000*Metragem*:0000Dispositivo: samsung SM-A065MVersão do Android: 16Versão do V·Tasks: 5.9.211 Status alterado de Remarcação para Encerramento | AC67: 28/08/2026 - 15:58 01. RELATO DO CLIENTE: cliente sem conexão, piscando vermelho no equipamento 02. ANÁLISE SISTEMA (UNM): LINK LOSS03. ANÁLISE SISTEMA (VOALLE): OFFLINE04. EXTRATO COM QUEDAS: NÃO 05. GERENCIAMENTO REM. HABILITADO: SIM ou NÃO (VERIFICAR E HABILITAR)06. PROCEDIMENTO REALIZADO: FEITO O REBOOT E SEM SUCESSO07. POTÊNCIA: XX08. CAIXA E PORTA: 2578 / 0808. CONTATO: (85)99420-681909. ENDEREÇO COMPLETO: Rua Zenaide Magalhães 120 , Barra do Ceará - Fortaleza, CE10. CONDOMÍNIO: NÃO 10. PONTO DE REFERÊNCIA: mercearia mãe rainha11. DISPONIBILIDADE: entrar em contato 12. OBSERVAÇÃO:
A68: 3844330 | B68: LUANA MARA BRITO CAVALCANTE | C68: Encerramento | D68: DNET - PENDÊNCIA FIBRA - COND. | E68: Rua | F68: Rua G | G68: 255 | H68: Fortaleza | I68: Paupina | J68: -38520453 | K68: -384896686 | L68: CARLOS HENRIQUE LINO SILVA | M68: ITALO NERY FORTE | N68: 46262 | O68: 46263 | P68: 46266 | Q68: 46266 | R68: Sim | S68: 3 | T68: DNET - Cliente Condomínio | U68: DNET - Pendência | V68: DNET - Potência Baixa | W68: DNET - Correção de Potência | X68: Troca Conector - Desgastado | AA68: OLT DNET TEMPORARIO | AB68: Abertura Solicitação para visita técnica no cliente, a pedido do mesmo.☑️☑️ *PENDÊNCIA* ☑️☑️*Chegada**Saída**Data* 01.09.2026*SUPORTE**COMERCIAL* *Técnico* CARLOS HENRIQUE*AUXILIAR:* MARLYSON *CLIENTE:* LUANA MARA BRITO CAVALCANTE*ENDEREÇO* Rua G, 255, Paupina - Fortaleza*obs sobre o endereço* *CONTATO* *Caixa* *PORTA* *SINAL DA CAIXA**SINAL DO CLIENTE**Velocidade* *Material utilizado* Conector Verde Conector Azul Fixa fixo canaleta0 Esticadoadesivo 0 Per CordRJ45 TUBETEPROBLEMA RELATADO: UPGRADE COM TROCA DE EQUIPAMENTO *OBS* CLIENTE INFORMOU QUE A CONEXÃO JA TERIA NORMALIZADO, SEM A NECESSIDADE DA VISITA TÉCNICA. *VALOR:* Cabo de redeInicial Final Metragem*SENHA DO EQUIPAMENTO* *Equipamento anterior* *ONT* *ONU* *ROTEADOR:* *Equipamento Atual* *ONT* *ONU* *ROTEADOR* *Drop inicial* *Drop Final* *Metragem:* *OBS:* *Classificação de Encerramento*RESOLVIDO✅Dispositivo: samsung SM-A055MVersão do Android: 14Versão do V·Tasks: 5.9.211 Status alterado de Andamento para Encerramento | AC68: 28/08/2026 - 16:15 01. RELATO DO CLIENTE: cliente informa internet muito lenta e caindo constantemente02. ANÁLISE SISTEMA (UNM): on line03. ANÁLISE SISTEMA (VOALLE): on line04. EXTRATO COM QUEDAS: SIM 05. GERENCIAMENTO REM. HABILITADO: SIM 06. PROCEDIMENTO REALIZADO: abertura de visita07. POTÊNCIA: -28.8608. CAIXA E PORTA: xxx08. CONTATO: 8599699518709. ENDEREÇO COMPLETO: Rua G 255, Paupina - Fortaleza, CE60873-57510. CONDOMÍNIO: SIM 10. PONTO DE REFERÊNCIA: -3.8519864208314214, -38.48964714679695511. DISPONIBILIDADE: sábado a partir das 10h e domingo o dia todo12. OBSERVAÇÃO: residenciais dos escritores bloco 12 ap 102
A69: 3844351 | B69: TARCISIO LEÃO LIMA | C69: Encerramento | D69: PENDÊNCIA FIBRA - PF | E69: Rua | F69: Rua 72 | G69: 895 | H69: Pacatuba | I69: Senador Carlos Jereissati | J69: -3889009 | K69: -38612577 | L69: ANTONIO RAFAEL ALEXANDRE DE SOUSA | M69: THIAGO PEREIRA LOPES | N69: 46262 | O69: 46263 | P69: 46266 | Q69: 46266 | R69: Sim | S69: 3 | T69: Cliente Pessoa Física | U69: Pendência | V69: LOS | W69: Fibra Sem Sinal / Luz Los Vermelha | X69: Troca Conector - Desgastado | AA69: OLT Pacatuba VLAN 1003 | AB69: PENDÊNCIAData: 01/09/2026Técnico: Rafael SousaCliente: Tarcisio Leão LimaEndereço: Rua 72, 895, Senador Carlos Jereissati – PacatubaDescrição:Cliente informou, por áudio via WhatsApp, que necessitava apenas da senha do Wi-Fi, pois havia perdido a senha. Como o cliente não estava no local, as meninas da loja realizaram o atendimento remotamente e repassaram a senha ao cliente.Status: Serviço concluído.Dispositivo: samsung SM-A146MVersão do Android: 15Versão do V·Tasks: 5.9.211 Status alterado de Andamento para Encerramento | AC69: 28/08/2026 - 16:03 01. RELATO DO CLIENTE: CLIENTE INSTALADO NO DIA 27/08 RELATOU QUE POUCO TEMPO DEPOIS QUE O TECNICO INSTALOU, FICOU SEM CONEXÃO TOTAL.08. CONTATO: (85)99266049009. ENDEREÇO COMPLETO: RUA 72, Nº 895 CASA A10. CONDOMÍNIO: NÃO 11. DISPONIBILIDADE: O DIA TODO12. OBSERVAÇÃO: LIGAR P/ O CLIENTE ANTES DE IR ATE A RESIDENCIA.
A70: 3844358 | B70: ANA ISABELY FREIRE DA SILVA | C70: Encerramento | D70: INSTALAÇÃO FIBRA - PF | E70: Avenida | F70: Avenida Antônio Lopes da Silva | G70: 7520 | H70: Aracoiaba | I70: Centro | J70: -43657029 | K70: -388098777 | L70: LUCIEUDO BANDEIRA ALVES FILHO | M70: FRANCISCO ANDERSON DA SILVA MORAIS | N70: 46262 | O70: 46265 | P70: 46267 | Q70: 46267 | R70: Sim | S70: 2 | T70: Cliente Pessoa Física | U70: Instalação | X70: Troca Conector - Desgastado | AA70: OLT Aracoiaba VLAN 2126 | AB70: 🛠 *INSTALAÇÃO* 🧰*Data:* 02/09/2026*Técnico:* LUCIEUDO BANDEIRA *Cliente* ANA ISABELY FREIRE DA SILVA*Endereço:* Av Antônio Lopes Da Silva, 00, Centro - Aracoiaba*Potência:* -20*Caixa:* 6398*porta*: 05*MATERIAL USADO* 01 Intelbras wifi601apc 01 canaleta 05fixa fio *inicial:* *Final:* *Metragem:* *Serviço Realizado:* INSTALAÇÃO concluída cabo puxado *Classificação de Encerramento:* Instalação ConcluídaDispositivo: motorola moto g04Versão do Android: 14Versão do V·Tasks: 5.9.213 Status alterado de Reagendado para Encerramento | AC70: VENDEDOR: FRANCISCO ANDERSON DA SILVA MORAIS ÁREA: PAP (X) CALL-CENTER ( ) LOJA ( ) TBR ( )TITULAR: NOMEANA ISABELY FREIRE DA SILVATELEFONE: ‪+55 85 99737‑5049‬WHATSAPP: ‪+55 85 99737‑5049‬DISPONIBILIDADE: MANHA( ) TARDE ( ) DIA TODO (x)DATA:CIDADE E BAIRRO: Aracoiaba- parque centenário PLANO: 200mbVALOR ORIGINAL DO PLANO: 79,99POSSUI DESCONTO DE PONTUALIDADE? SIM ( ) NÃO (x )SE SIM: D5 ( ) ou DNET - D10( )DESCONTO DE __ , SE PAGO ATÉ O VENCIMENTO POR 12 MESESTAXA INSTALAÇÃO: 0ATENDIMENTO REGISTRADO:Google Drive (x ) Fortics ( ) Smart ( )FIDELIDADE: ( x) SIM NÃO ( )CLIENTE DESEJA NOTA FISCAL: SIM ( ) NÃO ( )COORD: -4.365578148367256, -38.80992577558356 CAIXA: cx6398CASA DUPLEX (c ) CASA TERREA ()QUANTOS E QUAIS APARELHOS CONECTADOS: 3 celulares OBSERVAÇÃO ADICIONAL:Ativação do contrato: 174150---- Endereço de Instalação ----CEP: 62750-000Logradouro: Av Antônio Lopes Da SilvaNúmero: 00Bairro: CentroEstado: CECidade: Aracoiaba---- Serviços a serem ativados ----- 0722 - IFT - ULTRAINFO - 200MB
A71: 3844383 | B71: MARIA CLENILANE RODRIGUES MOURA | C71: Encerramento | D71: TRANSFERÊNCIA - PF | E71: Avenida | F71: Av. Cel. Cícero de Sá | G71: 1451 | H71: Eusébio | I71: Centro | J71: -3.9019423e+15 | K71: -3.8452481e+15 | L71: MAISSON FERREIRA DA SILVA | M71: JACKELINE RODRIGUES COSTA | N71: 46262 | O71: 46265 | P71: 46266 | Q71: 46266 | R71: Sim | S71: 1 | T71: Cliente Pessoa Física | U71: Transferência | V71: Equipamento no Novo Endereço | W71: Taxa Faturada | X71: Troca Conector - Desgastado | AA71: OLT Eusébio 1 VLAN 9 | AB71: 🧰🪜 */ MANUTENÇÃO /* 🧰🪜📱 *Data:* 01/SETEMBRO/26 🗓️ terça-feira *Atendente / Ativação* Gestão *Técnico:*👷🏻‍♂️ _Maisson👴🏽_/ Pedro Maia *Cliente 🚻* MARIA CLENILANE RODRIGUES MOURA*Endereço 📪* Av. Cel. Cícero de Sá, 1451, Centro - Eusébio*Potência / caixa:* 21*Potência / cliente:* 21*Caixa:* 1846*Porta:* 01*Descrição 👀* transferência realizada. Feito verificação de caixa pra liberar uma vaga pro cliente *Valor* 75$ em 3x *Mac Login* multipro 1 *Canaleta*5 *Fixa fio*2 *Conector verde* 🟢0 *Conector azul* 🔵0 *Adesivo* 🏷️0 *RJ45*0 *ONT / ROTEADOR AC* *Drop inicial:* *Drop final:* *Drop usado:* *Cabo de Rede:* *Obs:* cabo infolink na residência *Classificação* _Resolvido 🥱_Dispositivo: samsung SM-A055MVersão do Android: 15Versão do V·Tasks: 5.9.211 Status alterado de Andamento para Encerramento | AC71: 28/08/2026 - 17:55 PERGUNTA PRE-REQUISITO PARA ABERTURA:-CLIENTE JA SE MUDOU? SIMTEM ENERGIA ELETRICA NO LOCAL? SIM- É CONDOMINIO ? SIM ( ) NÃO (X )SE A RESPOSTA FOR NÃO PARA QUALQUER UMA DAS PERGUNTAS, A SOLICITAÇÃO NÃO PODE SER ABERTA.01. FONE 01: 8599810730702. FONE 02: 8899662805603. WHATSAPP: 85998107307 / 8899662805604. NOVO ENDEREÇO:* RUA: Av. Cel. Cícero de Sá* Nº: 1451* BAIRRO: Centro* CIDADE: Eusébio - CE, 61760-000* PONTO DE REFERÊNCIA DO ENDEREÇO NOVO: Bar do Cláudio05. CAIXA: 6771 / 184606. COORDENADAS: -3.9018513008857933, -38.4524269051073507. DISPONIBILIDADE PARA RECEBER A EQUIPE: disponibilidade para receber o técnico somente na terça-feira ( entrar em contato bem antes)09. DEIXAR O CLIENTE CIENTE QUE OS EQUIPAMENTOS PRECISAM ESTAR NO NOVO ENDEREÇO.10. VALOR ? 75 3x11. ANTIGO ENDEREÇO:* RUA: Av. Brasília* Nº: 279* BAIRRO: Centro* CIDADE:Eusébio - CE 11. PRAZO: 72 HORAS UTEIS.OBS:
A72: 3844392 | B72: MANUEL ANDERLINO DA SILVA | C72: Encerramento | D72: DNET - PENDÊNCIA FIBRA - COND. | E72: Rua | F72: RUA G | G72: 255 | H72: Fortaleza | I72: PAUPINA MESSEJANA | L72: CARLOS HENRIQUE LINO SILVA | M72: FRANCISCA ALICE MESQUITA FERREIRA | N72: 46262 | O72: 46263 | P72: 46266 | Q72: 46266 | R72: Sim | S72: 3 | T72: DNET - Cliente Condomínio | U72: DNET - Pendência | V72: DNET - LOS | W72: DNET - Fibra Sem Sinal / Luz Los Vermelha | X72: Troca Conector - Desgastado | AA72: OLT DNET TEMPORARIO | AB72: Abertura Solicitação para visita técnica no cliente, a pedido do mesmo.CLIENTE NORMALIZOU APÓS MANUTENÇÃO DA INFRAESTRUTURA Dispositivo: samsung SM-A055MVersão do Android: 14Versão do V·Tasks: 5.9.211 Status alterado de Tratamento Infra para Encerramento | AC72: 28/08/2026 - 16:16 01. RELATO DO CLIENTE: ROTEADOR COM LED VERMELHA 02. ANÁLISE SISTEMA (UNM): LOSS03. ANÁLISE SISTEMA (VOALLE): OFFLINE04. EXTRATO COM QUEDAS: NÃO 05. GERENCIAMENTO REM. HABILITADO: SIM06. PROCEDIMENTO REALIZADO: REBOOT DA TOMADA07. POTÊNCIA: NÃO LOCALIZADO UNM08. CAIXA E PORTA: NÃO LOCALIZADO UNM08. CONTATO: 8599719552109. ENDEREÇO COMPLETO: RUA G 255, PAUPINA MESSEJANA - Fortaleza, CE60873-57510. CONDOMÍNIO: SIM10. PONTO DE REFERÊNCIA: CONDOMINIO MACHADO DE ASSIS, BLOCO 33 AP 10111. DISPONIBILIDADE: O DIA TODO 12. OBSERVAÇÃO: LIGAR ANTES DE IR
A73: 3844447 | B73: ELLEN FORTE PAIVA | C73: Encerramento | D73: INSTALAÇÃO FIBRA - COND. | E73: Via | F73: Via local E13 | G73: sn | H73: Aquiraz | I73: Patacas | J73: -39829236 | K73: -383282285 | L73: BRENDHOWN CESAR VIANA SILVA FALCAO | M73: MARIA LEIDIVANIA DA SILVA RAMOS | N73: 46262 | O73: 46265 | P73: 46272 | Q73: 46269 | R73: Sim | S73: 7 | T73: Cliente Condomínio | U73: Instalação | X73: Troca Conector - Desgastado | AA73: OLT Tapera VLAN 1009 | AB73: INVIABILIDADE LOCAL: TUBULAÇÃO DA CASA DO CLIENTE OBSTRUIDA ||Ao chegar no local, não tinha tubulação do mini poste até a residência do cliente. Cliente informou que iria falar com a construtora, para ver essa situação. Cliente vai entrar em contato. | AC73: 28/08/2026 - 16:45 VENDEDOR: LEIDIVANIAÁREA: PAP () CALL-CENTER ( ) LOJA ( ) TBR ( X)TITULAR: ELLEN FORTE PAIVATELEFONE: 85 99152-7569WHATSAPP: 85 99745-2943DISPONIBILIDADE: MANHA(X ) TARDE ( ) DIA TODO ()DATA: 01.09.2026CIDADE E BAIRRO: SMART CITY - PATACASPLANO: 500mbVALOR ORIGINAL DO PLANO: 99,99POSSUI DESCONTO DE PONTUALIDADE? SIM ( ) NÃO (x )SE SIM: D5 ( ) ou DNET - D10( )DESCONTO DE __ , SE PAGO ATÉ O VENCIMENTO POR 12 MESESTAXA INSTALAÇÃO: 75 em 3 vezesATENDIMENTO REGISTRADO:Google Drive ( ) Fortics ( ) Smart (x )FIDELIDADE: (x ) SIM NÃO ( )CLIENTE DESEJA NOTA FISCAL: SIM ( ) NÃO x( )COORD: -3.9834085497779568, -38.32695292756067CAIXA: cx 8272CASA DUPLEX ( ) CASA TERREA (x)QUANTOS E QUAIS APARELHOS CONECTADOS:TV ´CELULAR , COMPUTADOROBSERVAÇÃO ADICIONAL:
A74: 3844470 | B74: MARIA DA CONCEIÇÃO DA SILVA BATISTA | C74: Encerramento | D74: INSTALAÇÃO FIBRA - PF | E74: Avenida | F74: Avenida Marginal Nordeste | G74: 481 | H74: Pacatuba | I74: Senador Carlos Jereissati | J74: -38914529 | K74: -386074775 | L74: FRANCISCO DIEGO ALVES FERREIRA | M74: FRANCISCO CHARLES GADELHA ARAUJO | N74: 46262 | O74: 46265 | P74: 46267 | Q74: 46267 | R74: Sim | S74: 2 | T74: Cliente Pessoa Física | U74: Instalação | X74: Troca Conector - Desgastado | AA74: OLT Pacatuba VLAN 1003 | AB74: 🛠 *INSTALAÇÃO* 🧰*Data:* 01/09/2026*Técnico:*Francisco Diego *Cliente:* MARIA DA CONCEIÇÃO DA SILVA BATISTA*Endereço:* Avenida Marginal Nordeste, 481, Senador Carlos Jereissati - Pacatuba*Potência:* - 23*Caixa:* 3119*porta*: 05*MATERIAL USADO* Conector verde: 2 undConector azul Adesivo Fixa fio: 05 Canaleta: EQUIPAMENTOS * intelbras 01* Roteador * ONU*inicial:* 84*Final:* 00*Metragem:* 84*Serviço Realizado:* Instalação Feito os testes com o cliente tudo funcionado corretamente. *OBS*: , APARELHO INTALADO ONDE CLIENTE SOLICITOU *Classificação de Encerramento:* Instalação ConcluídaDispositivo: samsung SM-A346MVersão do Android: 16Versão do V·Tasks: 5.9.211 Status alterado de Reagendado para Encerramento | AC74: VENDEDOR: FRANCISCO CHARLLES GADELHA ARAÚJO ÁREA: PAP (x) CALL-CENTER ( ) LOJA ( ) TBR ( )TITULAR: MARIA DA CONCEIÇÃO DA SILVA BATISTA TELEFONE: 85991325694WHATSAPP: 85991325694DISPONIBILIDADE: MANHA( ) TARDE ( ) DIA TODO (x)DATA:CIDADE E BAIRRO: Jereissati III/Maracanaú PLANO: 500MB VALOR ORIGINAL DO PLANO: 99,99POSSUI DESCONTO DE PONTUALIDADE? SIM (x ) NÃO ( )SE SIM: D5 ( ) ou DNET - D10( )DESCONTO DE19,99 __ , SE PAGO ATÉ O VENCIMENTO POR 12 MESESTAXA INSTALAÇÃO: 00,00 ATENDIMENTO REGISTRADO:Google Drive ( ) Fortics ( ) Smart ( )FIDELIDADE: (x ) SIM NÃO ( )CLIENTE DESEJA NOTA FISCAL: SIM ( ) NÃO ( )COORD: -3.891543,-38.607506 CAIXA: 3119CASA DUPLEX (x ) CASA TERREA ()QUANTOS E QUAIS APARELHOS CONECTADOS: 04 celulares 01tv OBSERVAÇÃO ADICIONAL:Ativação do contrato: 174160---- Endereço de Instalação ----CEP: 61814-048Logradouro: Avenida Marginal NordesteNúmero: 481Bairro: Senador Carlos JereissatiEstado: CECidade: PacatubaComplemento: casa (altos)Referência: próximo a padaria mr---- Serviços a serem ativados ----- 0422 - ULTRAINFO - 500MB
A75: 3844516 | B75: FRANCISCO PEDRO HENRIQUE DE ARAUJO BESSA | C75: Encerramento | D75: PENDÊNCIA FIBRA - COND. | E75: Rua | F75: Rua 5 | G75: 76 | H75: Eusébio | I75: Parque Havai | L75: ANTONIO FELIPE CASTRO DE OLIVEIRA | M75: FRANCISCA ALICE MESQUITA FERREIRA | N75: 46262 | O75: 46263 | P75: 46266 | Q75: 46266 | R75: Sim | S75: 3 | T75: Cliente Condomínio | U75: Pendência | V75: LOS | W75: Fibra Sem Sinal / Luz Los Vermelha | X75: Troca Conector - Desgastado | AA75: OLT Eusébio 1 VLAN 9 | AB75: ☑️☑️ *PENDENCIA/COND* ☑️☑️*Chegada**Saída**Data* 01.09.2026*SUPORTE**COMERCIAL* *Técnico* Ant.Felipe/Irineto*Cliente* FRANCISCO PEDRO HENRIQUE DE ARAUJO BESSA*Endereço* Avenida Zenóbio Leandro Evangelista, 35, Parque Hawaí - Eusébio*obs sobre o endereço* *LOCALIZAÇÃO*https://maps.app.goo.gl/zDpJGx72oj4KCmUn8?g_st=ic*CONTARO* *Caixa* *PORTA* *SINAL DO CAIXA* *SINAL DO CLIENTE* 23*Velocidade* *Material utilizado*2 Conector Verde 0 Conector Azul0 abraçadeira de nylon0 Fixa fixo 0 canaleta,0 Esticador0 adesivo 0 Per Cord0 RJ45PROBLEMA RELATADO: OBS. Drop rompidoCabo de redeInicial Final Utilizado *SENHA DO EQUIPAMENTO* *Equipamento anterior**Equipamento Atual**MEC* *Drop inicial* *Drop Final**Metragem* 189*Classificação de Encerramento* *RESOLVIDO*✅Dispositivo: iPhoneVersão do iOS: 26.5Versão do V·Tasks: 5.9.211 Status alterado de Reagendado para Encerramento | AC75: 28/08/2026 - 17:36 01. RELATO DO CLIENTE: ROTEADOR COM LED VERMELHA 02. ANÁLISE SISTEMA (UNM): LOSS03. ANÁLISE SISTEMA (VOALLE): OFFLINE04. EXTRATO COM QUEDAS: NÃO 05. GERENCIAMENTO REM. HABILITADO: SIM06. PROCEDIMENTO REALIZADO: REBOOT DA TOMADA07. POTÊNCIA: NÃO LOCALIZADO UNM08. CAIXA E PORTA: CX7690 P-0508. CONTATO: 85988095457 / 8598596279209. ENDEREÇO COMPLETO: Avenida Zenóbio Leandro Evangelista 35, Parque Hawaí - Eusébio, CE61761-68010. CONDOMÍNIO: NÃO 10. PONTO DE REFERÊNCIA: PIZZA DO BESSA11. DISPONIBILIDADE: O DIA TODO 12. OBSERVAÇÃO: LIGAR ANTES DE IR
A76: 3844553 | B76: ANNA CAROLINA LIBERATO MONTEIRO | C76: Encerramento | D76: PENDÊNCIA FIBRA - PF | E76: Rua | F76: R. Beira Rio | G76: 0 | H76: Aquiraz | I76: Iguape | J76: -39450717 | K76: -382896471 | L76: GLEISON VALENTIM ARAUJO | M76: CLEITON CHAGAS PEREIRA | N76: 46262 | O76: 46263 | P76: 46267 | Q76: 46267 | R76: Sim | S76: 4 | T76: Cliente Pessoa Física | U76: Pendência | V76: LOS | W76: Fibra Sem Sinal / Luz Los Vermelha | X76: Troca Conector - Desgastado | AA76: OLT Tapera VLAN 1009 | AB76: *PENDÊNCIA**Equipe:*- Técnico: Gleison Valentim*CLIENTE:* ANNA CAROLINA LIBERATO MONTEIRO*Endereço:* R. Beira Rio, 0, Iguape - Aquiraz*COORDENADAS:* https://maps.app.goo.gl/sB5rUFXmVQ68T5BP8*Potência final:* 17*Caixa:* 3227*Porta:* 03*OBS:* ENEL ESTAVA REALIZANDO UM SERVIÇO DE PODA NO PERCURSO DO DROP,APOS AGUARDAR FINALIZAR O SERVIÇO,FOI ENCONTRADO A ATENUAÇÃO POTENCIA NORMALIZADA. *Equipamentos:*00 - ONT ( )00 - ONU ( )00 - Roteador 2.0 ( )00 - Roteador 3.0 ( )00 - Roteador 4.0 ( )*Materiais*02 - Verde00- azul00 - adesivo. 05 - fixa fio00 - canaleta00 - Esticador00 - Pet Cord*Drop inicial:* *Drop final:* *Drop usado :* 02/09/26Dispositivo: samsung SM-A055MVersão do Android: 15Versão do V·Tasks: 5.9.213 Status alterado de Reagendado para Encerramento | AC76: 28/08/2026 - 18:08 01. RELATO DO CLIENTE: sem internet, led vermelho02. ANÁLISE SISTEMA (UNM): link loss03. ANÁLISE SISTEMA (VOALLE): off line04. EXTRATO COM QUEDAS: sim05. GERENCIAMENTO REM. HABILITADO: habilitar06. PROCEDIMENTO REALIZADO: reiniciado o roteador.07. POTÊNCIA: x08. CAIXA E PORTA: CX3227 P-1408. CONTATO:(85) 99617-360709. ENDEREÇO COMPLETO: R. Beira Rio, 0 - Iguape - Aquiraz - CE - CEP 6170000010. CONDOMÍNIO: NÃO10. PONTO DE REFERÊNCIA: Por trás do posto de saúde11. DISPONIBILIDADE: Disponibilidade integral12. OBSERVAÇÃO:
A77: 3844556 | B77: JUCIMAR CRISTOVAO CARVALHO | C77: Encerramento | D77: PENDÊNCIA FIBRA - PF | E77: Rua | F77: Rua Dona Chagas Nogueira | G77: 33 | H77: Itaitinga | I77: Pedras | J77: -3.8896992e+16 | K77: -3.8509268e+15 | L77: DANILO OLIVEIRA DE SOUSA | M77: ALLYSTER MARQUES OLIVEIRA COSTA | N77: 46262 | O77: 46263 | P77: 46269 | Q77: 46269 | R77: Sim | S77: 6 | T77: Cliente Pessoa Física | U77: Pendência | V77: LOS | W77: Fibra Sem Sinal / Luz Los Vermelha | X77: Troca Conector - Desgastado | AA77: OLT Jabuti VLAN 1000 | AB77: ♦️ *prdencia* ♦️*Chegada:* *Saída:* *Data:* 03/09/26*Atendente Responsável:* *Técnico:* Danilo*Cliente* JUCIMAR CRISTOVAO CARVALHO*Endereço* Rua dona Chagas Nogueira *Potência da caixa:* - *Potência do cliente:*-25*Caixa* *Porta**Serviço Realizado**Material Utilizado* equipamentos desautenticado *Valor* *Obs* *Drop inicial* *Drop final:* *Metragem Total:* *Cabo de rede:* *Classificação de Encerramento:* ResolvidoDispositivo: motorola moto g04sVersão do Android: 14Versão do V·Tasks: 5.9.213 Status alterado de Reagendado para Encerramento | AC77: 28/08/2026 - 18:11 01. RELATO DO CLIENTE: Cliente relata sem internet / offline no voalle / OFFLINE no FiberWatch / piscando VERDE no equipamento02. ANÁLISE SISTEMA (UNM): OFFLINE no FiberWatch03. ANÁLISE SISTEMA (VOALLE): offline no Voalle04. EXTRATO COM QUEDAS: XX05. GERENCIAMENTO REM. HABILITADO: XX06. PROCEDIMENTO REALIZADO: REBOOT DA TOMADA07. POTÊNCIA: XX08. CAIXA E PORTA: CX11785 P-1308. CONTATO: 8599163416809. ENDEREÇO COMPLETO: TRAVESSA JOSE NOGUEIRA 33, PEDRAS - Fortaleza, CE / Lat: -3.8895678 / Long: -38.509236410. CONDOMÍNIO: NÃO10. PONTO DE REFERÊNCIA: A próximo a praça na rua do colégio Tristão de Alencar casarão dúplex do lado esquerdo quinta casa amarelo da rua11. DISPONIBILIDADE: manhã12. OBSERVAÇÃO:
A78: 3844565 | B78: AILA MARIA DE SOUSA PEREIRA | C78: Encerramento | D78: PENDÊNCIA FIBRA - PF | E78: Rua | F78: Rua Felicita | G78: 8 | H78: Itaitinga | I78: Barrocão | J78: -38978345 | K78: -385150716 | L78: FRANCISCO DAS CHAGAS E SILVA ROCHA | M78: FRANCISCA ALICE MESQUITA FERREIRA | N78: 46262 | O78: 46263 | P78: 46266 | Q78: 46266 | R78: Sim | S78: 3 | T78: Cliente Pessoa Física | U78: Pendência | V78: LOS | W78: Fibra Sem Sinal / Luz Los Vermelha | X78: Troca Conector - Desgastado | AA78: OLT Jabuti VLAN 1000 | AB78: *PEND/fibra/COND**Data* 01/9/2026*Horário de saída:* 11:10*Técnico:* Fco.*Cliente:* AILA MARIA DE SOUSA PEREIRA*END:* Rua Felicita, 8, Barrocão - Itaitinga*Potência da caixa:* 22*Potência do cliente:* 23*Caixa:* 11750*Port:* 10*Gerenciamento remoto habilitado?* Sim*Obs:**Log:* *Senha:* *Serviço:*Drop avia sido cortado próximo a cx, local é um condomínio, na descrição call center colocou que não era condomínio.CLIENTE ESTAVA CHATEADA COM A DEMORA. Tive que abrir a cx de passagem soltar a reserva que havia e usar la e refazer o conector na cx.Sinal normalizou em - 23.*Material:*1v.*Recolhido:* *Drop inicial:* *Drop final:* *Total:* *Valor R$:* *Mbs:* *Classificaço:* Encerramento!Dispositivo: samsung SM-A075MVersão do Android: 16Versão do V·Tasks: 5.9.211 Status alterado de Agendado para Encerramento | AC78: 28/08/2026 - 18:20 01. RELATO DO CLIENTE: ROTEADOR COM LED VERMELHA 02. ANÁLISE SISTEMA (UNM): LOSS03. ANÁLISE SISTEMA (VOALLE): OFFLINE04. EXTRATO COM QUEDAS: NÃO 05. GERENCIAMENTO REM. HABILITADO: SIM06. PROCEDIMENTO REALIZADO: REBOOT DA TOMADA07. POTÊNCIA: NÃO LOCALIZADO UNM08. CAIXA E PORTA: CX11750 PORTA N CONSTA NO UNM08. CONTATO: 85989905246 LIGAR PARA FILHA NATALIA09. ENDEREÇO COMPLETO: Rua Felicita 8, Barrocão - Itaitinga, CE61880-00010. CONDOMÍNIO: NÃO 10. PONTO DE REFERÊNCIA: PROXIMO A OFICINA DO IRMÃO11. DISPONIBILIDADE: O DIA TODO12. OBSERVAÇÃO: LIGAR ANTES DE IR
A79: 3844585 | B79: ANTONIO SILVA RODRIGUES | C79: Encerramento | D79: PENDÊNCIA FIBRA - COND. | E79: Avenida | F79: Avenida Nova Assunção | G79: 0 | H79: Eusébio | I79: Santo Antônio | J79: -3.8900723e+15 | K79: -384963572044524 | L79: ALEFF PEREIRA SOARES | M79: ITALO NERY FORTE | N79: 46262 | O79: 46263 | P79: 46266 | Q79: 46266 | R79: Sim | S79: 3 | T79: Cliente Condomínio | U79: Pendência | V79: LOS | W79: Fibra Sem Sinal / Luz Los Vermelha | X79: Troca Conector - Desgastado | AA79: OLT Jabuti VLAN 1000 | AB79: ✅ *PENDENCIA*✅ 01.09.2026*Técnico* Aleff CLIENTE: ANTONIO SILVA RODRIGUESENDEREÇO:Avenida Nova Assunção, 0, Santo Antônio - Eusébio⏹️ *Caixa* 1003 Porta. 01*SINAL DA CAIXA* -23*SINAL DO CLIENTE* -23*DROP COM ETIQUET 🏷️ ☎️ *GESTÃO DE O.S* *ATENDIMENTO:* 📝 *SERVIÇO: Identificado que a fibra estava danificada na caixaFeito a correção potência normalizou Potência normalizou ⚙️ *Material utilizado01 Conector Verde00 Conector Azul00 Fixa fio00 Canaleta00 Esticador00 Adesivo conector 00 RJ4500 patch cord📡 *Equipamento utilizado 00 ZTE (MAC) =00 HG325AX (MAC) = 00 XC220G3 (MAC) =00 MERCUSYS (MAC) =00 ONT INTEL(MAC)=*Equipamento RMA00 ZTE (MAC) =00 HG325AX (MAC) = 00 ONT GLOBAL (MAC) =00 ONT TPL (MAC) =00 ROTEADOR TENDA (MAC) = 00 MERCUSYS (MAC) =00 ONU MINI (MAC) =00 ONU APC (MAC) = 00 ONT INTEL(MAC)=*OBS**VALOR* *Cabo inicial* 00m*Cabo final* 00m*Metragem* 00m*Drop inicial* *Drop final**Metragem**Classificação de Encerramento**RESOLVIDO✅**Status alterado de Reagendado para Encerramento* 😎 🇮🇹Dispositivo: samsung SM-A075MVersão do Android: 16Versão do V·Tasks: 5.9.211 Status alterado de Reagendado para Encerramento | AC79: 28/08/2026 - 19:15 01. RELATO DO CLIENTE: Cliente está sem conexão, luz vermelha piscando no roteador. 02. ANÁLISE SISTEMA (UNM): link los03. ANÁLISE SISTEMA (VOALLE): off line04. EXTRATO COM QUEDAS: NÃO 05. GERENCIAMENTO REM. HABILITADO: NÃO 06. PROCEDIMENTO REALIZADO: abertura de visita07. POTÊNCIA: link los08. CAIXA E PORTA: 1003/02 08. CONTATO: 8598172913509. ENDEREÇO COMPLETO: Avenida Nova Assunção 0, Santo Antônio - Eusébio, CE61768-17010. CONDOMÍNIO: SIM galpão do francine10. PONTO DE REFERÊNCIA: Próximo ao restaurante da tieta 11. DISPONIBILIDADE: após as 15h. domingo pode ir pela manhã, segunda-feira não há ninguém no local12. OBSERVAÇÃO: casa 8
A80: 3844607 | B80: FRANCISCO GILSON BASILIO DA SILVA | C80: Encerramento | D80: INSTALAÇÃO FIBRA - COND. | E80: Avenida | F80: Avenida Abolição | G80: s/n | H80: Redenção | I80: Centro | J80: -42243442 | K80: -387272229 | L80: JOAO PAULO DA SILVA LIMA | M80: NAYLI FILISMINA DE MELO | N80: 46262 | O80: 46266 | P80: 46269 | Q80: 46269 | R80: Sim | S80: 3 | T80: Cliente Condomínio | U80: Instalação Field | X80: Troca Conector - Desgastado | AA80: OLT Acarape VLAN 1040 | AB80: 🌐 *INSTALAÇÃO*🌐*Data:* 04/09/26*Atendente:* *Técnico:* João Paulo silva Cliente : FRANCISCO GILSON BASILIO DA SILVA Endereço: avenida abolição, 0, Centro - Redenção*Potência da Caixa: -25*Potência do cliente-25Cx 1607P 14*Gerenciamento remoto habilitado:* Sim*Serviço Realizado:* Instalação *Material Utilizado:*01 - modem optico HG6145F302- conector verde05-fixa fio01-canaleta *MAC:* *Drop inicial:00*Drop final: 00*Total: 00*Valor:* *Obs:* *Classificação de Encerramento:* Resolvido ✅Dispositivo: samsung SM-A075MVersão do Android: 16Versão do V·Tasks: 5.9.213 Status alterado de Agendado para Encerramento | AC80: VENDEDOR: nayli meloÁREA: PAP () CALL-CENTER (x ) LOJA ( ) TBR ( )TITULAR: FRANCISCO GILSON BASILIO DA SILVATELEFONE: 85991342629 WHATSAPP: 85991342629 DISPONIBILIDADE: MANHA( ) TARDE ( ) DIA TODO (X)DATA:CIDADE E BAIRRO: REDENCAO , CENTROPLANO: 500 MBVALOR ORIGINAL DO PLANO: 99,99POSSUI DESCONTO DE PONTUALIDADE? SIM ( ) NÃO ( X)SE SIM: D5 ( ) ou DNET - D10( )DESCONTO DE __ , SE PAGO ATÉ O VENCIMENTO POR 12 MESESTAXA INSTALAÇÃO: GRATISATENDIMENTO REGISTRADO:Google Drive ( ) Fortics (X ) Smart ( )FIDELIDADE: (X ) SIM NÃO ( )CLIENTE DESEJA NOTA FISCAL: SIM ( ) NÃO (X )COORD:-4.224565488559562, -38.72663787668136CAIXA: cx 7830CASA DUPLEX (X ) CASA TERREA ()QUANTOS E QUAIS APARELHOS CONECTADOS: 2 OBSERVAÇÃO ADICIONAL:Ativação do contrato: 174162---- Endereço de Instalação ----CEP: 62790-000Logradouro: avenida aboliçãoNúmero: 0Bairro: CentroEstado: CECidade: Redenção---- Serviços a serem ativados ----- 0422 - IFT - ULTRAINFO - 500MB
A81: 3844653 | B81: JOSE WILQUER DE ANDRADE | C81: Encerramento | D81: PENDÊNCIA FIBRA - PF | E81: Rua | F81: R. Mal. Deodoro da Fonseca | G81: n | H81: Maracanaú | I81: Parque Tropical | L81: ANTONIO RAFAEL ALEXANDRE DE SOUSA | M81: DIEGO DE SOUSA SILVA | N81: 46262 | O81: 46263 | P81: 46266 | Q81: 46266 | R81: Sim | S81: 3 | T81: Cliente Pessoa Física | U81: Pendência | V81: Teste de Velocidade | W81: Validação de Serviço/Velocidade | X81: Troca Conector - Desgastado | AA81: OLT Pajuçara VLAN 1007 | AB81: PENDÊNCIAData: 01/09/2026Técnico: Rafael SousaCliente: JOSE WILQUER DE ANDRADEEndereço: R. Mal. Deodoro da Fonseca, s/n, Parque Tropical – MaracanaúRelato:Cliente informou que, no domingo, esteve um técnico atendendo seu vizinho, o qual se identificou como prestador de serviço terceirizado da Infolink.Segundo o cliente, o técnico teria informado que o roteador instalado na recidencia do cliente não era compatível com o plano contratado e que o equipamento apresentava problemas.Foi explicado ao cliente que o equipamento instalado era compatível com o plano contratado e que a conexão estava funcionando normalmente, atingindo a velocidade contratada 300megas .Também foram esclarecidas as limitações relacionadas ao Wi-Fi e aos dispositivos conectados à rede.Mesmo após as orientações, o cliente informou que vai solicitar o cancelamento do serviço, pois acreditar que o equipamento apresenta problemas e não e compatível com seu plano, ele solicitou a troca ou cancelava.Para minimizar a insatisfação e evitar a desistência do cliente, foi realizada a substituição do equipamento. Após a troca, não foi identificado nenhum problema na conexão ou no equipamento anterior. A substituição foi realizada exclusivamente para atender à solicitação do cliente e proporcionar maior satisfação.Plano:300megas Atingindo a velocidade contratada normalmente.Potência óptica: -24 dBm.Material utilizado:- 01 UPC- 01 ONT VDSLDispositivo: samsung SM-A146MVersão do Android: 15Versão do V·Tasks: 5.9.211 Status alterado de Reagendado para Encerramento | AC81: 28/08/2026 - 21:11 01. RELATO DO CLIENTE: cliente informa esta com lentidão, feito velocidade de teste, mas não bate com a velocidade do contrato02. ANÁLISE SISTEMA (UNM): online no fiberwatch03. ANÁLISE SISTEMA (VOALLE): online04. EXTRATO COM QUEDAS: NÃO05. GERENCIAMENTO REM. HABILITADO: SIM06. PROCEDIMENTO REALIZADO: configurado teste padrões de lentidão, mais cliente exige uma visita técnica 07. POTÊNCIA: -23.7608. CAIXA E PORTA: cx3464p0108. CONTATO:(85) 98772-568809. ENDEREÇO COMPLETO:R. Mal. Deodoro da Fonseca n, Parque Tropical - Maracanaú, CE10. CONDOMÍNIO: NÃO10. PONTO DE REFERÊNCIA:espaço lemos11. DISPONIBILIDADE: manhã12. OBSERVAÇÃO:
A82: 3844675 | B82: MARIA JACIARA MENDES COSMO | C82: Encerramento | D82: INSTALAÇÃO FIBRA - PF | E82: Rua | F82: Rua Santiago da Barra do Ceará | G82: 527 | H82: Fortaleza | I82: Barra do Ceará | J82: -36992973 | K82: -385837623 | L82: FRANCISCO JHONATA DA COSTA | M82: ALLYSTER MARQUES OLIVEIRA COSTA | N82: 46262 | O82: 46266 | P82: 46267 | Q82: 46267 | R82: Sim | S82: 1 | T82: Cliente Pessoa Física | U82: Instalação | X82: Troca Conector - Desgastado | AA82: OLT Barra do Ceará VLAN 1001 | AB82: *INSTALAÇÃO**Data* 02/09/2026*Técnico* Jhonata Costa CLIENTE:MARIA JACIARA MENDES COSMOENDERECO:Rua Santiago da Barra do Ceará, 527, Barra do Ceará - Fortaleza*Caixa:2316*Porta*:12*SINAL DA CAIXA*. -23*SINAL DO CLIENTE:-23*SERVICO REALIZADO*Instalação concluída com sucesso...ja tinha Drop Existente..*Material utilizado*02Conector Verde 00Conector Azul06Fixa fio00 Canaleta00 Esticador00Adesivo conector0 RJ4500 pat Cord01 ONT FIBERHOME *OBS* : Concluído okLogin:multipro Senha:multipro *VALOR* :*Cabo inicial*:*Cabo final* *Metragem* *Drop inicial*0000*Drop final* : 0000*Metragem**0000Dispositivo: samsung SM-A075MVersão do Android: 16Versão do V·Tasks: 5.9.206 Status alterado de Abertura para Encerramento | AC82: VENDEDOR: ALLYSTER MARQUES OLIVEIRA COSTAÁREA: PAP () CALL-CENTER (X ) LOJA ( ) TBR ( )TITULAR: MARIA JACIARA MENDES COSMOTELEFONE: 85921468790WHATSAPP:85921468790DISPONIBILIDADE: MANHA( ) TARDE ( ) DIA TODO (X)DATA: 31/08CIDADE E BAIRRO: Barra do Ceará, Fortaleza - CEPLANO: 500VALOR ORIGINAL DO PLANO: 99,99POSSUI DESCONTO DE PONTUALIDADE? SIM ( ) NÃO (X )SE SIM: D5 ( ) ou DNET - D10( )DESCONTO DE __ , SE PAGO ATÉ O VENCIMENTO POR 12 MESESTAXA INSTALAÇÃO: GRATISATENDIMENTO REGISTRADO:Google Drive ( ) Fortics ( ) Smart ( X)FIDELIDADE: (X ) SIM NÃO ( )CLIENTE DESEJA NOTA FISCAL: SIM ( ) NÃO (X )COORD:-3.6986679799700615, -38.5835895849634CAIXA: CX15167CASA DUPLEX ( ) CASA TERREA (X)QUANTOS E QUAIS APARELHOS CONECTADOS: 1 CELULAR 1 TVOBSERVAÇÃO ADICIONAL:Ativação do contrato: 174163---- Endereço de Instalação ----CEP: 60331-440Logradouro: Rua Santiago da Barra do CearáNúmero: 527Bairro: Barra do CearáEstado: CECidade: Fortaleza---- Serviços a serem ativados ----- 0422 - IFT - ULTRAINFO - 500MB
A83: 3844690 | B83: MARIA LUCIA FREITAS DE SOUSA | C83: Encerramento | D83: RETRABALHO INSTALAÇÃO - PF | E83: Rua | F83: R. Maria Alves | G83: 42 | H83: Pacatuba | I83: Alvorada | L83: ANTONIO RAFAEL ALEXANDRE DE SOUSA | M83: FELIPE MESSIAS ABREU DA SILVA | N83: 46262 | O83: 46263 | P83: 46266 | Q83: 46266 | R83: Sim | S83: 3 | T83: Cliente Pessoa Física | U83: Retrabalho | V83: Instalação | X83: Troca Conector - Desgastado | Y83: ANTONIO RAFAEL ALEXANDRE DE SOUSA | Z83: 3801829 | AA83: OLT Pacatuba VLAN 1003 | AB83: PENDÊNCIA TÉCNICAData: 01/09/2026Técnico: Rafael SousaCliente: MARIA LUCIA FREITAS DE SOUSAEndereço: R. Maria Alves, 42, Alvorada – PacatubaOcorrência:Cliente encontrava-se em LOS. Ao realizar a vistoria, foi identificado que a caixa estava sem os conectores. A cliente informou que havia funcionários públicos realizando limpeza do matagal próximo ao poste e que, logo após o serviço, ficou sem conexão.Procedimento realizado:Para normalizar o serviço, foi utilizada a sobra técnica da fibra e realizado o reparo com a instalação de um novo conector APC. Após a intervenção, o serviço foi normalizado e ficou funcionando corretamente.Material utilizado:- 01 conector APCStatus: Serviço normalizado e concluído.Dispositivo: samsung SM-A146MVersão do Android: 15Versão do V·Tasks: 5.9.211 Status alterado de Andamento para Encerramento | AC83: 28/08/2026 - 22:46 01. RELATO DO CLIENTE:Cliente relata estar sem internet / piscando vermelho no equipamento02. ANÁLISE SISTEMA (UNM): link loss03. ANÁLISE SISTEMA (VOALLE): offline04. TÉCNICO ULTIMO ATENDIMENTO (ADICIONAR TAMBÉM AO CHECKLIST FINAL): ANTONIO RAFAEL ALEXANDRE DE SOUSA05. EXTRATO COM QUEDAS: xxxx06. GERENCIAMENTO REM. HABILITADO: Verificar07. PROCEDIMENTO REALIZADO: Reboot da tomada08. POTÊNCIA: xxx09. CAIXA E PORTA: CX 3460 P-0210. CONTATO: (85)98559-4333 / (85)98583-360311. ENDEREÇO COMPLETO: Rua Pedro Cabral 4212. CONDOMÍNIO: NÃO13. PONTO DE REFERÊNCIA: Próximo ao posto mil14. DISPONIBILIDADE: Manhã15. OBSERVAÇÃO:
A84: 3844723 | B84: MARIA DA CONCEIÇÃO RIBEIRO GONDIM | C84: Encerramento | D84: DNET - PENDENCIA FIBRA - PF | E84: Rua | F84: Povoado da Capoeira | G84: SN | H84: Aquiraz | I84: Justiniano de Serpa | J84: -38578057 | K84: -385023146 | L84: CAIO VICTOR MONTEIRO DE OLIVEIRA | M84: MIRELLA GOMES DE ABREU | N84: 46263 | O84: 46264 | P84: 46266 | Q84: 46266 | R84: Sim | S84: 2 | T84: DNET - Cliente Pessoa Física | U84: DNET - Pendência | V84: DNET - LOS | W84: DNET - Fibra Sem Sinal / Luz Los Vermelha | X84: Troca Conector - Desgastado | AA84: OLT DNET TEMPORARIO | AB84: Abertura Solicitação para visita técnica no cliente, a pedido do mesmo.TÉCNICO : CAIO VICTOR CLIENTE : MARIA DA CONCEIÇÃO RIBEIRO GONDIMENDEREÇO CORRETO: Povoado da Capoeira, SN, Justiniano de Serpa - AquirazNº CAIXA: N º PORTA: VERIFICAÇÃO DE CX: SINAL DA CTO: SINAL DO CLIENTE: -23MATERIAL UTILIZADO*CONECTOR VERDE: 2CONECTOR AZUL: FIXA FIO: CANALETA: ESTICADOR: ADESIVO CONECTOR: RJ45: CABO DE REDE: EQUIPAMENTO UTILIZADO ONT (S/N) = ONU (S/N) = ROTEADOR (S/N) = DROP CABO INICIAL: DROP CABO FINAL: DROP METRAGEM: TEVE FATURAMENTO? VALOR (SE HOUVER) :SERVIÇO:Dispositivo: motorola moto g04sVersão do Android: 14Versão do V·Tasks: 5.9.211 Status alterado de Andamento para Encerramento | AC84: 29/08/2026 - 07:02 01. RELATO DO CLIENTE: Sem Sinal / Luz Los Vermelha02. ANÁLISE SISTEMA (UNM): não possível identificar03. ANÁLISE SISTEMA (VOALLE): off-line04. EXTRATO COM QUEDAS: X05. GERENCIAMENTO REM. HABILITADO: X06. PROCEDIMENTO REALIZADO: REBOOT e aberto visita07. POTÊNCIA: xxx08. CAIXA E PORTA: não possivel identificar08. CONTATO: 858805812109. ENDEREÇO COMPLETO: Povoado da Capoeira SN, Justiniano de Serpa10. CONDOMÍNIO:NÃO10. PONTO DE REFERÊNCIA: prox ao posto do tata11. DISPONIBILIDADE: TOTAL12. OBSERVAÇÃO:
A85: 3844779 | B85: VICTOR PAULO NUNES BEZERRA | C85: Encerramento | D85: RETRABALHO PENDÊNCIA - PF | E85: Rua | F85: R. Maria Marques | G85: 110 | H85: Fortaleza | I85: Jangurussu | J85: -38514498 | K85: -385202848 | L85: DANILO OLIVEIRA DE SOUSA | M85: LUANA IASMIM DE SOUZA OLIVEIRA | N85: 46263 | O85: 46263 | P85: 46267 | Q85: 46267 | R85: Sim | S85: 4 | T85: Cliente Pessoa Física | U85: Retrabalho | V85: LOS | W85: Fibra Sem Sinal / Luz Los Vermelha | X85: Troca Conector - Desgastado | Y85: DANILO OLIVEIRA DE SOUSA | Z85: 3835531 | AA85: OLT Conj. Palmeiras VLAN 1002 | AB85: ♦️ *prdencia* ♦️*Chegada:* *Saída:* *Data:* 02/09/26*Atendente Responsável:* *Técnico:* Danilo*Cliente* VICTOR PAULO NUNES BEZERRA*Endereço* Rua Maria Marques *Potência da caixa:* - *Potência do cliente:*-23*Caixa**Porta* *Serviço Realizado**Material Utilizado* cliente com acesso normalizado após manutenção da infraestrutura verificado acesso -23*Valor* *Drop inicial* *Drop final:* *Metragem Total:* *Cabo de rede:* *Classificação de Encerramento:* ResolvidoDispositivo: motorola moto g04sVersão do Android: 14Versão do V·Tasks: 5.9.213 Status alterado de Tratamento Infra para Encerramento | AC85: 29/08/2026 - 09:02 01. RELATO DO CLIENTE: Sem internet novamente, LED vermelho no equipamento.02. ANÁLISE SISTEMA (UNM): Linkloss03. ANÁLISE SISTEMA (VOALLE): Offline04. TÉCNICO ULTIMO ATENDIMENTO (ADICIONAR TAMBÉM AO CHECKLIST FINAL): DANILO OLIVEIRA DE SOUSA05. EXTRATO COM QUEDAS: *06. GERENCIAMENTO REM. HABILITADO: Verificar07. PROCEDIMENTO REALIZADO: *08. POTÊNCIA: *09. CAIXA E PORTA: CX7185 P0110. CONTATO: (85) 9 8725-1303 - (85) 9 9112-869411. ENDEREÇO COMPLETO: R. Maria Marques, 110 - Jangurussu - Fortaleza - CE - CEP 60877-08512. CONDOMÍNIO: NÃO 13. PONTO DE REFERÊNCIA: Próximo ao mercadinho 3 irmãos14. DISPONIBILIDADE: Dia todo15. OBSERVAÇÃO:
